Workbook
Name High: [2]Source!$P$42:$P$43
Name High: Source!$P$42:$P$43
Name Low: [2]Source!$L$42
Name Low: Source!$L$42
Name Low_To_Moderate: [3]Source!$M$42:$M$43
Name LowToModerate: Source!$M$42:$M$43
Name Moderate: [2]Source!$N$42
Name Moderate: Source!$N$42
Name Moderate_To_High: [3]Source!$O$42:$O$43
Name ModerateToHigh: Source!$O$42:$O$43

Sheet Halaman Judul
E1: LAMPIRAN
E2: KEPUTUSAN DEPUTI BIDANG KEUANGAN DAN MANAJEMEN RISIKO
E3: NOMOR : | F3: SK-6/DKU.MBU/10/2023
E4: TENTANG: | F4: PETUNJUK TEKNIS PROSES MANAJEMEN RISIKO DAN AGREGASI PADA TAKSONOMI RISIKO PORTOFOLIO BADAN USAHA MILIK NEGARA
E5: TANGGAL : | F5: 26 OKTOBER 2023
E9: FORMAT PENYUSUNAN PERENCANAAN
E10: MANAJEMEN RISIKO
E11: BADAN USAHA MILIK NEGARA
E28: KEMENTERIAN BUMN
E29: JALAN MEDAN MERDEKA SELATAN NO.13 JAKARTA 10110

Sheet Daftar Isi
A2: DAFTAR ISI
B4: 1 | C4: Format Metrik Strategi Risiko | L4: Lengkap
B5: 2 | C5: Format Pilihan Sasaran&Strategi Bisnis | L5: Belum Lengkap
B6: 3 | C6: Format Profil Risiko
B7: 4 | C7: Format Risiko Inheren Kuantitatif
B8: 5 | C8: Format Risiko Inheren Kualitatif
B9: 6 | C9: Format Risiko Residual Kuantitatif
B10: 7 | C10: Format Risiko Residual Kualitatif
B11: 8 | C11: Format Rencana Perlakuan Risiko
B12: 9 | C12: Format Heatmap
B13: 10 | C13: Kriteria Dampak dan Probabilitas
B14: 11 | C14: Definisi Taksonomi Risiko
B15: 12 | C15: Petunjuk Pengisian Data Perencanaan Keuangan pada SIM KBUMN Melalui Platform Anaplan
B16: 13 | C16: Ilustrasi Contoh Perhitungan Ambang Batas Risiko dan Pola Integrasi Risiko

Sheet Metrik Strategi Risiko
A1: Kembali ke Daftar Isi
A2: Penerimaan Risiko Level Entitas/Korporate
A3: Data Item | B3: Nilai Kapasitas Risiko Perusahaan | C3: Nilai Selera Risiko Perusahaan | D3: Nilai Toleransi Risiko Perusahaan | E3: Nilai Batasan Risiko
A4: Jenis Data | B4: Nilai rupiah/mata uang fungsional pembukuan | C4: Nilai rupiah/mata uang fungsional pembukuan | D4: Nilai rupiah/mata uang fungsional pembukuan | E4: Nilai rupiah/mata uang fungsional pembukuan
A5: Petunjuk | B5: Diisi dengan nilai kapasitas risiko yang dimiliki oleh perusahaan. Kapasitas risiko perusahaan adalah maksimum nilai Risiko yang dapat ditanggung perusahaan berdasarkan modal, net working capital, likuiditas, total kemampuan pendanaan perusahaan, atau nilai batasan lainnya. | C5: Diisi dengan nilai selera risiko yang dihitung berdasarkan nilai batasan keseluruhan risiko yang bersedia diambil untuk mendapatkan hasil yang diharapkan. | D5: Diisi dengan nilai batasan risiko yang dapat ditoleransi dari nilai Selera Risiko yang bersedia diambil. Nilai ini lebih besar dari nilai Selera Risiko. | E5: Diisi dengan nilai batasan risiko yang akan didistribusikan dan menjadi acuan bagi unit pemilik risiko.
A6: Notes | B6: (satuan dalam rupiah/mata uang fungsional pembukuan). | C6: (satuan dalam rupiah/mata uang fungsional pembukuan). | D6: (satuan dalam rupiah/mata uang fungsional pembukuan). | E6: (satuan dalam rupiah/mata uang fungsional pembukuan).
A7: Start pengisian | B7: 5.02 | D7: =30.26%*B7 -> 1.519052 | E7: 0.36
A9: Metrik Strategi Risiko
A10: Data Item | B10: No. | C10: Nama BUMN | D10: Kode BUMN | E10: Kategori Risiko BUMN | F10: Kategori Risiko T2 & T3 KBUMN | G10: Risk Appetite Statement | H10: Sikap Terhadap Risiko | I10: Parameter | J10: Satuan Ukuran | K10: Nilai Batasan/Limit
A11: Jenis Data | B11: Number | C11: Dropdown list | D11: Formula | E11: Free Text | F11: Dropdown list | G11: Free Text | H11: Dropdown List | I11: Free Text | J11: Free Text/Ratio/Number | K11: Number
A12: Petunjuk | D12: Kolom ini tidak perlu diisi. Akan diisi oleh Kementerian BUMN | E12: Diisi dengan taksonomi risiko yang berlaku pada masing-masing BUMN | F12: Diisi dengan pilihan kategori risiko Portofolio BUMN Kementerian BUMN berikut: 1. Risiko Fiskal - Dividen 2. Risiko Fiskal - PMN 3. Risiko Fiskal - Subsidi & Kompensasi 4. Risiko Kebijakan - SDM 5. Risiko Kebijakan - Sektoral 6. Risiko Komposisi - Konsentrasi Portofolio 7. Risiko Struktur - Struktur Korporasi 8. Risiko Restrukturisasi & Reorganisasi - Penggabungan, Pengambilalihan, Peleburan, Pemisahan, Pembubaran, Likuidasi, Kemitraan, dan Restrukturisasi 9. Risiko Industri Umum - Formulasi Strategis 10. Risiko Industri Umum - Pasar & Makroekonomi 11. Risiko Industri Umum - Keuangan 12. Risiko Industri Umum - Reputasi & Kepatuhan 13. Risiko Industri Umum - Proyek 14. Risiko Industri Umum - Teknologi & Keamanan Siber 15. Risiko Industri Umum - Sosial & Lingkungan 16. Risiko Industri Umum - Operasional 17. Risiko Industri Perbankan - Kredit 18. Risiko Industri Perbankan - Likuiditas 19. Risiko Industri Asuransi - Investasi 20. Risiko Industri Asuransi - Aktuarial 21. Risiko lainnya | G12: Diisikan dengan pernyataan selera risiko BUMN | H12: Diisikan dengan postur selera risiko atas suatu taksonomi risiko yang terdiri dari: 1. Tidak Toleran 2. Konservatif 3. Moderat 4. Strategis | I12: Diisi dengan parameter risiko yang mencerminkan pernyataan selera risiko BUMN. Apabila terdapat lebih dari satu parameter, maka parameter berikutnya ditambahkan pada row dibawahnya dan tidak diinput pada satu cell row yang sama dengan parameter sebelumnya. | J12: Diisikan dengan satuan ukuran atau nominal atas level selera risiko relevan yang dipilih | K12: Diisi dengan nilai batasan atas parameter yang telah ditetapkan. Nilai batasan ini tidak boleh dilanggar dan akan menjadi barometer penentu suatu sasaran dan strategi diterima dan menjadi usulan dalam rancangan RKAP.
A13: Notes | F13: - BUMN pada Industri Umum tidak boleh memetakan dalam kategori Risiko Industri Perbankan dan Asuransi - BUMN pada Industri perbankan & asuransi ikut memetakan dalam kategori risiko Industri Umum | I13: Contoh parameter: - Tingkat fraud; - Tingkat fatality; - Tingkat kegagalan inovasi; - Rasio biaya operasi; - Dan lain-lain. | J13: Contoh: - % - kali - dan lain-lain
A14: Start pengisian | B14: 1 | C14: PT Perusahaan Listrik Negara (Persero) | D14: =IFERROR(VLOOKUP(C14,Master!$D$2:$E$50,2,0),"") -> PLNA | E14: T4 | F14: 16. Risiko Industri Umum - Operasional | G14: PT PLN Batam memiliki CAUTIOUS appetite terhadap gangguan operasional yang mempengaruhi kualitas (power quality), keandalan (reliability), dan ketersediaan (availability) pasokan listrik dan aset perusahaan, dengan tetap mempertahankan efisiensi. | H14: Moderat | I14: Pemehuan
B15: 2 | C15: PT Perusahaan Listrik Negara (Persero) | D15: =IFERROR(VLOOKUP(C15,Master!$D$2:$E$50,2,0),"") -> PLNA | E15: T4 | F15: 16. Risiko Industri Umum - Operasional | G15: PT PLN Batam memiliki CAUTIOUS appetite terhadap gangguan operasional yang mempengaruhi kualitas (power quality), keandalan (reliability), dan ketersediaan (availability) pasokan listrik dan aset perusahaan, dengan tetap mempertahankan efisiensi. | H15: Moderat | I15: Pemehuan
B16: 1 | C16: PT Perusahaan Listrik Negara (Persero) | D16: =IFERROR(VLOOKUP(C16,Master!$D$2:$E$50,2,0),"") -> PLNA | E16: T4 | F16: 16. Risiko Industri Umum - Operasional | G16: PT PLN Batam memiliki CAUTIOUS appetite terhadap gangguan operasional yang mempengaruhi kualitas (power quality), keandalan (reliability), dan ketersediaan (availability) pasokan listrik dan aset perusahaan, dengan tetap mempertahankan efisiensi. | H16: Moderat | I16: Pemehuan

Sheet Pilihan Sasaran&Strategi Bisnis
A1: Kembali ke Daftar Isi
A2: Data Item | B2: No | C2: Pilihan Sasaran | D2: Pilihan Strategi | E2: Hasil yang diharapkan dapat diterima perusahaan | F2: Nilai Risiko Yang Akan Timbul | G2: Nilai limit risiko sesuai dengan parameter risiko dalam Metrik Strategi Risiko | H2: Keputusan Penetapan
A3: Jenis Data | B3: Number | C3: Free Text | D3: Free Text | E3: Free Text | F3: Free Text | G3: Free Text | H3: Dropdown list
A4: Petunjuk | C4: Diisi dengan berbagai pilihan sasaran yang menjadi dinamika dalam perencanaan penyusunan rancangan RKAP. | D4: Diisi dengan berbagai pilihan strategi yang menjadi dinamika dalam perencanaan penyusunan rancangan RKAP. | E4: Diisi dengan nilai kuantitatif dalam mata uang rupiah/mata uang fungsional pembukuan atas hasil yang diharapkan dari pelaksanaan sasaran dan strategi yang akan dijalankan pada tahun 2024. | F4: Diisi dengan nilai risiko yang akan timbul sebagai konsekuensi dari suatu sasaran dan strategi yang akan dijalankan. | G4: Diisi dengan batasan risiko / limit risiko sesuai dengan parameter risiko dalam metrik strategi risiko. | H4: Diisi dengan pilihan: - Lanjut: apabila sasaran dan strategi diterima menjadi sasaran dan strategi yang akan dijalankan dalam rancangan RKAP. - Tidak Lanjut: apabila sasaran dan strategi tidak dapat diterima dan tidak dapat dimasukkan dalam sasaran dan strategi yang akan dijalankan di dalam rancangan RKAP.
A5: Notes | C5: Sasaran adalah: tujuan yang akan dicapai meliputi tingkat pertumbuhan dan kesehatan perusahaan serta sasaran bidang/unit kegiatan secara kuantitatif dan spesifik setiap tahunnya. | D5: Strategi adalah cara yang digunakan untuk mencapai sasaran, meliputi strategi korporasi sesuai posisi perusahaan, strategi bisnis, dan strategi fungsional tiap bidang/unit kegiatan. | E5: (satuan dalam rupiah/mata uang fungsional pembukuan). | F5: (satuan dalam rupiah/mata uang fungsional pembukuan). | H5: - Keputusan pemilihan sasaran tersebut terdiri dari: (i) lanjut, apabila imbal hasil (return) yang akan diperoleh sebanding dengan risiko (risk) yang dapat diterima oleh perusahaan, dan (ii) tidak lanjut, apabila risiko (risk) di luar ambang yang dapat diterima oleh perusahaan walaupun imbal hasil (return) tinggi. - Dokumentasi seluruh hasil pemilihan sasaran baik lanjut maupun tidak lanjut dimuat dalam dokumen perencanaan strategis BUMN baik RJP atau RKAP.
A6: Contoh pengisian | C6: Peningkatan segmen korporasi dengan pertumbuhan 5% yang akan dijalankan melalui strategi: | E6: Tambahan penjualan Rp800 miliar | F6: Penurunan cashflow operasi Rp200 miliar | G6: Penurunan cashflow operasi, limitnya sampai dengan Rp500 miliar | H6: Lanjut
D7: 1. Pemberian diskon harga sampai dengan 10% bagi korporasi yang membeli lebih dari 10 ribu ton per bulan. | H7: Tidak Lanjut
D8: 2. Pelanggan korporasi baru diberikan fleksibilitas pembayaran sampai dengan 6 bulan. | H8: Lanjut
A9: Start pengisian
A10: Start pengisian | C10: Meningkatkan keandalan suply dan kualitas layanan | G10: Pencapaian Biaya Pokok Penjualan (BPP) Non MPP (Rp/kWh) Rp 1.453,13
D11: Implementasi program anti blackout | E11: Penurunan kejadian gangguan | G11: EBITDA terealisasi sesuai target Rp 1.617,69 Miliar | H11: Lanjut
G12: ROIC terelasasi seusai target 5,65%
G13: Pengendalian penggunaan Anggaran Investasi sesuai RKAP 2024
G14: Compliance (GCG, Zero Fatality, Kepatuhan K3L, SPI, Reporting, Busdev Alignment)
G15: Optimalisasi Penempatan Dana
G16: Ketersediaan Saldo Kas Minimal
G17: Pemenuhan Roadmap Perbaikan Penerapan Manajemen Risiko
G18: Pengendalian atas Pengaruh Fluktuasi Selisih Kurs dengan Melaksanakan Transaksi Lindung Nilai (Hedging)
G19: Kecepatan Tagihan Vendor
G20: Ketersediaan Pendanaan Pembangunan Pembangkit PLTGU 120 MW di Tahun 2024
G21: Human Capital Readiness (HCR) & Organizational Capital Readiness (OCR) dan Produktifitas Pegawai
G22: Tingkat Optimalisasi Kredit Pajak dan Pajak Masukan
D28: Penguatan sistem jaringan

Sheet SUMMARY
AO1: Target Risiko Residual | BY1: RENCANA PERLAKUAN RISIKO | CB1: RENCANA PERLAKUAN RISIKO
BU2: Data Item | BV2: No. | BW2: BUMN | BX2: Kode BUMN | BY2: No. Risiko | BZ2: No. Penyebab Risiko | CA2: Penyebab risiko | CB2: Opsi Perlakuan Risiko | CC2: Jenis Rencana Perlakuan Risiko | CD2: Rencana Perlakuan Risiko | CE2: Output Perlakuan Risiko | CF2: Biaya Perlakuan Risiko (Rp/Mata Uang Lain) | CG2: Pos Anggaran | CH2: PRK | CI2: Jenis Program Dalam RKAP | CJ2: PIC | CK2: Timeline (Bulan)
A3: Kembali ke Daftar Isi | AI3: 610000000000 | AJ3: Risk Limit PLN Batam Tahun 2026 | AL3: No. | AM3: No. Risiko | AN3: Peristiwa risiko | AO3: Nilai Dampak | AS3: Skala Dampak | AW3: Nilai Probabilitas | BA3: Skala Probabilitas | BE3: Eksposur Risiko | BI3: Skala Risiko | BM3: Level Risiko | CK3: 1 | CL3: =CK3+1 -> 2 | CM3: =CL3+1 -> 3 | CN3: =CM3+1 -> 4 | CO3: =CN3+1 -> 5 | CP3: =CO3+1 -> 6 | CQ3: =CP3+1 -> 7 | CR3: =CQ3+1 -> 8 | CS3: =CR3+1 -> 9 | ... CV3: =CU3+1 -> 12
A4: Data Item | B4: No. | C4: Nama BUMN | D4: AP/SH | E4: Bidang/Unit (Drop Down) | F4: Sasaran BUMN | G4: No KM/KPI Bidang/Unit | H4: Sasaran PLN BATAM (KM UNIT/BIDANG) (Dropdown) | I4: Sasaran KBUMN | J4: Taksonomi Risiko PLN (T3) | K4: Kategori Risiko T2 & T3 KBUMN | L4: No. Risiko | M4: Peristiwa Risiko | N4: Deskripsi Peristiwa risiko | O4: No. Penyebab Risiko (Huruf Abjad) | P4: Kode Penyebab risiko | Q4: Penyebab risiko | R4: Key Risk Indicators | S4: Unit Satuan KRI | T4: Kategori Threshold KRI | W4: Jenis Existing Control | X4: Existing Control | Y4: Penilaian Efektivitas Kontrol | Z4: Kategori Dampak | AA4: Deskripsi Dampak | AB4: Perkiraan Waktu Terpapar Risiko | AC4: Asumsi Perhitungan Dampak Kuantitatif / Penjelasan Dampak Kualitatif | AD4: Nilai Dampak | AF4: Skala Dampak | AG4: Nilai Probabilitas (Sesuai dengan Sheet Justifikasi) | AH4: Skala Probabilitas | AI4: Nilai Eksposur Risiko | AJ4: Skala Risiko | AK4: Level Nilai Risiko | AS4: BUMN | BA4: BUMN | BI4: BUMN | BM4: BUMN | BQ4: KBUMN | BU4: Jenis Data | BV4: Number | BW4: Dropdown list | BX4: Formula | BY4: Number | BZ4: Alphabet | CA4: Formula | CB4: Dropdown list | CC4: Multiple List | CD4: Free Text | CE4: Free Text | CF4: Nilai full mata uang dalam Rupiah/mata uang fungsional pembukuan | CG4: Dropdown List | CH4: Free Text | CI4: Dropdown List | CJ4: Free Text | CK4: Numerik (diisi nilai 1 jika mitgasi dilakukan pada bulan tertentu)
T5: Aman | U5: Hati-Hati | V5: Bahaya | AD5: TIDAK / WAJIB | AE5: Rupiah (Hasil Perhitungan dari sheet Justifikasi) | AF5: BUMN | AH5: BUMN | AJ5: BUMN | AK5: BUMN | AO5: Q1 | AP5: Q2 | AQ5: Q3 | AR5: Q4 | AS5: Q1 | AT5: Q2 | AU5: Q3 | AV5: Q4 | AW5: Q1 | AX5: Q2 | AY5: Q3 | AZ5: Q4 | BA5: Q1 | BB5: Q2 | BC5: Q3 | BD5: Q4 | BE5: Q1 | BF5: Q2 | BG5: Q3 | BH5: Q4 | BI5: Q1 | BJ5: Q2 | BK5: Q3 | BL5: Q4 | BM5: Q1 | BN5: Q2 | BO5: Q3 | BP5: Q4 | BQ5: Q1 | BR5: Q2 | BS5: Q3 | BT5: Q4 | BU5: Petunjuk | BY5: Kolom ini tidak perlu diisi. Akan diisi oleh Kementerian BUMN | BZ5: Diisi dengan nomor urutan penyebab risiko | CA5: Diisi dengan penyebab risiko yang ada pada tabel profil risiko | CB5: Diisi dengan pilihan: - Transfer/sharing - Reduce/mitigate - Accept/monitor - Avoid/hindari | CC5: Diisi dengan pilihan jenis rencana perlakuan risiko: - Peningkatan Kecukupan Desain Control - Peningkatan Efektivitas Pelaksanaan Control - Perbaikan Melalui Breakthrough Project - Lainnya | CD5: 1. Setiap perlakuan risiko di-break down dalam aktivitas-aktivitas yang lebih detail 2. [rule] Setiap unique ID penyebab risiko memiliki minimal 1 perlakuan risiko | CE5: Diisi dengan output atas masing-masing aktivitas rencana perlakuan risiko | CF5: Diisi dengan anggaran dalam pelaksanaan perlakuan risiko | CI5: Anggaran biaya perlakuan risiko telah dimasukkan dalam salah satu jenis program RKAP, dengan pilihan: - Pemasaran dan penjualan - Pengadaan - Produksi dan Kualitas Produk - Teknis dan Teknologi - Keuangan dan Akuntansi - Sistem dan Organisasi - Pengembangan SDM - Penelitian dan Pengembangan - Pelestarian Lingkungan - Investasi - Lainnya | CJ5: Unit penanggung jawab perlakuan risiko setingkat BOD | CK5: Terhadap masing-masing perlakuan risiko per penyebab risiko, agar diisi timeline rencana implementasinya. Apabila perlakuan risiko berlangsung sepanjang tahun, maka timeline harus diisi setiap bulan
A6: Jenis Data | B6: Number | C6: Dropdown list | D6: Number | E6: Drowdown | F6: Free Text | H6: Drowdown | J6: Dropdown list | K6: Dropdown list | L6: Number | M6: Free Text (Wajib Isi) | N6: Free Text (Wajib Isi) | O6: Alphabet | P6: Formula | Q6: Free Text | R6: Free Text/Ratio/Number | S6: Free Text/Ratio/Number | T6: Free Text/Ratio/Number | U6: Free Text/Ratio/Number | V6: Free Text/Ratio/Number | W6: Dropdown List | X6: Free Text | Y6: Dropdown list | Z6: Dropdown list | AA6: Free Text | AB6: Free Text | AC6: Free Text | AF6: Dropdown list | AG6: % | AH6: Dropdown list | AJ6: Skala 1-25 | AK6: Free Text | AO6: Nilai full mata uang dalam Rupiah/mata uang fungsional pembukuan | AS6: Dropdown list | AW6: % | BA6: Dropdown list | BE6: Nilai full mata uang dalam Rupiah/mata uang fungsional pembukuan | BI6: Skala 1-25 | BM6: Free Text | BQ6: Formula | BU6: Notes | CA6: Nama penyebab risiko harus sama persis dengan nama penyebab risiko yang ada pada tabel profil risiko | CC6: Pilihan dapat lebih dari satu | CD6: 1. Setiap penyebab risiko memiliki rencana perlakuan risiko. 2. Rencana perlakuan risiko harus spesifik dan tidak memungkinkan akan sama untuk menyelesaikan setiap penyebab. 3. Apabila satu perlakuan risiko dapat menyelesaikan lebih dari satu penyebab, artinya penyebab-penyebab tersebut belum diidentifikasi secara mendalam untuk mendapatkan akar penyebabnya.
A7: Petunjuk | E7: Kolom ini tidak perlu diisi. Akan diisi oleh Kementerian BUMN | F7: Diisi sesuai dengan sasaran BUMN | H7: Diisi sesuai dengan sasaran BUMN | J7: Diisi dengan pilihan sasaran Kementerian BUMN yang meliputi: 1) Nilai ekonomi dan sosial; 2) Inovasi bisnis model; 3) Kepemimpinan teknologi; 4) Peningkatan investasi; dan 5) Pengembangan talenta. | K7: Diisi dengan pilihan kategori risiko Portofolio BUMN Kementerian BUMN berikut: 1. Risiko Fiskal - Dividen 2. Risiko Fiskal - PMN 3. Risiko Fiskal - Subsidi & Kompensasi 4. Risiko Kebijakan - SDM 5. Risiko Kebijakan - Sektoral 6. Risiko Komposisi - Konsentrasi Portofolio 7. Risiko Struktur - Struktur Korporasi 8. Risiko Restrukturisasi & Reorganisasi - Penggabungan, Pengambilalihan, Peleburan, Pemisahan, Pembubaran, Likuidasi, Kemitraan, dan Restrukturisasi 9. Risiko Industri Umum - Formulasi Strategis 10. Risiko Industri Umum - Pasar & Makroekonomi 11. Risiko Industri Umum - Keuangan 12. Risiko Industri Umum - Reputasi & Kepatuhan 13. Risiko Industri Umum - Proyek 14. Risiko Industri Umum - Teknologi & Keamanan Siber 15. Risiko Industri Umum - Sosial & Lingkungan 16. Risiko Industri Umum - Operasional 17. Risiko Industri Perbankan - Kredit 18. Risiko Industri Perbankan - Likuiditas 19. Risiko Industri Asuransi - Investasi 20. Risiko Industri Asuransi - Aktuarial | L7: Diisi dengan nomor urutan risiko | M7: Diisi dengan peristiwa risiko yang relevan. | N7: Penjelasan /narasi atas peristiwa risiko | O7: Diisi dengan nomor urutan penyebab risiko | P7: Kodifikasi untuk penyebab risiko (Setiap penyebab risiko diberikan unique ID, misal PTPI - 1. xxx") | Q7: Diisi penyebab risiko secara jelas. BUMN dapat menggali berbagai penyebab risiko. Sebagai contoh dapat melihat dari berbagai segi: people, process, network, maupun system. | R7: Setiap peristiwa risiko harus memiliki minimal satu KRI | S7: Unit satuan KRI bisa berbentuk amount,/percentage/range/kualitatif | T7: Diisi sesuai dengan batasan yang ditetapkan oleh masing-masing BUMN | W7: Diisi dengan pilihan pada hirarki pertama: - Kontrol operasi - Kontrol kepatuhan (compliance) - Kontrol pelaporan Setelah hirarki pertama dipilih, dilanjutkan dengan pilihan hirarki kedua: - Kontrol pada level entitas/kantor pusat - Kontral pada level operasi | X7: BUMN dapat mengisikan semua existing control yang relevan terhadap suatu risiko. Existing control tersebut dapat berupa kontrol SOP, sistem, kebijakan, dll | Y7: Diisi dengan penilaian terhadap efektivitas kontrol saat ini (existing control) dengan pilihan sebagai berikut: 1) Cukup dan Efektif; 2) Cukup dan Efektif Sebagian; 3) Cukup dan Tidak Efektif; 4) Tidak Cukup dan Efektif Sebagian; dan 5) Tidak Cukup dan Tidak Efektif. | Z7: Diisi dengan pilihan kategori dampak: - Dampak kuantitatif - Dampak kualitatif | AA7: Disi dengan penjelasan/deskripsi atas dampak yang akan diterima apabila risiko terjadi. | AB7: Diisi dengan perkiraan periode waktu BUMN terpapar Risiko, sesuai dengan karakter Risiko tersebut. Perkiraan waktu diidentifikasi melalui proyeksi, data historis, maupun keumuman pada industri BUMN terkait
A8: Notes | F8: Sasaran disusun secara lengkap. Sebagai contoh: "Peningkatan market share segmen corporate dari 20% menjadi 30% pada akhir tahun 2024" | H8: Sasaran disusun secara lengkap. Sebagai contoh: "Peningkatan market share segmen corporate dari 20% menjadi 30% pada akhir tahun 2024" | K8: - Risiko pada Industri Umum tidak boleh dipetakan dalam kategori Risiko Industri Perbankan dan Asuransi - Risiko pada Industri perbankan & asuransi dapat dipetakan dalam kategori Risiko Industri Umum | L8: 1. Nomor risiko harus konsisten pada saat pelaporan. 2. Apabila terdapat risiko yang bertambah maka nomornya melanjutkan sesuai dengan urutan terakhir | M8: Risiko harus diidentifikasi dengan tepat, dan memenuhi ketentuan: - Bukan negasi sasaran - Dipetakan dalam fault tree analysis dan yang menjadi risk event yang paling mendekati dengan sumber utama penyebab risiko. | P8: Setiap penyebab kejadian diberikan unique ID | Q8: Jika satu Risiko memiliki lebih dari satu penyebab Risiko, maka dituliskan dalam cell di baris berikutnya (tidak digabung menjadi satu cell). | R8: Kriteria memilih KRI : 1. Penyebab risiko yang paling utama 2. Paling tersedia data historisnya & dapat diintegrasikan 3. Relevan terhadap penyebab masalah 4. Prediktor perubahan profil risiko 5. Mudah diinterpretasikan, dipahami & dipantau 6. Relatif terhadap keefektifan biaya | V8: ≤ | W8: Apabila jenis existing control memiliki lebih dari satu jenis control, maka dituliskan dalam cell di baris berikutnya (tidak digabung menjadi satu cell). | X8: Apabila existing control lebih dari 1, untuk control ke 2 dst agar ditambahkan pada row di bawahnya | Y8: (Dalam memilih lihat sheet"kriteria efektivitas kontrol") | Z8: 1) Dampak kuantitatif: Risiko yang memiliki dampak finansial terhadap pencapaian target laba BUMN. 2) Dampak kualitatif: Risiko yang tidak memiliki dampak finansial terhadap pencapaian target laba BUMN. | AB8: Periode waktu dapat berupa range bulan (contoh Januari 2023 – Februari 2024)
AF9: =AE13/AI3 -> 0.16825731 | AO9: =AO13/$AI$3 -> 0.16825731 | AP9: =AP13/$AI$3 -> 0.16825731 | AQ9: =AQ13/$AI$3 -> 0.16825731 | AR9: =AR13/$AI$3 -> 0.16825731
A10: Contoh | B10: 1 | C10: PT Perusahaan Listrik Negara (Persero) | D10: PLN BATAM | E10: BID KEU | G10: 1 | H10: Pencapaian Biaya Pokok Penjualan (BPP) Non MPP (Rp/kWh) Rp 1.453,13 | I10: 1. Nilai ekonomi dan sosial | J10: 3.6.11 Peristiwa Risiko terkait keuangan | K10: 4. Risiko Kebijakan - SDM | L10: 1 | M10: Kenaikan beban operasi akibat pelemahan nilai tukar rupiah terhadap dollar | N10: Terdapat beban operasi PLN Batam yang menggunakan mata uang asing dalam proses pembayaran atau mengacu atas besaran kurs rupiah terhadap dollar sebagai bagian perhitungan besaran tagihan | O10: a | P10: =CONCATENATE(E10,"-",L10,"-",O10) -> BID KEU-1-a | Q10: Faktor eksternal perusahaan seperti kondisi ekonomi politik dalam negeri dan atau luar negeri, dan tingkat kebutuhan pasar akan mata uang dollar | R10: Nilai tukar rupiah terhadap dollar | S10: Rupiah | T10: 13.438 Rp/USD | U10: 13.439 Rp/USD sd 16.874 Rp/USD | V10: > 16.875 Rp/USD | W10: Kontrol operasi - level operasi | X10: Memonitor nilai tukar rupiah terhadap dollar | Y10: 1. Cukup dan Efektif | Z10: Kuantitatif | AA10: D1. Terganggunya likuiditas perusahaan D2. Biaya melebihi target RKAP D3. Pembayaran pokok dan bunga lebih tinggi dari RKAP | AB10: Maret-Des 2024 | AC10: Dari nilai tukar rupiah terhadap kurs untuk pembayaran biaya operasional dan beban bunga perusahaan | AD10: =IF(Z10="KUANTITATIF","Wajib Isi","Tidak Wajib") -> Wajib Isi | AE10: 100000000 | AF10: 4 | AG10: 0.67 | AH10: 1 | AI10: =IF(Z10="kuantitatif",(AE10*AG10),(AF10*AH10*1%*$AI$3)) -> 67000000 | AJ10: =INDEX(Source!$E$33:$I$37,MATCH(AH10,Source!$D$33:$D$37,0),MATCH(AF10,Source!$E$38:$I$38,0)) -> 15 | AK10: =LOOKUP(MATCH(AJ10,'Perhitungan Heatmap'!$D$9:$AB$9),'Perhitungan Heatmap'!$D$9:$AB$9,'Perhitungan Heatmap'!$D$10:$AB$10) -> Moderate | AS10: 3 | AT10: 5 | AU10: 3 | AV10: 2 | BA10: 2 | BB10: 4 | BC10: 3 | BD10: 3 | BI10: =INDEX(Source!$E$33:$I$37,MATCH(BA10,Source!$D$33:$D$37,0),MATCH(AS10,Source!$E$38:$I$38,0)) -> 11 | BJ10: =INDEX(Source!$E$33:$I$37,MATCH(BB10,Source!$D$33:$D$37,0),MATCH(AT10,Source!$E$38:$I$38,0)) -> 24 | BK10: =INDEX(Source!$E$33:$I$37,MATCH(BC10,Source!$D$33:$D$37,0),MATCH(AU10,Source!$E$38:$I$38,0)) -> 13 | BL10: =INDEX(Source!$E$33:$I$37,MATCH(BD10,Source!$D$33:$D$37,0),MATCH(AV10,Source!$E$38:$I$38,0)) -> 8 | BM10: =LOOKUP(MATCH(BI10,'Perhitungan Heatmap'!$D$9:$AB$9),'Perhitungan Heatmap'!$D$9:$AB$9,'Perhitungan Heatmap'!$D$10:$AB$10) -> Low To Moderate | BN10: =LOOKUP(MATCH(BJ10,'Perhitungan Heatmap'!$D$9:$AB$9),'Perhitungan Heatmap'!$D$9:$AB$9,'Perhitungan Heatmap'!$D$10:$AB$10) -> High | BO10: =LOOKUP(MATCH(BK10,'Perhitungan Heatmap'!$D$9:$AB$9),'Perhitungan Heatmap'!$D$9:$AB$9,'Perhitungan Heatmap'!$D$10:$AB$10) -> Moderate | BP10: =LOOKUP(MATCH(BL10,'Perhitungan Heatmap'!$D$9:$AB$9),'Perhitungan Heatmap'!$D$9:$AB$9,'Perhitungan Heatmap'!$D$10:$AB$10) -> Low To Moderate | BY10: =L10 -> 1 | BZ10: =O10 -> a | CA10: =Q10 -> Faktor eksternal perusahaan seperti kondisi ekonomi politik dalam negeri dan atau luar negeri, dan tingkat kebutuhan pasar akan mata uang dollar | CB10: Reduce/Mitigate | CC10: Peningkatan Efektivitas Pelaksanaan Control | CD10: 1. Kegiatan pemasaran menggunakan integrated marketing channel secara offline dan online 2. Mengakuisisi captive power 3. Melaksanakan akselerasi layanan pelanggan dan calon pelanggan potensial dengan upaya terobosan dalam percepatan nota kesepakatan, percepatan pembayaran dan percepatan penyalaan 4. Mendorong tambah daya bagi pelanggan retail (TR) yang jam nyala minimumnya ? 400-600 jam. | CE10: Jumlah program pemasaran | CF10: 292092000000 | CG10: Anggaran Kas Investasi | CI10: Pengadaan | CJ10: DIR AGA | CU10: 1 | CV10: 1
A11: Start Pengisian | B11: 1 | C11: PT Perusahaan Listrik Negara (Persero) | D11: PLN BATAM | E11: BID AGA | H11: Pendapatan Penjualan Tenaga Listrik TUL 309 PLN Batam sebesar Rp 7.951.21 Milyar | I11: 1. Nilai ekonomi dan sosial | J11: 3.6.16 Peristiwa Risiko terkait operasional | K11: 11. Risiko Industri Umum - Keuangan | L11: 1 | M11: Mundurnya atau batalnya aktivasi daya potensi pelanggan yang telah diperhitungkan dalam RKAP | N11: Terdapat permintaan penyambungan atau aktivasi daya dari calon pelanggan dan pelanggan dalam jumlah besar yang akan masuk ke Batam pada tahun 2026 sebesar 92,1 MVA, namun belum dapat dipastikan apakah calon pelanggan akan melakukan aktivasi sesuai rencana penyambungan dalam perjanjian dan lama berlangganan | O11: a | P11: =CONCATENATE(E11,"-",L11,"-",O11) -> BID AGA-1-a | Q11: Belum siapnya infrastruktur pelanggan | R11: Jumlah pendapatan TL | S11: Rupiah | T11: >7.951.21 Milyar | U11: 7.951.21 Milyar | V11: <7.951.21 Milyar | W11: Kontrol operasi - level operasi | X11: Cash War Room (CWR) | Y11: 1. Cukup dan Efektif | Z11: Kuantitatif | AA11: Pendapatan penjualan listrik di bawah target | AB11: Januari s.d Desember 2026 | AC11: Nilai Dampak dihitung dari proyeksi penjualan 2026 dan probability dihitung dari % calon pelanggan / pelanggan batal/mundur | AD11: =IF(Z11="KUANTITATIF","Wajib Isi","Tidak Wajib") -> Wajib Isi | AE11: ='Justifikasi Risk Assessment'!P40 -> 660636000000 | AF11: 5 | AG11: ='Justifikasi Risk Assessment'!D52 -> 0.6 | AH11: 4 | AI11: =IF(Z11="kuantitatif",(AE11*AG11),(AF11*AH11*1%*$AI$3)) -> 396381600000 | AJ11: =INDEX(Source!$E$33:$I$37,MATCH(AH11,Source!$D$33:$D$37,0),MATCH(AF11,Source!$E$38:$I$38,0)) -> 24 | AK11: =LOOKUP(MATCH(AJ11,'Perhitungan Heatmap'!$D$9:$AB$9),'Perhitungan Heatmap'!$D$9:$AB$9,'Perhitungan Heatmap'!$D$10:$AB$10) -> High | AO11: =AE11 -> 660636000000 | AP11: ='Justifikasi Risk Assessment'!R42 -> 585357000000 | AQ11: ='Justifikasi Risk Assessment'!S42 -> 410748000000 | AR11: ='Justifikasi Risk Assessment'!T42 -> 213579000000 | AS11: 5 | AT11: 5 | AU11: 4 | AV11: 2 | AW11: =AG11 -> 0.6 | AX11: =AW11*75% -> 0.45 | AY11: =AX11*75% -> 0.3375 | AZ11: =AY11*75% -> 0.253125 | BA11: 4 | BB11: 3 | BC11: 2 | BD11: 2 | BE11: =AO11*AW11 -> 396381600000 | BF11: =AP11*AX11 -> 2.6341065e+11 | BG11: =AQ11*AY11 -> 138627450000 | BH11: =AR11*AZ11 -> 54062184375 | BI11: =INDEX(Source!$E$33:$I$37,MATCH(BA11,Source!$D$33:$D$37,0),MATCH(AS11,Source!$E$38:$I$38,0)) -> 24 | BJ11: =INDEX(Source!$E$33:$I$37,MATCH(BB11,Source!$D$33:$D$37,0),MATCH(AT11,Source!$E$38:$I$38,0)) -> 23 | BK11: =INDEX(Source!$E$33:$I$37,MATCH(BC11,Source!$D$33:$D$37,0),MATCH(AU11,Source!$E$38:$I$38,0)) -> 16 | BL11: =INDEX(Source!$E$33:$I$37,MATCH(BD11,Source!$D$33:$D$37,0),MATCH(AV11,Source!$E$38:$I$38,0)) -> 6 | BM11: =LOOKUP(MATCH(BI11,'Perhitungan Heatmap'!$D$9:$AB$9),'Perhitungan Heatmap'!$D$9:$AB$9,'Perhitungan Heatmap'!$D$10:$AB$10) -> High | BN11: =LOOKUP(MATCH(BJ11,'Perhitungan Heatmap'!$D$9:$AB$9),'Perhitungan Heatmap'!$D$9:$AB$9,'Perhitungan Heatmap'!$D$10:$AB$10) -> High | BO11: =LOOKUP(MATCH(BK11,'Perhitungan Heatmap'!$D$9:$AB$9),'Perhitungan Heatmap'!$D$9:$AB$9,'Perhitungan Heatmap'!$D$10:$AB$10) -> Moderate To High | BP11: =LOOKUP(MATCH(BL11,'Perhitungan Heatmap'!$D$9:$AB$9),'Perhitungan Heatmap'!$D$9:$AB$9,'Perhitungan Heatmap'!$D$10:$AB$10) -> Low To Moderate | CB11: Reduce/Mitigate | CC11: Peningkatan Efektivitas Pelaksanaan Control | CD11: 1. Penagihan e-min sebesar 50 jam nyala sesuai tahapan aktivasi daya | CE11: Surat penagihan e-min kepada calon pelanggan | CJ11: VP AGA | CK11: 1 | CL11: 1 | CM11: 1 | CN11: 1 | CO11: 1 | CP11: 1 | CQ11: 1 | CR11: 1 | CS11: 1 | CT11: 1 | CU11: 1 | CV11: 1
B12: 2 | C12: PT Perusahaan Listrik Negara (Persero) | D12: PLN BATAM | E12: BID AGA | H12: Optimalisasi Biaya Operasi | I12: 1. Nilai ekonomi dan sosial | J12: 3.6.11 Peristiwa Risiko terkait keuangan | K12: 11. Risiko Industri Umum - Keuangan | L12: 2 | M12: Realisasi Biaya Operasi melampaui Pagu anggaran yang ditetapkan dalam RKAP | N12: Terdapat penambahan program layanan yang belum direncanakan pada saat penyusunan Anggaran Operasi, sehingga menimbulkan penambahan kebutuhan Anggaran Operasi | O12: a | P12: =CONCATENATE(E12,"-",L12,"-",O12) -> BID AGA-2-a | Q12: Adanya program pemasaran/produk layanan baru yang belum direncanakan dan masuk dalam RKAP | R12: Realisasi SKAO | S12: % | T12: <100% | U12: 1 | V12: >100% | W12: Kontrol operasi - level operasi | X12: SK Pengadaan Barang dan Jasa SK Pengendalian Anggaran | Y12: 1. Cukup dan Efektif | Z12: Kuantitatif | AA12: Biaya Operasi melebihi pagu anggaran | AB12: Juli s.d Desember 2026 | AC12: Nilai Dampak dan probabilitas diambil dari nilai tengah atau rata-rata selisih AO selama 2021-2025 | AD12: =IF(Z12="KUANTITATIF","Wajib Isi","Tidak Wajib") -> Wajib Isi | AE12: ='Justifikasi Risk Assessment'!G65 -> 3600000000 | AF12: 1 | AG12: ='Justifikasi Risk Assessment'!J60 -> 0.2 | AH12: 2 | AI12: =IF(Z12="kuantitatif",(AE12*AG12),(AF12*AH12*1%*$AI$3)) -> 720000000 | AJ12: =INDEX(Source!$E$33:$I$37,MATCH(AH12,Source!$D$33:$D$37,0),MATCH(AF12,Source!$E$38:$I$38,0)) -> 2 | AK12: =LOOKUP(MATCH(AJ12,'Perhitungan Heatmap'!$D$9:$AB$9),'Perhitungan Heatmap'!$D$9:$AB$9,'Perhitungan Heatmap'!$D$10:$AB$10) -> Low | AO12: =AE12 -> 3600000000 | AP12: =AO12*75% -> 2700000000 | AQ12: =AO12*50% -> 1800000000 | AR12: =AO12*25% -> 900000000 | AS12: 1 | AT12: 1 | AU12: 1 | AV12: 1 | AW12: =AG12 -> 0.2 | AX12: =AW12*75% -> 0.15 | AY12: =AX12*75% -> 0.1125 | AZ12: =AY12*75% -> 0.084375 | BA12: 2 | BB12: 2 | BC12: 2 | BD12: 1 | BE12: =AO12*AW12 -> 720000000 | BF12: =AP12*AX12 -> 4.05e+08 | BG12: =AQ12*AY12 -> 2.025e+08 | BH12: =AR12*AZ12 -> 75937500 | BI12: =INDEX(Source!$E$33:$I$37,MATCH(BA12,Source!$D$33:$D$37,0),MATCH(AS12,Source!$E$38:$I$38,0)) -> 2 | BJ12: =INDEX(Source!$E$33:$I$37,MATCH(BB12,Source!$D$33:$D$37,0),MATCH(AT12,Source!$E$38:$I$38,0)) -> 2 | BK12: =INDEX(Source!$E$33:$I$37,MATCH(BC12,Source!$D$33:$D$37,0),MATCH(AU12,Source!$E$38:$I$38,0)) -> 2 | BL12: =INDEX(Source!$E$33:$I$37,MATCH(BD12,Source!$D$33:$D$37,0),MATCH(AV12,Source!$E$38:$I$38,0)) -> 1 | BM12: =LOOKUP(MATCH(BI12,'Perhitungan Heatmap'!$D$9:$AB$9),'Perhitungan Heatmap'!$D$9:$AB$9,'Perhitungan Heatmap'!$D$10:$AB$10) -> Low | BN12: =LOOKUP(MATCH(BJ12,'Perhitungan Heatmap'!$D$9:$AB$9),'Perhitungan Heatmap'!$D$9:$AB$9,'Perhitungan Heatmap'!$D$10:$AB$10) -> Low | BO12: =LOOKUP(MATCH(BK12,'Perhitungan Heatmap'!$D$9:$AB$9),'Perhitungan Heatmap'!$D$9:$AB$9,'Perhitungan Heatmap'!$D$10:$AB$10) -> Low | BP12: =LOOKUP(MATCH(BL12,'Perhitungan Heatmap'!$D$9:$AB$9),'Perhitungan Heatmap'!$D$9:$AB$9,'Perhitungan Heatmap'!$D$10:$AB$10) -> Low | CB12: Accept/Monitor | CC12: Peningkatan Efektivitas Pelaksanaan Control | CD12: 1. Memastikan penggunaan anggaran operasi sesuai dengan program kerja yang telah ditetapkan. 2. Melakukan monitoring penggunaan anggaran operasi setiap bulannya 3. Melakukan evaluasi atas rencana penggunaan anggaran operasi dengan memperhatikan tingkat urgensi | CE12: Daftar Produk Layanan beserta anggaran | CI12: Pemasaran dan penjualan | CJ12: VP AGA | CK12: 1 | CL12: 1 | CM12: 1 | CN12: 1 | CO12: 1 | CP12: 1 | CQ12: 1 | CR12: 1 | CS12: 1 | CT12: 1 | CU12: 1 | CV12: 1
B13: 3 | C13: PT Perusahaan Listrik Negara (Persero) | D13: PLN BATAM | E13: BID AGA | H13: Periode Pengumpulan Piutang (Collection Period) | I13: 1. Nilai ekonomi dan sosial | J13: 3.6.11 Peristiwa Risiko terkait keuangan | K13: 11. Risiko Industri Umum - Keuangan | L13: 3 | M13: Keterlambatan Pembayaran tagihan interkoneksi | N13: Dalam kurun waktu tahun 2023 sampai dengan 2025 realisasi keterlambatan Penerimaan Pembayaran Tagihan Interkoneksi Bintan, Sembulang, Belakang Padang dan Buluh lebih dari 35 adalah sebanyak 16 bulan dari 36 bulan | O13: a | P13: =CONCATENATE(E13,"-",L13,"-",O13) -> BID AGA-3-a | Q13: Dokumen penagihan terlambat di submit pada aplikasi Vendor Invoice Portal (VIP), dikarenakan SKAO PLN UID RKR belum terbit | R13: Realisasi Periode Pengumpulan Piutang | S13: hari kalender | T13: <35 hari | U13: 35 hari | V13: >35 hari | W13: Kontrol operasi - level operasi | X13: PJBTL Interkoneksi antara PLN UID RKR dengan PLN Batam | Y13: 2. Cukup dan Efektif Sebagian | Z13: Kuantitatif | AA13: Realisasi atas Penerimaan Pendapatan Interkoneksi tidak sesuai dengan target penerimaan | AB13: Januari s.d Desember 2026 | AC13: Rata-rata keterlambatan penerimaan arus kas | AD13: =IF(Z13="KUANTITATIF","Wajib Isi","Tidak Wajib") -> Wajib Isi | AE13: ='Justifikasi Risk Assessment'!H89 -> 1.0263696e+11 | AF13: 1 | AG13: ='Justifikasi Risk Assessment'!H90 -> 0.44444444 | AH13: 3 | AI13: =IF(Z13="kuantitatif",(AE13*AG13),(AF13*AH13*1%*$AI$3)) -> 4.5616425e+10 | AJ13: =INDEX(Source!$E$33:$I$37,MATCH(AH13,Source!$D$33:$D$37,0),MATCH(AF13,Source!$E$38:$I$38,0)) -> 3 | AK13: =LOOKUP(MATCH(AJ13,'Perhitungan Heatmap'!$D$9:$AB$9),'Perhitungan Heatmap'!$D$9:$AB$9,'Perhitungan Heatmap'!$D$10:$AB$10) -> Low | AO13: =AE13 -> 1.0263696e+11 | AP13: =AO13 -> 1.0263696e+11 | AQ13: =AP13 -> 1.0263696e+11 | AR13: =AQ13 -> 1.0263696e+11 | AS13: 1 | AT13: 1 | AU13: 1 | AV13: 1 | AW13: =AG13 -> 0.44444444 | AX13: =AW13*75% -> 0.33333333 | AY13: =AX13*75% -> 0.25 | AZ13: =AY13*75% -> 0.1875 | BA13: 3 | BB13: 2 | BC13: 2 | BD13: 1 | BE13: =AO13*AW13 -> 4.5616425e+10 | BF13: =AP13*AX13 -> 3.4212319e+10 | BG13: =AQ13*AY13 -> 2.5659239e+10 | BH13: =AR13*AZ13 -> 1.9244429e+10 | BI13: =INDEX(Source!$E$33:$I$37,MATCH(BA13,Source!$D$33:$D$37,0),MATCH(AS13,Source!$E$38:$I$38,0)) -> 3 | BJ13: =INDEX(Source!$E$33:$I$37,MATCH(BB13,Source!$D$33:$D$37,0),MATCH(AT13,Source!$E$38:$I$38,0)) -> 2 | BK13: =INDEX(Source!$E$33:$I$37,MATCH(BC13,Source!$D$33:$D$37,0),MATCH(AU13,Source!$E$38:$I$38,0)) -> 2 | BL13: =INDEX(Source!$E$33:$I$37,MATCH(BD13,Source!$D$33:$D$37,0),MATCH(AV13,Source!$E$38:$I$38,0)) -> 1 | BM13: =LOOKUP(MATCH(BI13,'Perhitungan Heatmap'!$D$9:$AB$9),'Perhitungan Heatmap'!$D$9:$AB$9,'Perhitungan Heatmap'!$D$10:$AB$10) -> Low | BN13: =LOOKUP(MATCH(BJ13,'Perhitungan Heatmap'!$D$9:$AB$9),'Perhitungan Heatmap'!$D$9:$AB$9,'Perhitungan Heatmap'!$D$10:$AB$10) -> Low | BO13: =LOOKUP(MATCH(BK13,'Perhitungan Heatmap'!$D$9:$AB$9),'Perhitungan Heatmap'!$D$9:$AB$9,'Perhitungan Heatmap'!$D$10:$AB$10) -> Low | BP13: =LOOKUP(MATCH(BL13,'Perhitungan Heatmap'!$D$9:$AB$9),'Perhitungan Heatmap'!$D$9:$AB$9,'Perhitungan Heatmap'!$D$10:$AB$10) -> Low | CB13: Accept/Monitor | CC13: Peningkatan Efektivitas Pelaksanaan Control | CD13: 1. Memastikan pelaksanaan pembacaan meter tanggal 1 pukul 10 setiap bulannya. 2. Berkoordinasi dengan Bidang Operasi untuk Memastikan terbitnya Berita Acara penyaluran tenaga listrik 3. Koordinasi dengan pihak UID untuk memastikan kecapatan proses pembayaran 2. Membuat invoice penagihan dan memastikan bahwa invoice yang diterbitkan telah sesuai dan benar. 3. Mereview secara bertingkat mulai dari MAN REV dan VP AGA atas invoice penagihan dan lampirannya. 4. Melakukan pengiriman invoice tagihan via Pos 5. Menghubungi pihak RKR untuk memastikan invoice tagihan telah diterima 6. Melakukan sales call secara rutin dengan pihak RKR untuk memastikan pembayaran | CE13: 1. Invoice tagihan Penjualan Listrik ke RKR 2. Bukti koordinasi via email, atau WA atau media lain. | CF13: 50000000 | CJ13: VP AGA | CK13: 1 | CL13: 1 | CM13: 1 | CN13: 1 | CO13: 1 | CP13: 1 | CQ13: 1 | CR13: 1 | CS13: 1 | CT13: 1 | CU13: 1 | CV13: 1
B14: 4 | C14: PT Perusahaan Listrik Negara (Persero) | D14: PLN BATAM | E14: BID AGA | H14: Penyediaan Tenaga Listrik Pelanggan Additional Demand | I14: 1. Nilai ekonomi dan sosial | J14: 3.6.11 Peristiwa Risiko terkait keuangan | K14: 16. Risiko Industri Umum - Operasional | L14: 4 | M14: Calon Pelanggan Additional Demand batal menjadi pelanggan | N14: Terdapat permintaan additional demand dari calon pelanggan dalam jumlah besar yang akan masuk ke Batam pada tahun 2026 sebesar 203,5 MVA., namun belum dapat dipastikan apakah calon pelanggan akan melakukan aktivasi sesuai rencana penyambungan dalam perjanjian dan lama berlangganan | O14: a | P14: =CONCATENATE(E14,"-",L14,"-",O14) -> BID AGA-4-a | Q14: 1. Tidak mencapai kesepakatan tarif dengan calon pelanggan 2. Calon pelanggan memilih investasi diluar Batam | R14: Penandatangan PJBTL/ Amandemen PJBTL | S14: % | T14: <100% | U14: 1 | V14: >100% | W14: Kontrol operasi - level operasi | X14: Penandatanganan PJBTL/Amandemen PJBTL dengan Pelanggan Add Demand | Y14: 2. Cukup dan Efektif Sebagian | Z14: Kuantitatif | AA14: Potensi tambahan pendapatan dari calon pelanggan additional demand tidak tercapai | AB14: September s.d Desember 2026 | AC14: Dihitung berdasarkan kapasitas pelanggan dikali jam nyala minimum, dikali tarif dikali durasi kontrak selama tahun 2026 | AD14: =IF(Z14="KUANTITATIF","Wajib Isi","Tidak Wajib") -> Wajib Isi | AE14: ='Justifikasi Risk Assessment'!P112 -> 254880000000 | AF14: 3 | AG14: ='Justifikasi Risk Assessment'!D124 -> 0.33333333 | AH14: 2 | AI14: =IF(Z14="kuantitatif",(AE14*AG14),(AF14*AH14*1%*$AI$3)) -> 84960000000 | AJ14: =INDEX(Source!$E$33:$I$37,MATCH(AH14,Source!$D$33:$D$37,0),MATCH(AF14,Source!$E$38:$I$38,0)) -> 11 | AK14: =LOOKUP(MATCH(AJ14,'Perhitungan Heatmap'!$D$9:$AB$9),'Perhitungan Heatmap'!$D$9:$AB$9,'Perhitungan Heatmap'!$D$10:$AB$10) -> Low To Moderate | AO14: ='Justifikasi Risk Assessment'!Q114 -> 254880000000 | AP14: ='Justifikasi Risk Assessment'!R114 -> 254880000000 | AQ14: ='Justifikasi Risk Assessment'!S114 -> 254880000000 | AR14: ='Justifikasi Risk Assessment'!T114 -> 191160000000 | AS14: 2 | AT14: 2 | AU14: 2 | AV14: 1 | AW14: =AG14 -> 0.33333333 | AX14: =AW14*75% -> 0.25 | AY14: =AW14*50% -> 0.16666667 | AZ14: =AW14*25% -> 0.083333333 | BA14: 2 | BB14: 1 | BC14: 1 | BD14: 1 | BE14: =AO14*AW14 -> 84960000000 | BF14: =AP14*AX14 -> 63720000000 | BG14: =AQ14*AY14 -> 42480000000 | BH14: =AR14*AZ14 -> 15930000000 | BI14: =INDEX(Source!$E$33:$I$37,MATCH(BA14,Source!$D$33:$D$37,0),MATCH(AS14,Source!$E$38:$I$38,0)) -> 6 | BJ14: =INDEX(Source!$E$33:$I$37,MATCH(BB14,Source!$D$33:$D$37,0),MATCH(AT14,Source!$E$38:$I$38,0)) -> 5 | BK14: =INDEX(Source!$E$33:$I$37,MATCH(BC14,Source!$D$33:$D$37,0),MATCH(AU14,Source!$E$38:$I$38,0)) -> 5 | BL14: =INDEX(Source!$E$33:$I$37,MATCH(BD14,Source!$D$33:$D$37,0),MATCH(AV14,Source!$E$38:$I$38,0)) -> 1 | BM14: =LOOKUP(MATCH(BI14,'Perhitungan Heatmap'!$D$9:$AB$9),'Perhitungan Heatmap'!$D$9:$AB$9,'Perhitungan Heatmap'!$D$10:$AB$10) -> Low To Moderate | BN14: =LOOKUP(MATCH(BJ14,'Perhitungan Heatmap'!$D$9:$AB$9),'Perhitungan Heatmap'!$D$9:$AB$9,'Perhitungan Heatmap'!$D$10:$AB$10) -> Low | BO14: =LOOKUP(MATCH(BK14,'Perhitungan Heatmap'!$D$9:$AB$9),'Perhitungan Heatmap'!$D$9:$AB$9,'Perhitungan Heatmap'!$D$10:$AB$10) -> Low | BP14: =LOOKUP(MATCH(BL14,'Perhitungan Heatmap'!$D$9:$AB$9),'Perhitungan Heatmap'!$D$9:$AB$9,'Perhitungan Heatmap'!$D$10:$AB$10) -> Low | BZ14: b. | CA14: ddddhhjjk | CB14: Accept/Monitor | CC14: Peningkatan Efektivitas Pelaksanaan Control | CD14: Probing ke Pelanggan Additional Demand & memastikan penandatanganan SPJBTL dan Amandemen dengan total daya 259,9 MVA | CE14: PJBTL / Amandemen PJBTL | CI14: Pemasaran dan penjualan | CJ14: VP AGA | CS14: 1 | CT14: 1 | CU14: 1 | CV14: 1
B15: 5 | C15: PT Perusahaan Listrik Negara (Persero) | D15: PLN BATAM | E15: BID AGA | H15: Harga Jual interkoneksi 150 kV Batam-Bintan dan 20 kV On-Grid | I15: 1. Nilai ekonomi dan sosial | J15: 3.6.11 Peristiwa Risiko terkait keuangan | K15: 16. Risiko Industri Umum - Operasional | L15: 5 | M15: Tidak disetujuinya persetujuan harga jual tenaga listrik interkoneksi oleh Menteri | N15: PLN Batam mengajukan perubahan harga jual tenaga listrik interkoneksi, dimana harga jual tenaga listrik saat ini menggunakan tarif tertinggi layanan khusus sebesar Rp 2.005/kWh berdasarkan penetapan TA TW III 2025. | O15: a | P15: =CONCATENATE(E15,"-",L15,"-",O15) -> BID AGA-5-a | Q15: Kajian dan analisis harga jual belum terinformasi secara komprehensive kepada Pejabat berwenang yang memberikan persetujuan Harga Jual | R15: Persetujuan Menteri terhadap Harga Jual Listrik Batam Bintan | S15: Bulan | T15: Mei | U15: Juni | V15: Juli | W15: Kontrol operasi - level entitas/kantor pusat | X15: Koordinasi dengan PLN UID RKR terkait proses persetujuan harga jual interkoneksi | Y15: 2. Cukup dan Efektif Sebagian | Z15: Kuantitatif | AA15: HJR Batam Bintan tidak tercapai | AB15: Januari s.d Desember 2026 | AC15: Delta HJR saat ini dengan HJR usulan dikali kwh jual | AD15: =IF(Z15="KUANTITATIF","Wajib Isi","Tidak Wajib") -> Wajib Isi | AE15: ='Justifikasi Risk Assessment'!O135 -> 7.9112115e+09 | AF15: 3 | AG15: ='Justifikasi Risk Assessment'!D139 -> 0.25 | AH15: 2 | AI15: =IF(Z15="kuantitatif",(AE15*AG15),(AF15*AH15*1%*$AI$3)) -> 1.9778029e+09 | AJ15: =INDEX(Source!$E$33:$I$37,MATCH(AH15,Source!$D$33:$D$37,0),MATCH(AF15,Source!$E$38:$I$38,0)) -> 11 | AK15: =LOOKUP(MATCH(AJ15,'Perhitungan Heatmap'!$D$9:$AB$9),'Perhitungan Heatmap'!$D$9:$AB$9,'Perhitungan Heatmap'!$D$10:$AB$10) -> Low To Moderate | AO15: ='Justifikasi Risk Assessment'!Q136 -> 7.9112115e+09 | AP15: ='Justifikasi Risk Assessment'!R136 -> 6.0335038e+09 | AQ15: ='Justifikasi Risk Assessment'!S136 -> 4.0587236e+09 | AR15: ='Justifikasi Risk Assessment'!T136 -> 2.0065139e+09 | AS15: 1 | AT15: 1 | AU15: 1 | AV15: 1 | AW15: =AG15 -> 0.25 | AX15: =AW15*75% -> 0.1875 | AY15: =AW15*50% -> 0.125 | AZ15: =AW15*25% -> 0.0625 | BA15: 3 | BB15: 2 | BC15: 2 | BD15: 1 | BE15: =AO15*AW15 -> 1.9778029e+09 | BF15: =AP15*AX15 -> 1.131282e+09 | BG15: =AQ15*AY15 -> 5.0734045e+08 | BH15: =AR15*AZ15 -> 1.2540712e+08 | BI15: 1 | BJ15: 1 | BK15: 1 | BL15: 1 | BM15: =LOOKUP(MATCH(BI15,'Perhitungan Heatmap'!$D$9:$AB$9),'Perhitungan Heatmap'!$D$9:$AB$9,'Perhitungan Heatmap'!$D$10:$AB$10) -> Low | BN15: =LOOKUP(MATCH(BJ15,'Perhitungan Heatmap'!$D$9:$AB$9),'Perhitungan Heatmap'!$D$9:$AB$9,'Perhitungan Heatmap'!$D$10:$AB$10) -> Low | BO15: =LOOKUP(MATCH(BK15,'Perhitungan Heatmap'!$D$9:$AB$9),'Perhitungan Heatmap'!$D$9:$AB$9,'Perhitungan Heatmap'!$D$10:$AB$10) -> Low | BP15: =LOOKUP(MATCH(BL15,'Perhitungan Heatmap'!$D$9:$AB$9),'Perhitungan Heatmap'!$D$9:$AB$9,'Perhitungan Heatmap'!$D$10:$AB$10) -> Low | CB15: Accept/Monitor | CC15: Peningkatan Efektivitas Pelaksanaan Control | CD15: 1. Koordinasi dengan PLN UID RKR, DIV DKI, DIV APR terkait KKP, Proses GRC dan surat permohonan persetujuan harga jual tenaga listrik dari PLN Persero 2. Koordinasi dengan DJK mengenai persetujuan harga jual tenaga listrik | CE15: Notulen rapat koordinasi pembahasan | CF15: 100000000 | CJ15: VP AGA | CK15: 1 | CL15: 1 | CM15: 1 | CN15: 1 | CO15: 1 | CP15: 1 | CQ15: 1
B16: 6 | C16: PT Perusahaan Listrik Negara (Persero) | D16: PLN BATAM | E16: BID AGA | H16: Indeks Kepuasan Pelanggan | I16: 1. Nilai ekonomi dan sosial | J16: 3.6.12 Peristiwa Risiko terkait hukum, reputasi, dan kepatuhan | K16: 12. Risiko Industri Umum - Reputasi & Kepatuhan | L16: 6 | M16: Target CSI tidak tercapai | N16: Realisasi Pencapaian Indeks Kepuasan Pelanggan sebesar 99,73% Tahun 2026 tidak tercapai | O16: a | P16: =CONCATENATE(E16,"-",L16,"-",O16) -> BID AGA-6-a | Q16: Keandalan pasokan listrik, sering terjadi Pemadaman. | R16: Indeks Kepuasan Pelanggan | S16: Skor | T16: >99,75% | U16: 0.9973 | V16: <99,73% | W16: Kontrol operasi - level operasi | X16: Evaluasi Realisasi Pencapaian TMP setiap Periodik dan melakukan Kompensasi bagi Pelanggan yang melewati TMP | Y16: 2. Cukup dan Efektif Sebagian | Z16: Kualitatif | AA16: Reputasi Perusahaan Menurun | AB16: Januari s.d Desember 2026 | AC16: Reputasi Perusahaan menurun akibat seringnya terjadi pemadaman | AD16: =IF(Z16="KUANTITATIF","Wajib Isi","Tidak Wajib") -> Tidak Wajib | AF16: 3 | AG16: ='Justifikasi Risk Assessment'!D152 -> 0.2 | AH16: 1 | AI16: =IF(Z16="kuantitatif",(AE16*AG16),(AF16*AH16*1%*$AI$3)) -> 18300000000 | AJ16: =INDEX(Source!$E$33:$I$37,MATCH(AH16,Source!$D$33:$D$37,0),MATCH(AF16,Source!$E$38:$I$38,0)) -> 10 | AK16: =LOOKUP(MATCH(AJ16,'Perhitungan Heatmap'!$D$9:$AB$9),'Perhitungan Heatmap'!$D$9:$AB$9,'Perhitungan Heatmap'!$D$10:$AB$10) -> Low To Moderate | AS16: 3 | AT16: 3 | AU16: 3 | AV16: 3 | AW16: 0.2 | AX16: 0.2 | AY16: 0.2 | AZ16: 0.2 | BA16: 2 | BB16: 2 | BC16: 2 | BD16: 2 | BE16: =AI16 -> 18300000000 | BF16: =BE16 -> 18300000000 | BG16: =BF16 -> 18300000000 | BH16: =BG16 -> 18300000000 | BI16: =INDEX(Source!$E$33:$I$37,MATCH(BA16,Source!$D$33:$D$37,0),MATCH(AS16,Source!$E$38:$I$38,0)) -> 11 | BJ16: =INDEX(Source!$E$33:$I$37,MATCH(BB16,Source!$D$33:$D$37,0),MATCH(AT16,Source!$E$38:$I$38,0)) -> 11 | BK16: =INDEX(Source!$E$33:$I$37,MATCH(BC16,Source!$D$33:$D$37,0),MATCH(AU16,Source!$E$38:$I$38,0)) -> 11 | BL16: =INDEX(Source!$E$33:$I$37,MATCH(BD16,Source!$D$33:$D$37,0),MATCH(AV16,Source!$E$38:$I$38,0)) -> 11 | BM16: =LOOKUP(MATCH(BI16,'Perhitungan Heatmap'!$D$9:$AB$9),'Perhitungan Heatmap'!$D$9:$AB$9,'Perhitungan Heatmap'!$D$10:$AB$10) -> Low To Moderate | BN16: =LOOKUP(MATCH(BJ16,'Perhitungan Heatmap'!$D$9:$AB$9),'Perhitungan Heatmap'!$D$9:$AB$9,'Perhitungan Heatmap'!$D$10:$AB$10) -> Low To Moderate | BO16: =LOOKUP(MATCH(BK16,'Perhitungan Heatmap'!$D$9:$AB$9),'Perhitungan Heatmap'!$D$9:$AB$9,'Perhitungan Heatmap'!$D$10:$AB$10) -> Low To Moderate | BP16: =LOOKUP(MATCH(BL16,'Perhitungan Heatmap'!$D$9:$AB$9),'Perhitungan Heatmap'!$D$9:$AB$9,'Perhitungan Heatmap'!$D$10:$AB$10) -> Low To Moderate | CB16: Reduce/Mitigate | CC16: Peningkatan Efektivitas Pelaksanaan Control | CD16: 1. Melakukan sosialisasi hasil SKP Tahun 2025. 2. Menindaklanjuti dan mengevaluasi action plan dan tindaklanjut hasil Survei Kepuasan Pelanggan (SKP) 2024 pada aplikasi CheSKP 3. Memetakan responden SKP 2026 4. Pelaksanaan SKP 2026 5. Melakukan koordinasi dengan pihak Surveyor dan Area Pelayanan terkait dengan rencana pelaksanaan SKP 6. Melakukan Pendampingan dalam proses pelaksanaan SKP 7. Melakukan Evaluasi Pelaksanaan SKP 8. Pemberian apresiasi pelanggan tercepat bayar | CE16: Tindaklanjut Action Plan SKP dalam aplikasi CheSKP | CF16: 400000000 | CJ16: VP AGA | CK16: 1 | CL16: 1 | CM16: 1 | CN16: 1 | CO16: 1 | CP16: 1 | CQ16: 1 | CR16: 1 | CS16: 1 | CT16: 1 | CU16: 1 | CV16: 1
B17: 7 | C17: PT Perusahaan Listrik Negara (Persero) | D17: PLN BATAM | E17: BID AGA | H17: Implementasi Roadmap Perbaikan Penerapan Manajemen Risiko SH/AP | I17: 2. Inovasi bisnis model | J17: 3.6.12 Peristiwa Risiko terkait hukum, reputasi, dan kepatuhan | K17: 12. Risiko Industri Umum - Reputasi & Kepatuhan | L17: 7 | M17: Nilai roadmap perbaikan risiko BID AGA tidak memenuhi target | N17: Nilai roadmap perbaikan risiko BID AGA tidak memenuhi target yang ditetapkan oleh Manajemen | O17: a | P17: =CONCATENATE(E17,"-",L17,"-",O17) -> BID AGA-7-a | Q17: Rsiko Bidang AGA belum dikelola dengan baik seperti belum ada sharing session, belum ada monitoring dan belum ada keterlibatan pimpinan dalam pengelolaan risiko | R17: Skor penerapan road map MR | S17: Skor | T17: 1 | U17: 0.99 | V17: <99% | W17: Kontrol kepatuhan (compliance) - level operasi | X17: Pununjukan Risk Officer untuk membantu memonitor pelaksanaan perbaikan road map MR | Y17: 2. Cukup dan Efektif Sebagian | Z17: Kualitatif | AA17: Tidak tercapai nilai road map MR | AB17: Januari s.d Desember 2026 | AC17: Deviasi nilai road map perbaikan MR antara target dan realisasi | AD17: =IF(Z17="KUANTITATIF","Wajib Isi","Tidak Wajib") -> Tidak Wajib | AF17: 1 | AG17: ='Justifikasi Risk Assessment'!F165 -> 0 | AH17: 1 | AI17: =IF(Z17="kuantitatif",(AE17*AG17),(AF17*AH17*1%*$AI$3)) -> 6100000000 | AJ17: =INDEX(Source!$E$33:$I$37,MATCH(AH17,Source!$D$33:$D$37,0),MATCH(AF17,Source!$E$38:$I$38,0)) -> 1 | AK17: =LOOKUP(MATCH(AJ17,'Perhitungan Heatmap'!$D$9:$AB$9),'Perhitungan Heatmap'!$D$9:$AB$9,'Perhitungan Heatmap'!$D$10:$AB$10) -> Low | AS17: 1 | AT17: 1 | AU17: 1 | AV17: 1 | AW17: 0.2 | AX17: 0.2 | AY17: 0.2 | AZ17: 0.2 | BA17: 1 | BB17: 1 | BC17: 1 | BD17: 1 | BE17: =AI17 -> 6100000000 | BF17: =BE17 -> 6100000000 | BG17: =BF17 -> 6100000000 | BH17: =BG17 -> 6100000000 | BI17: =INDEX(Source!$E$33:$I$37,MATCH(BA17,Source!$D$33:$D$37,0),MATCH(AS17,Source!$E$38:$I$38,0)) -> 1 | BJ17: =INDEX(Source!$E$33:$I$37,MATCH(BB17,Source!$D$33:$D$37,0),MATCH(AT17,Source!$E$38:$I$38,0)) -> 1 | BK17: =INDEX(Source!$E$33:$I$37,MATCH(BC17,Source!$D$33:$D$37,0),MATCH(AU17,Source!$E$38:$I$38,0)) -> 1 | BL17: =INDEX(Source!$E$33:$I$37,MATCH(BD17,Source!$D$33:$D$37,0),MATCH(AV17,Source!$E$38:$I$38,0)) -> 1 | BM17: =LOOKUP(MATCH(BI17,'Perhitungan Heatmap'!$D$9:$AB$9),'Perhitungan Heatmap'!$D$9:$AB$9,'Perhitungan Heatmap'!$D$10:$AB$10) -> Low | BN17: =LOOKUP(MATCH(BJ17,'Perhitungan Heatmap'!$D$9:$AB$9),'Perhitungan Heatmap'!$D$9:$AB$9,'Perhitungan Heatmap'!$D$10:$AB$10) -> Low | BO17: =LOOKUP(MATCH(BK17,'Perhitungan Heatmap'!$D$9:$AB$9),'Perhitungan Heatmap'!$D$9:$AB$9,'Perhitungan Heatmap'!$D$10:$AB$10) -> Low | BP17: =LOOKUP(MATCH(BL17,'Perhitungan Heatmap'!$D$9:$AB$9),'Perhitungan Heatmap'!$D$9:$AB$9,'Perhitungan Heatmap'!$D$10:$AB$10) -> Low | CB17: Accept/Monitor | CC17: Peningkatan Efektivitas Pelaksanaan Control | CD17: Pelaporan MR dan monitoring roadmap MR setiap bulan. | CE17: Laporan MR | CJ17: VP AGA | CL17: 1 | CM17: 1 | CN17: 1 | CO17: 1 | CP17: 1 | CQ17: 1 | CR17: 1 | CS17: 1 | CT17: 1 | CU17: 1 | CV17: 1
B18: 8 | C18: PT Perusahaan Listrik Negara (Persero) | D18: PLN BATAM | E18: BID AGA | H18: Kajian Biaya Penyambungan dan Tingkat Mutu Pelayanan | I18: 2. Inovasi bisnis model | J18: 3.6.16 Peristiwa Risiko terkait operasional | K18: 16. Risiko Industri Umum - Operasional | L18: 8 | M18: Keterlambatan tersedianya kajian BP dan TMP | N18: Kajian perubahan Biaya Penyambungan dan Tingkat Mutu Pelayanan belum tersedia pada waktu yang ditetapkan. | O18: a | P18: =CONCATENATE(E18,"-",L18,"-",O18) -> BID AGA-8-a | Q18: Milestone kajian Biaya Penyambungan dan Tingkat Mutu Pelayanan belum disusun | R18: Kajian BP dan TMP | S18: Bulan | T18: Oktober | U18: November | V18: Desember | W18: Kontrol operasi - level operasi | X18: Prosedur Evaluasi dan Pelapporan TMP | Y18: 2. Cukup dan Efektif Sebagian | Z18: Kualitatif | AA18: Tidak ada kajian / evaluasi BP dan TMP untuk menilai kelayakan BP dan TMPyang berjalan saat ini | AB18: Januari s.d Desember 2026 | AC18: Reputasi Perusahaan menurun akibat tidak adanya peningkatan Tingkat Mutu Pelayanan yang dirasakan pelanggan | AD18: =IF(Z18="KUANTITATIF","Wajib Isi","Tidak Wajib") -> Tidak Wajib | AF18: 1 | AG18: ='Justifikasi Risk Assessment'!D171 -> 20%% | AH18: 1 | AI18: =IF(Z18="kuantitatif",(AE18*AG18),(AF18*AH18*1%*$AI$3)) -> 6100000000 | AJ18: =INDEX(Source!$E$33:$I$37,MATCH(AH18,Source!$D$33:$D$37,0),MATCH(AF18,Source!$E$38:$I$38,0)) -> 1 | AK18: =LOOKUP(MATCH(AJ18,'Perhitungan Heatmap'!$D$9:$AB$9),'Perhitungan Heatmap'!$D$9:$AB$9,'Perhitungan Heatmap'!$D$10:$AB$10) -> Low | AS18: 3 | AT18: 3 | AU18: 3 | AV18: 3 | AW18: =AG18 -> 20%% | AX18: =AW18 -> 20%% | AY18: =AX18 -> 20%% | AZ18: =AY18 -> 20%% | BA18: 1 | BB18: 1 | BC18: 1 | BD18: 1 | BE18: =AI18 -> 6100000000 | BF18: =BE18 -> 6100000000 | BG18: =BF18 -> 6100000000 | BH18: =BG18 -> 6100000000 | BI18: =INDEX(Source!$E$33:$I$37,MATCH(BA18,Source!$D$33:$D$37,0),MATCH(AS18,Source!$E$38:$I$38,0)) -> 10 | BJ18: =INDEX(Source!$E$33:$I$37,MATCH(BB18,Source!$D$33:$D$37,0),MATCH(AT18,Source!$E$38:$I$38,0)) -> 10 | BK18: =INDEX(Source!$E$33:$I$37,MATCH(BC18,Source!$D$33:$D$37,0),MATCH(AU18,Source!$E$38:$I$38,0)) -> 10 | BL18: =INDEX(Source!$E$33:$I$37,MATCH(BD18,Source!$D$33:$D$37,0),MATCH(AV18,Source!$E$38:$I$38,0)) -> 10 | BM18: =LOOKUP(MATCH(BI18,'Perhitungan Heatmap'!$D$9:$AB$9),'Perhitungan Heatmap'!$D$9:$AB$9,'Perhitungan Heatmap'!$D$10:$AB$10) -> Low To Moderate | BN18: =LOOKUP(MATCH(BJ18,'Perhitungan Heatmap'!$D$9:$AB$9),'Perhitungan Heatmap'!$D$9:$AB$9,'Perhitungan Heatmap'!$D$10:$AB$10) -> Low To Moderate | BO18: =LOOKUP(MATCH(BK18,'Perhitungan Heatmap'!$D$9:$AB$9),'Perhitungan Heatmap'!$D$9:$AB$9,'Perhitungan Heatmap'!$D$10:$AB$10) -> Low To Moderate | BP18: =LOOKUP(MATCH(BL18,'Perhitungan Heatmap'!$D$9:$AB$9),'Perhitungan Heatmap'!$D$9:$AB$9,'Perhitungan Heatmap'!$D$10:$AB$10) -> Low To Moderate | CB18: Reduce/Mitigate | CC18: Peningkatan Efektivitas Pelaksanaan Control | CD18: 1. Menyusun dokumen pengadaan pada TW 2 2026 2. Koordinasi dengan konsultan eksternal | CE18: Dokumen Perjanjian Kerjasama dengan Konsultan | CF18: 2500000000 | CG18: Anggaran Operasi | CI18: Pengadaan | CJ18: VP AGA | CK18: 1 | CL18: 1 | CM18: 1 | CN18: 1 | CO18: 1 | CP18: 1 | CQ18: 1 | CR18: 1 | CS18: 1 | CT18: 1 | CU18: 1 | CV18: 1
B19: 9 | C19: PT Perusahaan Listrik Negara (Persero) | D19: PLN BATAM | E19: BID AGA | H19: Pengembangan Produk Layanan Niaga | I19: 3. Kepemimpinan teknologi | J19: 3.6.16 Peristiwa Risiko terkait operasional | K19: 16. Risiko Industri Umum - Operasional | L19: 9 | M19: Keterlambatan pengesahan produk layanan niaga yang baru | N19: Produk layanan niaga yang direncanakan 8 produk pada tahun 2026 terlambat disahkan Pejabat berwenang | O19: a | P19: =CONCATENATE(E19,"-",L19,"-",O19) -> BID AGA-9-a | Q19: Dokumen kajian produk layanan niaga terlambat disusun dan tidak dimonitor secara intensive | R19: Produk Layanan Niaga | S19: Produk | T19: >6 | U19: 6 | V19: <6 | W19: Kontrol operasi - level entitas/kantor pusat | X19: Prosedur Kebijakan dan Strategi Pemasaran | Y19: 2. Cukup dan Efektif Sebagian | Z19: Kuantitatif | AA19: Potensi kehilangan pendapatan bagi perusahaan | AB19: Desember 2026 | AC19: Delta Revenue dari produk layanan niaga | AD19: =IF(Z19="KUANTITATIF","Wajib Isi","Tidak Wajib") -> Wajib Isi | AE19: ='Justifikasi Risk Assessment'!D189 -> 1.0100404e+11 | AF19: 1 | AG19: ='Justifikasi Risk Assessment'!D191 -> 0 | AH19: 1 | AI19: =IF(Z19="kuantitatif",(AE19*AG19),(AF19*AH19*1%*$AI$3)) -> 0 | AJ19: =INDEX(Source!$E$33:$I$37,MATCH(AH19,Source!$D$33:$D$37,0),MATCH(AF19,Source!$E$38:$I$38,0)) -> 1 | AK19: =LOOKUP(MATCH(AJ19,'Perhitungan Heatmap'!$D$9:$AB$9),'Perhitungan Heatmap'!$D$9:$AB$9,'Perhitungan Heatmap'!$D$10:$AB$10) -> Low | AR19: ='Justifikasi Risk Assessment'!D189 -> 1.0100404e+11 | AS19: 1 | AT19: 1 | AU19: 1 | AV19: 1 | AW19: =AG19 -> 0 | AX19: =AW19 -> 0 | AY19: =AG19 -> 0 | AZ19: =AY19 -> 0 | BA19: 1 | BB19: 1 | BC19: 1 | BD19: 1 | BE19: =AO19*AW19 -> 0 | BF19: =AP19*AX19 -> 0 | BG19: =AQ19*AY19 -> 0 | BH19: =AR19*AZ19 -> 0 | BI19: =INDEX(Source!$E$33:$I$37,MATCH(BA19,Source!$D$33:$D$37,0),MATCH(AS19,Source!$E$38:$I$38,0)) -> 1 | BJ19: =INDEX(Source!$E$33:$I$37,MATCH(BB19,Source!$D$33:$D$37,0),MATCH(AT19,Source!$E$38:$I$38,0)) -> 1 | BK19: =INDEX(Source!$E$33:$I$37,MATCH(BC19,Source!$D$33:$D$37,0),MATCH(AU19,Source!$E$38:$I$38,0)) -> 1 | BL19: =INDEX(Source!$E$33:$I$37,MATCH(BD19,Source!$D$33:$D$37,0),MATCH(AV19,Source!$E$38:$I$38,0)) -> 1 | BM19: =LOOKUP(MATCH(BI19,'Perhitungan Heatmap'!$D$9:$AB$9),'Perhitungan Heatmap'!$D$9:$AB$9,'Perhitungan Heatmap'!$D$10:$AB$10) -> Low | BN19: =LOOKUP(MATCH(BJ19,'Perhitungan Heatmap'!$D$9:$AB$9),'Perhitungan Heatmap'!$D$9:$AB$9,'Perhitungan Heatmap'!$D$10:$AB$10) -> Low | BO19: =LOOKUP(MATCH(BK19,'Perhitungan Heatmap'!$D$9:$AB$9),'Perhitungan Heatmap'!$D$9:$AB$9,'Perhitungan Heatmap'!$D$10:$AB$10) -> Low | BP19: =LOOKUP(MATCH(BL19,'Perhitungan Heatmap'!$D$9:$AB$9),'Perhitungan Heatmap'!$D$9:$AB$9,'Perhitungan Heatmap'!$D$10:$AB$10) -> Low | CB19: Accept/Monitor | CC19: Peningkatan Efektivitas Pelaksanaan Control | CD19: 1. Menyusun Dokumen Manajemen Risiko (KKO, KKF, AR) 2. Menyusun draft Kebijakan Strategi Penjualan Peningkatan dan Pengendalian Penjualan Tenaga Listrik 3. Melakukan pembahasan secara intens dengan UB DISYAN, UB INFRA, BID MRK 4. Melakukan Strategi Pemasaran dengan paid media | CE19: 1. KKO, KKF, KR 2. Draft produk layanan niaga 3. Marketing tool program | CF19: 5883771685 | CJ19: VP AGA | CK19: 1 | CL19: 1 | CM19: 1 | CN19: 1 | CO19: 1 | CP19: 1 | CQ19: 1 | CR19: 1 | CS19: 1 | CT19: 1 | CU19: 1 | CV19: 1
B20: 10 | C20: PT Perusahaan Listrik Negara (Persero) | D20: PLN BATAM | E20: BID AGA | H20: Penyelesaian Tarif Tenaga Listrik baru PLN Batam sesuai tahapan/milestone | I20: 4. Peningkatan investasi | J20: 3.6.16 Peristiwa Risiko terkait operasional | K20: 16. Risiko Industri Umum - Operasional | L20: 10 | M20: Keterlambatan penyelesaian Tarif Tenaga Listrik Baru | N20: Penyelesaian tarif tenaga listrik baru tidak sesuai dengan milistone yang tekah ditetapkan (terlambat) | O20: a | P20: =CONCATENATE(E20,"-",L20,"-",O20) -> BID AGA-10-a | Q20: Tahapan penyelesaian tarif tenaga listrik baru sesuai milistone tidak dimonitor secara intens | R20: Persetujuan tarif tenaga listrik | S20: Bulan | T20: >Juli | U20: Juli | V20: <Juli | W20: Kontrol operasi - level entitas/kantor pusat | X20: Prosedur Usulan Tenaga Listrik | Y20: 2. Cukup dan Efektif Sebagian | Z20: Kuantitatif | AA20: Potensi kehilangan pendapatan bagi perusahaan | AB20: Juli s.d Desember 2026 | AC20: Delta revenue dari RKAP dengan realisais tarif baru | AD20: =IF(Z20="KUANTITATIF","Wajib Isi","Tidak Wajib") -> Wajib Isi | AE20: ='Justifikasi Risk Assessment'!P201 -> 2.9273971e+11 | AF20: 3 | AG20: ='Justifikasi Risk Assessment'!D203 -> 0.9 | AH20: 5 | AI20: =IF(Z20="kuantitatif",(AE20*AG20),(AF20*AH20*1%*$AI$3)) -> 2.6346574e+11 | AJ20: =INDEX(Source!$E$33:$I$37,MATCH(AH20,Source!$D$33:$D$37,0),MATCH(AF20,Source!$E$38:$I$38,0)) -> 17 | AK20: =LOOKUP(MATCH(AJ20,'Perhitungan Heatmap'!$D$9:$AB$9),'Perhitungan Heatmap'!$D$9:$AB$9,'Perhitungan Heatmap'!$D$10:$AB$10) -> Moderate To High | AO20: ='Justifikasi Risk Assessment'!Q203 -> 0 | AP20: ='Justifikasi Risk Assessment'!R203 -> 0 | AQ20: ='Justifikasi Risk Assessment'!S202 -> 2.9273971e+11 | AR20: ='Justifikasi Risk Assessment'!T202 -> 2.4402832e+11 | AU20: 3 | AV20: 3 | AY20: =AG20 -> 0.9 | AZ20: =AY20 -> 0.9 | BC20: 5 | BD20: 5 | BE20: =AO20*AW20 -> 0 | BF20: =AP20*AX20 -> 0 | BG20: =AQ20*AY20 -> 2.6346574e+11 | BH20: =AR20*AZ20 -> 2.1962549e+11 | BI20: =INDEX(Source!$E$33:$I$37,MATCH(BA20,Source!$D$33:$D$37,0),MATCH(AS20,Source!$E$38:$I$38,0)) -> #N/A | BJ20: =INDEX(Source!$E$33:$I$37,MATCH(BB20,Source!$D$33:$D$37,0),MATCH(AT20,Source!$E$38:$I$38,0)) -> #N/A | BK20: =INDEX(Source!$E$33:$I$37,MATCH(BC20,Source!$D$33:$D$37,0),MATCH(AU20,Source!$E$38:$I$38,0)) -> 17 | BL20: =INDEX(Source!$E$33:$I$37,MATCH(BD20,Source!$D$33:$D$37,0),MATCH(AV20,Source!$E$38:$I$38,0)) -> 17 | BM20: =LOOKUP(MATCH(BI20,'Perhitungan Heatmap'!$D$9:$AB$9),'Perhitungan Heatmap'!$D$9:$AB$9,'Perhitungan Heatmap'!$D$10:$AB$10) -> #N/A | BN20: =LOOKUP(MATCH(BJ20,'Perhitungan Heatmap'!$D$9:$AB$9),'Perhitungan Heatmap'!$D$9:$AB$9,'Perhitungan Heatmap'!$D$10:$AB$10) -> #N/A | BO20: =LOOKUP(MATCH(BK20,'Perhitungan Heatmap'!$D$9:$AB$9),'Perhitungan Heatmap'!$D$9:$AB$9,'Perhitungan Heatmap'!$D$10:$AB$10) -> Moderate To High | BP20: =LOOKUP(MATCH(BL20,'Perhitungan Heatmap'!$D$9:$AB$9),'Perhitungan Heatmap'!$D$9:$AB$9,'Perhitungan Heatmap'!$D$10:$AB$10) -> Moderate To High | CB20: Reduce/Mitigate | CC20: Peningkatan Efektivitas Pelaksanaan Control | CD20: 1. Diskusi intensif dengan LKFT UGM untuk pendampingan pembahasan dengan DJK 2. Koordinasi dengan DJK terkait data-data teknis pendukung usulan tarif tenaga listrik | CE20: Monitoring milistone usulan tarif tenaga listrik | CF20: 1716000000 | CJ20: VP AGA | CQ20: 1 | CR20: 1 | CS20: 1 | CT20: 1 | CU20: 1 | CV20: 1
B21: 11 | C21: PT Perusahaan Listrik Negara (Persero) | D21: PLN BATAM | E21: BID AGA | H21: Pengendalian Penggunaan Anggaran Investasi sesuai RKAP 2026 | I21: 4. Peningkatan investasi | J21: 3.6.16 Peristiwa Risiko terkait operasional | K21: 16. Risiko Industri Umum - Operasional | L21: 11 | M21: Penyerapan Investasi tidak optimal | N21: Realisasi penyerapan AKI lebih kecil dari penyerapan AKI seharusnya | O21: a | P21: =CONCATENATE(E21,"-",L21,"-",O21) -> BID AGA-11-a | Q21: Tidak dilakukan monitoring AKI | R21: Monitoring Penyerapan AKI | S21: % | T21: <100% | U21: 1 | V21: >100% | W21: Kontrol operasi - level operasi | X21: SK Pengadaan Barang dan Jasa SK Pengendalian Anggaran | Y21: 1. Cukup dan Efektif | Z21: Kuantitatif | AA21: Biaya Investasi melebihi pagu anggaran | AB21: Januari s.d Desember 2026 | AC21: Nilai Dampak dan probabilitas diambil dari nilai tengah atau rata-rata selisih AI selama 2021-2025 | AD21: =IF(Z21="KUANTITATIF","Wajib Isi","Tidak Wajib") -> Wajib Isi | AE21: ='Justifikasi Risk Assessment'!F214 -> 0 | AF21: 1 | AG21: ='Justifikasi Risk Assessment'!G214 -> 0 | AH21: 1 | AI21: =IF(Z21="kuantitatif",(AE21*AG21),(AF21*AH21*1%*$AI$3)) -> 0 | AJ21: =INDEX(Source!$E$33:$I$37,MATCH(AH21,Source!$D$33:$D$37,0),MATCH(AF21,Source!$E$38:$I$38,0)) -> 1 | AK21: =LOOKUP(MATCH(AJ21,'Perhitungan Heatmap'!$D$9:$AB$9),'Perhitungan Heatmap'!$D$9:$AB$9,'Perhitungan Heatmap'!$D$10:$AB$10) -> Low | AO21: =AE21 -> 0 | AP21: =AO21*75% -> 0 | AQ21: =AO21*50% -> 0 | AR21: =AO21*25% -> 0 | AS21: 1 | AT21: 1 | AU21: 1 | AV21: 1 | AW21: =AG21 -> 0 | AX21: =AW21*75% -> 0 | AY21: =AX21*75% -> 0 | AZ21: =AY21*75% -> 0 | BA21: 2 | BB21: 2 | BC21: 2 | BD21: 1 | BE21: =AO21*AW21 -> 0 | BF21: =AP21*AX21 -> 0 | BG21: =AQ21*AY21 -> 0 | BH21: =AR21*AZ21 -> 0 | BI21: 1 | BJ21: 1 | BK21: 1 | BL21: =INDEX(Source!$E$33:$I$37,MATCH(BD21,Source!$D$33:$D$37,0),MATCH(AV21,Source!$E$38:$I$38,0)) -> 1 | BM21: =LOOKUP(MATCH(BI21,'Perhitungan Heatmap'!$D$9:$AB$9),'Perhitungan Heatmap'!$D$9:$AB$9,'Perhitungan Heatmap'!$D$10:$AB$10) -> Low | BN21: =LOOKUP(MATCH(BJ21,'Perhitungan Heatmap'!$D$9:$AB$9),'Perhitungan Heatmap'!$D$9:$AB$9,'Perhitungan Heatmap'!$D$10:$AB$10) -> Low | BO21: =LOOKUP(MATCH(BK21,'Perhitungan Heatmap'!$D$9:$AB$9),'Perhitungan Heatmap'!$D$9:$AB$9,'Perhitungan Heatmap'!$D$10:$AB$10) -> Low | BP21: =LOOKUP(MATCH(BL21,'Perhitungan Heatmap'!$D$9:$AB$9),'Perhitungan Heatmap'!$D$9:$AB$9,'Perhitungan Heatmap'!$D$10:$AB$10) -> Low | CB21: Accept/Monitor | CC21: Peningkatan Efektivitas Pelaksanaan Control | CD21: 1. Memastikan penggunaan anggaran investasi sesuai dengan program kerja yang telah ditetapkan. 2. Melakukan monitoring penggunaan anggaran operasi setiap bulannya 3. Melakukan evaluasi atas rencana penggunaan anggaran operasi dengan memperhatikan tingkat urgensi | CE21: Daftar Produk Layanan beserta anggaran | CJ21: VP AGA | CK21: 1 | CL21: 1 | CM21: 1 | CN21: 1 | CO21: 1 | CP21: 1 | CQ21: 1 | CR21: 1 | CS21: 1 | CT21: 1 | CU21: 1 | CV21: 1
B22: 12 | C22: PT Perusahaan Listrik Negara (Persero) | D22: PLN BATAM | E22: BID AGA | H22: Human Capital Readiness (HCR) & Organizational Capital Readiness (OCR) dan Produktivitas Pegawai | I22: 5. Pengembangan talenta | J22: 3.6.12 Peristiwa Risiko terkait hukum, reputasi, dan kepatuhan | K22: 16. Risiko Industri Umum - Operasional | L22: 12 | M22: Target HCR OCR tidak tercapai | N22: Target pencapaian kinerja HCR OCR yang telah ditetapkan oleh HCGA tidak tercapai | O22: a | P22: =CONCATENATE(E22,"-",L22,"-",O22) -> BID AGA-12-a | Q22: Pimpinan dan PIC yang ditunjuk belum mengetahui dan memahami target HCR OCR denagn baik | R22: Nilai HCR OCR sesuai target | S22: % | T22: 1 | U22: 0.99 | V22: <99% | W22: Kontrol kepatuhan (compliance) - level entitas/kantor pusat | X22: Penunjukan PIC pengelola target HCR OCR | Y22: 1. Cukup dan Efektif | Z22: Kualitatif | AA22: Nilai HCR OCR Bidang Niaga tidak tercapai yang akan berpengaruh pada pencapaian nilai organisasi | AB22: Setiap Triwulan | AC22: Deviasi antara nilai target HCR OCR dengan realisasi | AD22: =IF(Z22="KUANTITATIF","Wajib Isi","Tidak Wajib") -> Tidak Wajib | AE22: ='Justifikasi Risk Assessment'!F215 -> 0 | AF22: 1 | AG22: ='Justifikasi Risk Assessment'!D233 -> 0 | AH22: 1 | AI22: =IF(Z22="kuantitatif",(AE22*AG22),(AF22*AH22*1%*$AI$3)) -> 6100000000 | AJ22: =INDEX(Source!$E$33:$I$37,MATCH(AH22,Source!$D$33:$D$37,0),MATCH(AF22,Source!$E$38:$I$38,0)) -> 1 | AK22: =LOOKUP(MATCH(AJ22,'Perhitungan Heatmap'!$D$9:$AB$9),'Perhitungan Heatmap'!$D$9:$AB$9,'Perhitungan Heatmap'!$D$10:$AB$10) -> Low | AO22: =AE22 -> 0 | AP22: =AO22*75% -> 0 | AQ22: =AO22*50% -> 0 | AR22: =AO22*25% -> 0 | AS22: 1 | AT22: 1 | AU22: 1 | AV22: 1 | AW22: =AG22 -> 0 | AX22: =AW22*75% -> 0 | AY22: =AX22*75% -> 0 | AZ22: =AY22*75% -> 0 | BA22: 2 | BB22: 2 | BC22: 2 | BD22: 1 | BE22: =AO22*AW22 -> 0 | BF22: =AP22*AX22 -> 0 | BG22: =AQ22*AY22 -> 0 | BH22: =AR22*AZ22 -> 0 | BI22: 1 | BJ22: 1 | BK22: 1 | BL22: =INDEX(Source!$E$33:$I$37,MATCH(BD22,Source!$D$33:$D$37,0),MATCH(AV22,Source!$E$38:$I$38,0)) -> 1 | BM22: =LOOKUP(MATCH(BI22,'Perhitungan Heatmap'!$D$9:$AB$9),'Perhitungan Heatmap'!$D$9:$AB$9,'Perhitungan Heatmap'!$D$10:$AB$10) -> Low | BN22: =LOOKUP(MATCH(BJ22,'Perhitungan Heatmap'!$D$9:$AB$9),'Perhitungan Heatmap'!$D$9:$AB$9,'Perhitungan Heatmap'!$D$10:$AB$10) -> Low | BO22: =LOOKUP(MATCH(BK22,'Perhitungan Heatmap'!$D$9:$AB$9),'Perhitungan Heatmap'!$D$9:$AB$9,'Perhitungan Heatmap'!$D$10:$AB$10) -> Low | BP22: =LOOKUP(MATCH(BL22,'Perhitungan Heatmap'!$D$9:$AB$9),'Perhitungan Heatmap'!$D$9:$AB$9,'Perhitungan Heatmap'!$D$10:$AB$10) -> Low | CB22: Accept/Monitor | CC22: Peningkatan Efektivitas Pelaksanaan Control | CD22: Melakiukan monitoring mingguan terhadap kegiatan pencapaian HCR OCR dan reminder oleh PIC | CE22: Daftar monitoring dan reminder | CJ22: VP AGA | CK22: 1 | CL22: 1 | CM22: 1 | CN22: 1 | CO22: 1 | CP22: 1 | CQ22: 1 | CR22: 1 | CS22: 1 | CT22: 1 | CU22: 1 | CV22: 1
B23: 13 | C23: PT Perusahaan Listrik Negara (Persero) | D23: PLN BATAM | E23: BID AGA | H23: Compliance (GCG, Kepatuhan HSSE, Auditor, Reporting, Busdev Alignment, PACA, Critical Events, ICOFR & SPIN) | I23: 6. Kepatuhan | J23: 3.6.12 Peristiwa Risiko terkait hukum, reputasi, dan kepatuhan | K23: 21. Risiko lainnya | L23: 13 | M23: Realisasi nilai compliance di bawah target | N23: Terdapat pengurang Nilai kinerja compliance | O23: a | P23: =CONCATENATE(E23,"-",L23,"-",O23) -> BID AGA-13-a | Q23: Tidak dimonitor oleh Pimpinan | R23: Nilai Compliance sesuai target | S23: % | T23: 1 | U23: 0.99 | V23: <99% | W23: Kontrol kepatuhan (compliance) - level operasi | X23: Review KM setiap periode | Y23: 1. Cukup dan Efektif | Z23: Kualitatif | AA23: Nilai compliance Bidang Niaga tidak tercapai | AB23: Januari s.d Desember 2026 | AC23: Deviasi nilai target dan realisasi | AD23: =IF(Z23="KUANTITATIF","Wajib Isi","Tidak Wajib") -> Tidak Wajib | AE23: ='Justifikasi Risk Assessment'!F216 -> 0 | AF23: 1 | AG23: ='Justifikasi Risk Assessment'!D246 -> 0 | AH23: 1 | AI23: =IF(Z23="kuantitatif",(AE23*AG23),(AF23*AH23*1%*$AI$3)) -> 6100000000 | AJ23: =INDEX(Source!$E$33:$I$37,MATCH(AH23,Source!$D$33:$D$37,0),MATCH(AF23,Source!$E$38:$I$38,0)) -> 1 | AK23: =LOOKUP(MATCH(AJ23,'Perhitungan Heatmap'!$D$9:$AB$9),'Perhitungan Heatmap'!$D$9:$AB$9,'Perhitungan Heatmap'!$D$10:$AB$10) -> Low | AO23: =AE23 -> 0 | AP23: =AO23*75% -> 0 | AQ23: =AO23*50% -> 0 | AR23: =AO23*25% -> 0 | AS23: 1 | AT23: 1 | AU23: 1 | AV23: 1 | AW23: =AG23 -> 0 | AX23: =AW23*75% -> 0 | AY23: =AX23*75% -> 0 | AZ23: =AY23*75% -> 0 | BA23: 2 | BB23: 2 | BC23: 2 | BD23: 1 | BE23: =AO23*AW23 -> 0 | BF23: =AP23*AX23 -> 0 | BG23: =AQ23*AY23 -> 0 | BH23: =AR23*AZ23 -> 0 | BI23: 1 | BJ23: 1 | BK23: 1 | BL23: =INDEX(Source!$E$33:$I$37,MATCH(BD23,Source!$D$33:$D$37,0),MATCH(AV23,Source!$E$38:$I$38,0)) -> 1 | BM23: =LOOKUP(MATCH(BI23,'Perhitungan Heatmap'!$D$9:$AB$9),'Perhitungan Heatmap'!$D$9:$AB$9,'Perhitungan Heatmap'!$D$10:$AB$10) -> Low | BN23: =LOOKUP(MATCH(BJ23,'Perhitungan Heatmap'!$D$9:$AB$9),'Perhitungan Heatmap'!$D$9:$AB$9,'Perhitungan Heatmap'!$D$10:$AB$10) -> Low | BO23: =LOOKUP(MATCH(BK23,'Perhitungan Heatmap'!$D$9:$AB$9),'Perhitungan Heatmap'!$D$9:$AB$9,'Perhitungan Heatmap'!$D$10:$AB$10) -> Low | BP23: =LOOKUP(MATCH(BL23,'Perhitungan Heatmap'!$D$9:$AB$9),'Perhitungan Heatmap'!$D$9:$AB$9,'Perhitungan Heatmap'!$D$10:$AB$10) -> Low | CB23: Accept/Monitor | CC23: Peningkatan Efektivitas Pelaksanaan Control | CD23: Monitoring oleh PIC dan reminder dari Penanggung jawab Bidang AGA | CE23: Monitoring dan reminder | CI23: Lainnya | CJ23: VP AGA | CK23: 1 | CL23: 1 | CM23: 1 | CN23: 1 | CO23: 1 | CP23: 1 | CQ23: 1 | CR23: 1 | CS23: 1 | CT23: 1 | CU23: 1 | CV23: 1
CF24: =SUM(CF12:CF23) -> 10649771685
CF25: =CF24-CF27 -> 0
CF27: =SUM(CF28:CF30) -> 10649771685
CF28: 8933771685
CF29: 1716000000

Sheet Justifikasi Risk Assessment
B2: Sheet ini berisi informasi setiap Risiko yang terdiri : 1. Data tabel berisi informasi penyebab risiko untuk setiap risiko utama (data 3-5 tahun terakhir) 2. Alasan memilih kriteria dampak kualitatif dan dilengkapi data
B9: 1 | C9: Risiko Mundurnya atau batalnya aktivasi daya potensi pelanggan yang telah diperhitungkan dalam RKAP
C10: Calon Pelanggan yang diperhitungkan dalam menghitung nilai dampak adalah pelanggan /calon pelanggan dengan kategori Confident Level Sedang, yang terdiri dari:
C11: PELANGGAN | D11: DAYA | F11: STATUS | G11: RENCANA NYALA 2026
C12: PT TAMAN RESOR INTERNET | D12: =D26-Z34 -> 40.6 | E12: MVA | F12: PJBTL | G12: Januari
C13: PT TEKNOLOGI DATA INFRASTRUKTUR | D13: =D27 -> 15 | E13: MVA | F13: PJBTL | G13: Januari
C14: PT PRIMA UTILITAS ENERGI II | D14: =F28 -> 16 | E14: MVA | F14: PJBTL | G14: Maret
C15: PT PRIMA UTILITAS ENERGI I | D15: =F29 -> 8.5 | E15: MVA | F15: PJBTL | G15: Maret
C16: PT ECOGREEN OLEOCHEMICAL | D16: =D30 -> 12 | E16: MVA | F16: PJBTL | G16: Januari
C17: JN Minimum - Diamond DC | D17: 200 | E17: Jam
C18: JN Minimum - Diamond PWU | D18: 200 | E18: Jam
C19: JN Minimum - Silver High | D19: 200 | E19: Jam
C20: Tarif Diamond DC | D20: 1800 | E20: Rp/kWh
C21: Tarif Diamond PWU | D21: 1650 | E21: Rp/kWh
C22: Tarif Silver High | D22: 1500 | E22: Rp/kWh
C24: Rencana aktivasi daya
C25: Pelanggan | D25: JAN | E25: FEB | F25: MAR | G25: APR | H25: MAY | I25: JUN | J25: JUL | K25: AUG | L25: SEP | M25: OCT | N25: NOV | O25: DEC
C26: PT TAMAN RESOR INTERNET | D26: 173.2 | E26: 173.2 | F26: 173.2 | G26: 245.2 | H26: 263.2 | I26: 263.2 | J26: 263.2 | K26: 280.2 | L26: 280.2 | M26: 280.2 | N26: 280.2 | O26: 280.2
C27: PT TEKNOLOGI DATA INFRASTRUKTUR | D27: 15 | E27: 15 | F27: 15 | G27: 15 | H27: 15 | I27: 15 | J27: 15 | K27: 15 | L27: 30 | M27: 30 | N27: 30 | O27: 30
C28: PT PRIMA UTILITAS ENERGI II | F28: 16 | G28: 16 | H28: 16 | I28: 16 | J28: 16 | K28: 16 | L28: 16 | M28: 16 | N28: 16 | O28: 16
C29: PT PRIMA UTILITAS ENERGI I | F29: 8.5 | G29: 8.5 | H29: 8.5 | I29: 8.5 | J29: 8.5 | K29: 8.5 | L29: 8.5 | M29: 8.5 | N29: 8.5 | O29: 8.5
C30: PT ECOGREEN OLEOCHEMICAL | D30: 12 | E30: 12 | F30: 12 | G30: 12 | H30: 12 | I30: 12 | J30: 12 | K30: 12 | L30: 12 | M30: 12 | N30: 12 | O30: 12
C32: Target | V32: NO | W32: PELANGGAN | X32: PB/PD | Y32: SATUAN | Z32: 2025
C33: PELANGGAN | D33: Jan | E33: Feb | F33: Mar | G33: Apr | H33: Mei | I33: Jun | J33: Jul | K33: Agus | L33: Sep | M33: Okt | N33: Nov | O33: Des | P33: JUMLAH | Q33: Q1 | R33: Q2 | S33: Q3 | T33: Q4 | Z33: DEC
C34: PT TAMAN RESOR INTERNET | D34: =(D26-132.6)*$D$18*$D$21*1000 -> 1.3398e+10 | E34: =(E26-132.6)*$D$18*$D$21*1000 -> 1.3398e+10 | F34: =(F26-132.6)*$D$18*$D$21*1000 -> 1.3398e+10 | G34: =(G26-132.6)*$D$18*$D$21*1000 -> 37158000000 | H34: =(H26-132.6)*$D$18*$D$21*1000 -> 43098000000 | I34: =(I26-132.6)*$D$18*$D$21*1000 -> 43098000000 | J34: =(J26-132.6)*$D$18*$D$21*1000 -> 43098000000 | K34: =(K26-132.6)*$D$18*$D$21*1000 -> 48708000000 | ... O34: =(O26-132.6)*$D$18*$D$21*1000 -> 48708000000 | P34: =SUM(D34:O34) -> 450186000000 | Q34: =SUM(D34:F34) -> 4.0194e+10 | R34: =SUM(G34:I34) -> 123354000000 | S34: =SUM(J34:L34) -> 140514000000 | T34: =SUM(M34:O34) -> 146124000000 | V34: 1 | W34: PT TAMAN RESOR INTERNET | X34: PD | Y34: MVA | Z34: 132.6
B35: dc | C35: PT TEKNOLOGI DATA INFRASTRUKTUR | D35: =D27*$D$17*$D$20*1000 -> 5400000000 | E35: =E27*$D$17*$D$20*1000 -> 5400000000 | F35: =F27*$D$17*$D$20*1000 -> 5400000000 | G35: =G27*$D$17*$D$20*1000 -> 5400000000 | H35: =H27*$D$17*$D$20*1000 -> 5400000000 | I35: =I27*$D$17*$D$20*1000 -> 5400000000 | J35: =J27*$D$17*$D$20*1000 -> 5400000000 | K35: =K27*$D$17*$D$20*1000 -> 5400000000 | ... O35: =O27*$D$17*$D$20*1000 -> 10800000000 | P35: =SUM(D35:O35) -> 86400000000 | Q35: =SUM(D35:F35) -> 16200000000 | R35: =SUM(G35:I35) -> 16200000000 | S35: =SUM(J35:L35) -> 21600000000 | T35: =SUM(M35:O35) -> 32400000000 | V35: 2 | W35: PT TEKNOLOGI DATA INFRASTRUKTUR | X35: PD | Y35: MVA | Z35: 0
B36: pwu | C36: PT PRIMA UTILITAS ENERGI II | F36: =F28*$D$21*$D$18*1000 -> 5280000000 | G36: =G28*$D$21*$D$18*1000 -> 5280000000 | H36: =H28*$D$21*$D$18*1000 -> 5280000000 | I36: =I28*$D$21*$D$18*1000 -> 5280000000 | J36: =J28*$D$21*$D$18*1000 -> 5280000000 | K36: =K28*$D$21*$D$18*1000 -> 5280000000 | L36: =L28*$D$21*$D$18*1000 -> 5280000000 | M36: =M28*$D$21*$D$18*1000 -> 5280000000 | ... O36: =O28*$D$21*$D$18*1000 -> 5280000000 | P36: =SUM(D36:O36) -> 52800000000 | Q36: =SUM(D36:F36) -> 5280000000 | R36: =SUM(G36:I36) -> 15840000000 | S36: =SUM(J36:L36) -> 15840000000 | T36: =SUM(M36:O36) -> 15840000000 | V36: 3 | W36: PT PRIMA UTILITAS ENERGI II | X36: PD | Y36: MVA
B37: pwu | C37: PT PRIMA UTILITAS ENERGI I | F37: =F29*$D$21*$D$18*1000 -> 2805000000 | G37: =G29*$D$21*$D$18*1000 -> 2805000000 | H37: =H29*$D$21*$D$18*1000 -> 2805000000 | I37: =I29*$D$21*$D$18*1000 -> 2805000000 | J37: =J29*$D$21*$D$18*1000 -> 2805000000 | K37: =K29*$D$21*$D$18*1000 -> 2805000000 | L37: =L29*$D$21*$D$18*1000 -> 2805000000 | M37: =M29*$D$21*$D$18*1000 -> 2805000000 | ... O37: =O29*$D$21*$D$18*1000 -> 2805000000 | P37: =SUM(D37:O37) -> 28050000000 | Q37: =SUM(D37:F37) -> 2805000000 | R37: =SUM(G37:I37) -> 8415000000 | S37: =SUM(J37:L37) -> 8415000000 | T37: =SUM(M37:O37) -> 8415000000 | V37: 4 | W37: PT PRIMA UTILITAS ENERGI I | X37: PB | Y37: MVA
B38: Silver | C38: PT ECOGREEN OLEOCHEMICAL | D38: =D30*$D$22*$D$19*1000 -> 3600000000 | E38: =E30*$D$22*$D$19*1000 -> 3600000000 | F38: =F30*$D$22*$D$19*1000 -> 3600000000 | G38: =G30*$D$22*$D$19*1000 -> 3600000000 | H38: =H30*$D$22*$D$19*1000 -> 3600000000 | I38: =I30*$D$22*$D$19*1000 -> 3600000000 | J38: =J30*$D$22*$D$19*1000 -> 3600000000 | K38: =K30*$D$22*$D$19*1000 -> 3600000000 | ... O38: =O30*$D$22*$D$19*1000 -> 3600000000 | P38: =SUM(D38:O38) -> 43200000000 | Q38: =SUM(D38:F38) -> 10800000000 | R38: =SUM(G38:I38) -> 10800000000 | S38: =SUM(J38:L38) -> 10800000000 | T38: =SUM(M38:O38) -> 10800000000 | V38: 5 | W38: PT ECOGREEN OLEOCHEMICAL | Y38: MVA
C40: TOTAL | D40: =SUM(D34:D38) -> 22398000000 | E40: =SUM(E34:E38) -> 22398000000 | F40: =SUM(F34:F38) -> 30483000000 | G40: =SUM(G34:G38) -> 54243000000 | H40: =SUM(H34:H38) -> 60183000000 | I40: =SUM(I34:I38) -> 60183000000 | J40: =SUM(J34:J38) -> 60183000000 | K40: =SUM(K34:K38) -> 65793000000 | ... O40: =SUM(O34:O38) -> 71193000000 | P40: =SUM(P34:P39) -> 660636000000 | Q40: =SUM(Q34:Q39) -> 75279000000 | R40: =SUM(R34:R39) -> 174609000000 | S40: =SUM(S34:S39) -> 197169000000 | T40: =SUM(T34:T39) -> 213579000000
C41: DAMPAK KUMULATIF | D41: =D40 -> 22398000000 | E41: =D41+E40 -> 44796000000 | F41: =E41+F40 -> 75279000000 | G41: =F41+G40 -> 129522000000 | H41: =G41+H40 -> 189705000000 | I41: =H41+I40 -> 249888000000 | J41: =I41+J40 -> 310071000000 | K41: =J41+K40 -> 375864000000 | L41: =K41+L40 -> 447057000000 | ... O41: =N41+O40 -> 660636000000 | Q41: =Q40 -> 75279000000 | R41: =Q41+R40 -> 249888000000 | S41: =R41+S40 -> 447057000000 | T41: =S41+T40 -> 660636000000
Q42: =T41 -> 660636000000 | R42: =$Q$42-Q41 -> 585357000000 | S42: =$Q$42-R41 -> 410748000000 | T42: =$Q$42-S41 -> 213579000000
C44: PELANGGAN | D44: DAYA | F44: STATUS | G44: RENCANA NYALA 2025 | H44: RENCANA PERUBAHAN | I44: KETERANGAN
C45: Nongsa Digital Park | D45: 243.2 | E45: MVA | F45: PJBTL | G45: Februari | H45: September 2025 | I45: MUNDUR
C46: Neutra DC | D46: 15 | E46: MVA | F46: PJBTL | G46: Juni | H46: Januari 2026 | I46: MUNDUR
C47: PT McDermott Indonesia | D47: 12.5 | E47: MVA | F47: PJBTL | G47: Januari | H47: Agustus 2025 | I47: MUNDUR
C48: PT Ecogreen Oleochemical | D48: 12 | E48: MVA | F48: PJBTL | G48: Juli | H48: Januari 2025 | I48: PERCEPAT
C49: PT Citra Buana 3 | D49: 5 | E49: MVA | F49: PJBTL | G49: Maret | H49: Maret 2025 | I49: SESUAI
C50: PT Aman Sejati Propertindo | D50: 8 | E50: MVA | F50: Belum PJBTL | G50: Januari | I50: BELUM ADA PJBTL
C52: Probabilitas | D52: =3/5 -> 0.6
C53: *) Dari 3 Pelanggan Add Demand 2025 yang sudah status PJBTL terdapat 3 pelanggan yang mundur aktivasi daya dari jadwal yang direncanakan
B56: 2 | C56: Risiko Penggunaan anggaran melebihi pagu anggaran yang ditetapkan dalam RKAP
C57: Berdasarkan Nota Dinas DIRKEUSDM nomor 4176/KEU.00.03/DIRKEUSDM/2024 tanggal 24 Juli 2024 perihal Revisi Penetapan Pagu SKAO Biaya Administrasi Tahun 2024 sebesar Rp 5,112,390,764,-
C59: Tahun | D59: Usulan Awal | E59: SKAO Awal | F59: Penetapan Revisi SKAO | G59: Selisih | H59: Realisasi Penyerapan | I59: Realisasi Lebih | J59: Probabilitas
C60: 2025 | D60: 7734910000 | E60: 3634910000 | H60: 2418887596 | I60: 0 | J60: =1/5 -> 0.2
C61: 2024 | D61: 1573060280 | E61: 1512390764 | F61: 5112390764 | G61: =F61-E61 -> 3600000000 | H61: 5013011085 | I61: 1 | J61: =1/4 -> 0.25
C62: 2023 | D62: 1102020280 | E62: 783784120 | H62: 711254036 | I62: 0
C63: 2022 | D63: 758962364 | E63: =757357827 -> 757357827 | H63: 754071920 | I63: 0
C64: 2021 | D64: 2241366965 | E64: =758962365 -> 758962365 | H64: 603995223 | I64: 0
F65: Dampak | G65: =AVERAGE(G60:G64) -> 3600000000 | J65: =AVERAGE(J60:J61) -> 0.225
C67: *Nilai Dampak diambil dari nilai tengah atau rata2 selisih kurang AO selama 5 tahun terakhir
C68: ** Probabilitas diambil dari berapa kali terjadi penetapan revisi SKAO selama 5 tahun terakhir
B72: 3 | C72: Keterlambatan Penerimaan Penjualan Tenaga Listrik Interkoneksi di atas 35 hari
C74: Tahun 2025 | J74: Tahun 2024 | P74: Tahun 2023
C75: Penjualan Juli 2025 | G75: 35 | J75: Penjualan Desember 2024 | N75: 35 | P75: Penjualan Desember 2023 | T75: 35
C76: Periode Penjualan | D76: UIW Riau | E76: Saldo Piutang | F76: Hari Penerimaan | G76: Delta Target Hari | H76: Penerimaan > 35 hari | J76: Periode Penjualan | K76: UIW Riau | L76: Saldo Piutang | M76: Hari Penerimaan | N76: Delta Target Hari | P76: Periode Penjualan | Q76: UIW Riau | R76: Saldo Piutang | S76: Hari Penerimaan | T76: Delta Target Hari
C77: Januari '25 | D77: 99781531200 | F77: 25 | G77: =$G$75-F77 -> 10 | H77: =IF(G77<0,D77,0) -> 0 | J77: Januari '24 | K77: 93718324800 | M77: 42 | N77: =$N$75-M77 -> -7 | P77: Januari '23 | Q77: 86650048800 | S77: 30 | T77: =$T$75-S77 -> 5
C78: Februari '25 | D78: 96182460000 | F78: 26 | G78: =$G$75-F78 -> 9 | H78: =IF(G78<0,D78,0) -> 0 | J78: Februari '24 | K78: 95259931200 | M78: 35 | N78: =$N$75-M78 -> 0 | P78: Februari '23 | Q78: 8.0564213e+10 | S78: 21 | T78: =$T$75-S78 -> 14
C79: Maret '25 | D79: =102746880000+1814018400 -> 104560898400 | F79: 45 | G79: =$G$75-F79 -> -10 | H79: =IF(G79<0,D79,0) -> 104560898400 | J79: Maret '24 | K79: 105042664800 | M79: 33 | N79: =$N$75-M79 -> 2 | P79: Maret '23 | Q79: 89349890400 | S79: 17 | T79: =$T$75-S79 -> 18
C80: April '25 | D80: 1.0300687e+11 | F80: 57 | G80: =$G$75-F80 -> -22 | H80: =IF(G80<0,D80,0) -> 1.0300687e+11 | J80: April '24 | K80: 100435492800 | M80: 28 | N80: =$N$75-M80 -> 7 | P80: April '23 | Q80: 90138830400 | S80: 17 | T80: =$T$75-S80 -> 18
C81: Mei '25 | D81: 1.1193065e+11 | F81: 23 | G81: =$G$75-F81 -> 12 | H81: =IF(G81<0,D81,0) -> 0 | J81: Mei '24 | K81: 105950952000 | M81: 24 | N81: =$N$75-M81 -> 11 | P81: Mei '23 | Q81: 97139764800 | S81: 22 | T81: =$T$75-S81 -> 13
C82: Juni '25 | D82: 1.1031039e+11 | F82: 25 | G82: =$G$75-F82 -> 10 | H82: =IF(G82<0,D82,0) -> 0 | J82: Juni '24 | K82: 102736440000 | M82: 168 | N82: =$N$75-M82 -> -133 | P82: Juni '23 | Q82: 95140101600 | S82: 26 | T82: =$T$75-S82 -> 9
C83: Juli'25 | D83: 1.2635729e+11 | F83: 124 | G83: =$G$75-F83 -> -89 | H83: =IF(G83<0,D83,0) -> 1.2635729e+11 | J83: Juli'24 | K83: 109467604800 | M83: 138 | N83: =$N$75-M83 -> -103 | P83: Juli'23 | Q83: 9.810247e+10 | S83: 14 | T83: =$T$75-S83 -> 21
C84: Agustus'25 | D84: 1.2267898e+11 | F84: 93 | G84: =$G$75-F84 -> -58 | H84: =IF(G84<0,D84,0) -> 1.2267898e+11 | J84: Agustus'24 | K84: 107426217600 | M84: 107 | N84: =$N$75-M84 -> -72 | P84: Agustus'23 | Q84: 1.0019545e+11 | S84: 43 | T84: =$T$75-S84 -> -8
C85: September'25 | D85: 1.1483779e+11 | F85: 63 | G85: =$G$75-F85 -> -28 | H85: =IF(G85<0,D85,0) -> 1.1483779e+11 | J85: September'24 | K85: 103772044800 | M85: 77 | N85: =$N$75-M85 -> -42 | P85: September'23 | Q85: 97049030400 | S85: 19 | T85: =$T$75-S85 -> 16
C86: Oktober'25 | D86: 1.5378244e+11 | E86: 1.5378244e+11 | F86: =30+31+31+28 -> 120 | G86: =$G$75-F86 -> -85 | H86: =IF(G86<0,D86,0) -> 1.5378244e+11 | J86: Oktober'24 | K86: 107230820400 | M86: 46 | N86: =$N$75-M86 -> -11 | P86: Oktober'23 | Q86: 101634674400 | S86: 17 | T86: =$T$75-S86 -> 18
C87: November'25 | D87: 1.4461373e+11 | E87: 1.4461373e+11 | F87: =31+31+28 -> 90 | G87: =$G$75-F87 -> -55 | H87: =IF(G87<0,D87,0) -> 1.4461373e+11 | J87: November'24 | K87: 99108144000 | M87: 16 | N87: =$N$75-M87 -> 19 | P87: November'23 | Q87: 96269191200 | S87: 12 | T87: =$T$75-S87 -> 23
C88: Desember'25 | D88: 1.4585225e+11 | E88: 1.4585225e+11 | F88: =31+28 -> 59 | G88: =$G$75-F88 -> -24 | H88: =IF(G88<0,D88,0) -> 1.4585225e+11 | J88: Desember'24 | K88: 107228059200 | M88: 55 | N88: =$N$75-M88 -> -20 | P88: Desember'23 | Q88: 97001827200 | S88: 4 | T88: =$T$75-S88 -> 31
C89: Total | D89: =SUM(D77:D88) -> 1.4338953e+12 | E89: =SUM(E77:E88) -> 4.4424842e+11 | F89: =SUM(F77:F88) -> 750 | H89: =AVERAGE(H79:H88,K77,K82:K86,K88,Q84) -> 1.0263696e+11 | J89: Total | K89: =SUM(K77:K88) -> 1237376696400 | L89: =SUM(L77:L88) -> 0 | M89: =SUM(M77:M88) -> 769 | P89: Total | Q89: =SUM(Q77:Q88) -> 1129235493600 | R89: =SUM(R77:R88) -> 0 | S89: =SUM(S77:S88) -> 242
G90: Probabilitas | H90: =(8+7+1)/36 -> 0.44444444
J91: 2023 | K91: 1
C92: * Nilai Dampak diperhitungkan dari realisasi rata-rata penerimaan yang dibawah 35 hari s.d Desember 2025 sebesar Rp 102.636.956.505,- | J92: 2024 | K92: 7
C93: * Probabilitas Risiko piutang lebih dari 35 hari pernah terjadi pada periode Agustus 2023, Januari 2024, Juni - Oktober 2024, Desember 2024, Maret - April 2025, dan Juli - Desember 2025. Nilai probabilitas dihitung dari frekuensi kejadian dibagi jumlah transaksi selama 3 tahun terakhir sebesar 44,44% sehingga dikategorikan skala 3 atau bisa terjadi
B97: 4 | C97: Risiko Calon Pelanggan Additional Demand batal menjadi pelanggan
C98: Calon Pelanggan yang diperhitungkan dalam menghitung nilai dampak adalah pelanggan /calon pelanggan dengan kategori Confident Level Sedang, yang terdiri dari:
C99: PELANGGAN | D99: DAYA | F99: STATUS | G99: RENCANA NYALA 2026
C100: PT DIGITALLAND SERVICE ONE | D100: 511 | E100: MVA | F100: Belum PJBTL | G100: September
C101: JN Minimum - Diamond DC | D101: 200 | E101: Jam
C102: Tarif Diamond DC | D102: 1800 | E102: Rp/kWh
C104: Rencana aktivasi daya
C105: Pelanggan | D105: JAN | E105: FEB | F105: MAR | G105: APR | H105: MAY | I105: JUN | J105: JUL | K105: AUG | L105: SEP | M105: OCT | N105: NOV | O105: DEC
C106: PT DIGITALLAND SERVICE ONE | L106: 177 | M106: 177 | N106: 177 | O106: 177
C108: Target | V108: NO | W108: PELANGGAN | X108: PB/PD | Y108: SATUAN | Z108: 2025
C109: PELANGGAN | D109: Jan | E109: Feb | F109: Mar | G109: Apr | H109: Mei | I109: Jun | J109: Jul | K109: Agus | L109: Sep | M109: Okt | N109: Nov | O109: Des | P109: JUMLAH | Q109: Q1 | R109: Q2 | S109: Q3 | T109: Q4 | Z109: DEC
C110: PT DIGITALLAND SERVICE ONE | L110: =(L106*$D$101*$D$102*1000) -> 63720000000 | M110: =(M106*$D$101*$D$102*1000) -> 63720000000 | N110: =(N106*$D$101*$D$102*1000) -> 63720000000 | O110: =(O106*$D$101*$D$102*1000) -> 63720000000 | P110: =SUM(D110:O110) -> 254880000000 | Q110: =SUM(D110:F110) -> 0 | R110: =SUM(G110:I110) -> 0 | S110: =SUM(J110:L110) -> 63720000000 | T110: =SUM(M110:O110) -> 191160000000 | V110: 1 | W110: PT TAMAN RESOR INTERNET | X110: PD | Y110: MVA | Z110: 132.6
C112: TOTAL | D112: =SUM(D110:D110) -> 0 | E112: =SUM(E110:E110) -> 0 | F112: =SUM(F110:F110) -> 0 | G112: =SUM(G110:G110) -> 0 | H112: =SUM(H110:H110) -> 0 | I112: =SUM(I110:I110) -> 0 | J112: =SUM(J110:J110) -> 0 | K112: =SUM(K110:K110) -> 0 | ... O112: =SUM(O110:O110) -> 63720000000 | P112: =SUM(P110:P111) -> 254880000000 | Q112: =SUM(Q110:Q111) -> 0 | R112: =SUM(R110:R111) -> 0 | S112: =SUM(S110:S111) -> 63720000000 | T112: =SUM(T110:T111) -> 191160000000
C113: DAMPAK KUMULATIF | D113: =D112 -> 0 | E113: =D113+E112 -> 0 | F113: =E113+F112 -> 0 | G113: =F113+G112 -> 0 | H113: =G113+H112 -> 0 | I113: =H113+I112 -> 0 | J113: =I113+J112 -> 0 | K113: =J113+K112 -> 0 | L113: =K113+L112 -> 63720000000 | ... O113: =N113+O112 -> 254880000000 | Q113: =Q112 -> 0 | R113: =Q113+R112 -> 0 | S113: =R113+S112 -> 63720000000 | T113: =S113+T112 -> 254880000000
Q114: =T113 -> 254880000000 | R114: =$Q$114-Q113 -> 254880000000 | S114: =$Q$114-R113 -> 254880000000 | T114: =$Q$114-S113 -> 191160000000
C116: PELANGGAN | D116: DAYA | F116: STATUS | G116: RENCANA NYALA 2025 | H116: RENCANA PERUBAHAN | I116: KETERANGAN
C117: Nongsa Digital Park | D117: 243.2 | E117: MVA | F117: PJBTL | G117: Februari | H117: September 2025 | I117: MUNDUR
C118: Neutra DC | D118: 15 | E118: MVA | F118: PJBTL | G118: Juni | H118: Januari 2026 | I118: MUNDUR
C119: PT McDermott Indonesia | D119: 12.5 | E119: MVA | F119: Belum PJBTL | G119: Januari | H119: Agustus 2025 | I119: MUNDUR
C120: PT Ecogreen Oleochemical | D120: 12 | E120: MVA | F120: PJBTL | G120: Juli | H120: Januari 2025 | I120: PERCEPAT
C121: PT Citra Buana 3 | D121: 5 | E121: MVA | F121: Belum PJBTL | G121: Maret | H121: Maret 2025 | I121: SESUAI
C122: PT Aman Sejati Propertindo | D122: 8 | E122: MVA | F122: Belum PJBTL | G122: Januari | I122: BELUM ADA PJBTL
C124: Probabilitas | D124: =1/3 -> 0.33333333
C125: *) Dari 3 Pelanggan Add Demand 2025 yang sudah status belum PJBTL terdapat 1 pelanggan yang belum tantadangan PJBTL sampai akhir 2025
B128: 5 | C128: Risiko Tidak disetujuinya persetujuan harga jual tenaga listrik interkoneksi oleh Menteri
C130: Bulan | D130: Jan | E130: Feb | F130: Mar | G130: Apr | H130: Mei | I130: Jun | J130: Jul | K130: Agus | L130: Sep | M130: Okt | N130: Nov | O130: Des | P130: JUMLAH | Q130: Q1 | R130: Q2 | S130: Q3 | T130: Q4
C131: Kwh Jual Interkoneksi 2026 | D131: 57363967 | E131: 55282247 | F131: 61215608 | G131: 59213324 | H131: 62776463 | I131: 60860228 | J131: 64876032 | K131: 63659143 | L131: 61484240 | M131: 63544700 | N131: 58698886 | O131: 63544741 | P131: =SUM(D131:O131) -> 7.3251958e+08 | Q131: =SUM(D131:F131) -> 1.7386182e+08 | R131: =SUM(G131:I131) -> 1.8285002e+08 | S131: =SUM(J131:L131) -> 1.9001942e+08 | T131: =SUM(M131:O131) -> 1.8578833e+08
...

Sheet Contoh Justifikasi Risk Assess
B1: Sheet ini berisi informasi setiap Risiko yang terdiri : 1. Data tabel berisi informasi penyebab risiko untuk setiap risiko utama (data 3-5 tahun terakhir) 2. Alasan memilih kriteria dampak kualitatif dan dilengkapi data
A6: Contoh :
A7: 1. Risiko foreign exchange loss
C8: Berdasarkan informasi bahwa selama selama 3 tahun terakhir terjadi pelemahan IDR dengan level terendah turun sebesar 11% dari kurs asumsi RKAP. Berdasarkan data RKAP diketahui nilai piutang usaha non-USD adalah sebesar IDR 3.000 juta, sehingga nilai dampak inherennya dapat dihitung sebagai berikut:
C9: Tabel Perhitungan Dampak Kuantitatif Inheren atas Risiko Valuta Asing
C10: Keterangan | F10: Nilai
C11: Nilai piutang non-USD pemerintah (a) | F11: IDR 3.000 juta
C12: % penurunan IDR terhadap USD (b) | F12: 0.11
C13: Dampak jika Risiko terwujud (c=a*b) | F13: IDR 330 juta
D14: Maka berdasarkan skala Dampak mengacu pada Tabel Kriteria Dampak Kuantitatif. Risiko foreign exchange loss dalam contoh dengan nilai dampak IDR 330 juta dipetakan ke skala 4 atau Tinggi.
D16: FX Loss terjadi jika realisasi kurs transaksi IDR/USD RKAP berada di atas target RKAP. Range data menggunakan waktu 3 (tiga) tahun terakhir dengan total 750 hari transaksi IDR/USD (terdapat 250 hari transaksi dalam 1 tahun berdasarkan data dari Bank Indonesia ) dengan perhitungan skala Probabilitas sebagai berikut:
D17: Tabel Perhitungan Skala Probabilitas Risiko Valas
D18: Tahun | E18: Kurs Transaksi IDR/USD RKAP | F18: Realisasi Kurs di atas RKAP (range 14.355 - 15.000) | G18: Realisasi Kurs di bawah RKAP (range 14.000 - 14.355) | H18: % Kurs Realisasi di atas Kurs RKAP | I18: Skala Probabi-litas
D19: 2022 | E19: 14350 | F19: 175 transaksi | G19: 75 transaksi
D20: 2021 | E20: 14600 | F20: 200 transaksi | G20: 50 transaksi
D21: 2020 | E21: 14400 | F21: 225 transaksi | G21: 25 transaksi
D22: Total | F22: 600 transaksi | G22: 150 transaksi | H22: 80%* | I22: 4 (sangat mungkin terjadi)
D23: Catatan:
D24: % Probabilitas=(Frekuensi kejadian di masa lalu)/(Populasi data kejadian dalam perhitungan)x 100%
D26: Berdasarkan perhitungan di atas, maka % probalibilitasnya sebesar 80%, dan dipetakan ke dalam Tabel Kriteria Probabilitas, didapatkan skala Probabilitas Risiko pada skala 4 atau sangat mungkin terjadi.
A28: 2. Risiko menurunnya reputasi perusahaan
D29: Berdasarkan informasi 3 tahun terakhir, terdapat pemberitaan negatif yang berdampak secara lokal di tiap tahunnya, sehingga ditentukan Dampak Risiko reputasi memiliki skala 3 atau Moderat setelah dipetakan ke dalam Tabel Kriteria Dampak Kualitatif
D30: Selama 3 (tiga) tahun terakhir diperoleh informasi pemberitaan dengan klasifikasi dan frekuensi sebagai berikut:
D31: Tabel Data Historis Informasi Pemberitaan 3 (Tiga) Tahun Terakhir
D32: Periode | E32: Frekuensi Pemberitaan | H32: % kejadian pemberitaan negative (d = a / a+b+c)
E33: Negatif (a) | F33: Netral (b) | G33: Positif (c)
D34: 2022 | E34: 10 | F34: 20 | G34: 15 | H34: 0.2222
D35: 2021 | E35: 15 | F35: 24 | G35: 17 | H35: 0.2678
D36: 2020 | E36: 9 | F36: 30 | G36: 20 | H36: 0.1525
G37: Rata-rata | H37: 0.2142
D38: Dari data di atas diketahui persentase Probabilitas terjadinya Risiko menurunnya reputasi adalah 21,42% atau skala 2 (jarang terjadi) sesuai Tabel Kriteria Probabilitas
C41: BIDANG KEUANGAN
N42: Selisih Kurs Tahun 2023 | U42: Selisih Kurs Tahun 2021 | AB42: Selisih Kurs Tahun 2022
C43: 1. Kenaikan beban operasi akibat pelemahan nilai tukar rupiah terhadap dollar (Nomor Risiko : 1-A.2-KEU-1) | N43: Periode | O43: Kurs Penutup (Jisdor) | P43: Kurs RKAP | Q43: Selisih Kurs | R43: Total Biaya dalam dollar/terekspos dollar | S43: Efek Ke Beban Operasi | U43: Periode | V43: Kurs Penutup | W43: Kurs RKAP | X43: Selisih Kurs | Y43: Total Biaya dalam dollar/terekspos dollar | Z43: Efek Ke Beban Operasi | AB43: Periode | AC43: Kurs Penutup | AD43: Kurs RKAP | AE43: Selisih Kurs | AF43: Total Biaya dalam dollar/terekspos dollar | AG43: Efek Ke Beban Operasi
O45: ( Rp ) | P45: ( Rp ) | Q45: ( Rp ) | R45: ( USD ) | S45: ( Rp ) | V45: ( Rp ) | W45: ( Rp ) | X45: ( Rp ) | Y45: ( USD ) | Z45: ( Rp ) | AC45: ( Rp ) | AD45: ( Rp ) | AE45: ( Rp ) | AF45: ( USD ) | AG45: ( Rp )
N46: 44227 | O46: 14992 | P46: 14800 | Q46: 192 | R46: 19525568 | S46: 3748909019 | U46: 44227 | V46: 14084 | W46: 14600 | X46: -516 | Y46: 17388506 | Z46: -8.972469e+09 | AB46: 44592 | AC46: 14381.005 | AD46: 14350 | AE46: 31.005 | AF46: 17868687 | AG46: 554018625
D47: Data Realisasi Rata-rata Nilai Kurs di bandingkan RKAP 3 Tahun Terakhir | N47: 44255 | O47: 15240 | P47: 14800 | Q47: 440 | R47: 17724851 | S47: 7798934524 | U47: 44255 | V47: 14229.005 | W47: 14600 | X47: -370.995 | Y47: 16499129 | Z47: -6.1210943e+09 | AB47: 44620 | AC47: 14371.005 | AD47: 14350 | AE47: 21.005 | AF47: 16568101 | AG47: 348012954
D48: No | E48: Tahun | F48: Kurs RKAP | G48: Realisasi kurs rata-rata | H48: Selisih | I48: Selisih | N48: 44286 | O48: 14977 | P48: 14800 | Q48: 177 | R48: 21050203 | S48: 3725885970 | U48: 44286 | V48: 14572 | W48: 14600 | X48: -28 | Y48: 17924852 | Z48: -5.0189585e+08 | AB48: 44651 | AC48: 14349.005 | AD48: 14350 | AE48: -0.995 | AF48: 19759462 | AG48: -19660665
D49: 1 | E49: 2021 | F49: 14600 | G49: =V59 -> 14344.918 | H49: =F49-G49 -> 255.08167 | I49: =H49/F49 -> 0.017471347 | N49: 44316 | O49: 14661 | P49: 14800 | Q49: -139 | R49: 20187051 | S49: -2806000047 | U49: 44316 | V49: 14468 | W49: 14600 | X49: -132 | Y49: 18024797 | Z49: -2.3792732e+09 | AB49: 44681 | AC49: 14418 | AD49: 14350 | AE49: 68 | AF49: 19366428 | AG49: 1316917106
D50: 2 | E50: 2022 | F50: 14350 | G50: =AC59 -> 14905.168 | H50: =F50-G50 -> -555.16833 | I50: =H50/F50 -> -0.038687689 | N50: 44347 | O50: 15003 | P50: 14800 | Q50: 203 | R50: 21099401 | S50: 4283178488 | U50: 44347 | V50: 14310 | W50: 14600 | X50: -290 | Y50: 19280499 | Z50: -5.5913446e+09 | AB50: 44712 | AC50: 14544 | AD50: 14350 | AE50: 194 | AF50: 20777293 | AG50: 4030794908
D51: 3 | E51: 2023 | F51: 14800 | G51: =O59 -> 15209.083 | H51: =F51-G51 -> -409.08333 | I51: =H51/F51 -> -0.027640766 | N51: 44377 | O51: 15000 | P51: 14800 | Q51: 200 | R51: 21143140 | S51: 4228627974 | U51: 44377 | V51: 14496 | W51: 14600 | X51: -104 | Y51: 18796499 | Z51: -1.9548359e+09 | AB51: 44742 | AC51: 14848 | AD51: 14350 | AE51: 498 | AF51: 19431106 | AG51: 9676690818
E52: Rata-rata | I52: =AVERAGE(I49:I51) -> -0.016285702 | N52: 44408 | O52: 15092 | P52: 14800 | Q52: 292 | R52: 21624724 | S52: 6314419417 | U52: 44408 | V52: 14491 | W52: 14600 | X52: -109 | Y52: 19328692 | Z52: -2.1068275e+09 | AB52: 44773 | AC52: 14958 | AD52: 14350 | AE52: 608 | AF52: 20636275 | AG52: 12546855060
N53: 44439 | O53: 15237 | P53: 14800 | Q53: 437 | R53: 21561066 | S53: 9422185667 | U53: 44439 | V53: 14374 | W53: 14600 | X53: -226 | Y53: 19182701 | Z53: -4.3352905e+09 | AB53: 44804 | AC53: 14875.005 | AD53: 14350 | AE53: 525.005 | AF53: 20680306 | AG53: 10857264230
D54: Data Laba/Rugi Kurs 3 tahun terakhir | N54: 44469 | O54: 15487 | P54: 14800 | Q54: 687 | R54: 20769867 | S54: 14268898911 | U54: 44469 | V54: 14307.005 | W54: 14600 | X54: -292.995 | Y54: 18196224 | Z54: -5.3314026e+09 | AB54: 44834 | AC54: 15247 | AD54: 14350 | AE54: 897 | AF54: 19107707 | AG54: 17139613062
D55: No | E55: Tahun | F55: Kurs RKAP | G55: Kurs realisasi | H55: selisih | I55: % | J55: Laba/Rugi | K55: Rugi % | N55: 44500 | O55: 15897 | P55: 14800 | Q55: 1097 | R55: 21572648 | S55: 23665195383 | U55: 44500 | V55: 14199.005 | W55: 14600 | X55: -400.995 | Y55: 19598980 | Z55: -7.859093e+09 | AB55: 44865 | AC55: 15542 | AD55: 14350 | AE55: 1192 | AF55: 21270286 | AG55: 25354181055
D56: 1 | E56: 2021 | F56: =F49*Y58 -> 3259773041790 | G56: =G49*Y58 -> 3.2028204e+12 | H56: 0 | I56: =H56/H59 -> 0 | J56: 1 | N56: 44530 | O56: 15484 | P56: 14800 | Q56: 684 | R56: 21474738 | S56: 14688721127 | U56: 44530 | V56: 14340 | W56: 14600 | X56: -260 | Y56: 19135298 | Z56: -4.9751774e+09 | AB56: 44895 | AC56: 15737 | AD56: 14350 | AE56: 1387 | AF56: 19008556 | AG56: 26364867089
D57: 2 | E57: 2022 | F57: =F50*AF58 -> 3.3697451e+12 | G57: =G50*AF58 -> 3.5001127e+12 | H57: =G57-F57 -> 1.3036765e+11 | I57: =H57/H59 -> 0.56051453 | J57: 1 | K57: =SUM(J57+J58)/J59 -> 0.66666667 | N57: 44561 | O57: 15439 | P57: 14800 | Q57: 639 | R57: 22137650 | S57: 14145958050 | U57: 44561 | V57: 14269.005 | W57: 14600 | X57: -330.995 | Y57: 19915950 | Z57: -6.5920797e+09 | AB57: 44926 | AC57: 15592 | AD57: 14350 | AE57: 1242 | AF57: 20351233 | AG57: 25276231013
D58: 3 | E58: 2023 | F58: =F51*R58 -> 3.6980894e+12 | G58: =G51*R58 -> 3.8003075e+12 | H58: =G58-F58 -> 1.0221802e+11 | I58: =H58/H59 -> 0.43948547 | J58: 1 | N58: Total | R58: 2.4987091e+08 | S58: 103484914483 | U58: Total | Y58: 2.2327213e+08 | Z58: -5.6720784e+10 | AB58: Total | AF58: 2.3482544e+08 | AG58: 133445785255
H59: =SUM(H56:H58) -> 2.3258567e+11 | I59: =AVERAGE(I57:I58) -> 0.5 | J59: =SUM(J56:J58) -> 3 | K59: prosentasi Probabilitas | O59: =AVERAGE(O46:O57) -> 15209.083 | V59: =AVERAGE(V46:V57) -> 14344.918 | AC59: =AVERAGE(AC46:AC57) -> 14905.168
H60: 118465349869 | R60: =R58*I52 -> -4069323.3
D62: Dari perhitungan diatas terdapat Dampak disruptif yang dapat mengakibatkan kerusakan/ kerugian/ penurunan 40% < X ≤ 60% dikategorikan skala 3 atau Moderat | N62: selisih kurs di peroleh dari total biaya operasional selama satu tahun dibandingkan dengan kurs RKAP
D63: untuk probabilitas Risiko pernah terjadi sekali dalam 2 bulan sehingga dikategorikan skala 4 atau sangat mungkin terjadi
C65: 2. Keterlambatan Penerimaan Penjualan Tenaga Listrik MPP 500 MW di atas 120 hari (Nomor Risiko : 2-A.1-KEU-2)
D67: Tahun 2023 | O67: Tahun 2022 | X67: Tahun 2021
D68: Saldo Piutang Per 31 Desember 2023
D69: Periode Tagihan Interkoneksi & MPP | E69: UIW Riau | F69: Kit SUMUT | G69: KIT SUMSEL | H69: KIT KALIMANTAN | I69: UIW BABEL | J69: UIW NTB | K69: Total | O69: Periode Tagihan Interkoneksi & MPP | P69: UIW Riau | Q69: Kit SUMUT | R69: KIT SUMSEL | S69: KIT KALIMANTAN | T69: UIW BABEL | U69: UIW NTB | V69: Total
D70: September'22 | K70: 0 | O70: September'21 | V70: 0 | Y70: Pendapatan sesusi Target RKAP
D71: Oktober'22 | K71: 0 | O71: Oktober'21 | V71: 0 | Y71: Pendapatan tenaga listrik | AB71: 6306470000000
D72: November'22 | K72: 0 | O72: November'21 | V72: 0 | Y72: Pendapatan Lain-lain | AB72: =2443901*10^6 -> 2443901000000
D73: Desember'22 | K73: 0 | O73: Desember'21 | V73: 0 | Y73: Pendapatan BP | AB73: =26114*10^6 -> 26114000000
D74: Januari'23 | K74: 0 | O74: Januari '22 | V74: 0 | Y74: Total Pendapatan | AB74: =AB71+AB72+AB73 -> 8776485000000
D75: Februari'23 | K75: 0 | O75: Februari '22 | V75: 0 | Y75: Pendapatan Bintan Sembulang belakang padang | AB75: 1351618000000
D76: Maret'23 | K76: 0 | O76: Maret '22 | V76: 0 | Y76: Pendpatan BP | AB76: =AB73 -> 26114000000
D77: April'23 | K77: 0 | O77: April '22 | V77: 0 | Y77: Total Pendaptan tanpa bintan sembulang dan belakang padang | AB77: =AB74-AB75 -> 7424867000000
D78: Mei'23 | K78: 0 | O78: Mei '22 | V78: 0 | Y78: Total Dampak dihitung 5% dari KRI | AB78: =AB77*5% -> 371243350000
D79: Juni'23 | K79: 0 | O79: Juni '22 | V79: 0
D80: Juli'23 | I80: 16212236256 | K80: 16212236256 | O80: Juli'22 | V80: 0
D81: Agustus'23 | I81: 19978691723 | K81: 19978691723 | O81: Agustus'22 | V81: 0
D82: September'23 | I82: 17869882750 | J82: 10161403671 | K82: 28031286421 | O82: September'22 | S82: 22408250838 | U82: 11384146440 | V82: 33792397278
D83: Oktober'23 | I83: 18227891372 | J83: 12642851241 | K83: 30870742613 | O83: Oktober'22 | Q83: 43650791805 | U83: 9728415731 | V83: 53379207536
D84: November'23 | F84: 36409473467 | G84: 16844127395 | H84: 23656171438 | I84: 25250531264 | J84: 13468225713 | K84: 115628529277 | L84: 337229341473 | M84: MPP | O84: November'22 | Q84: 43805745871 | R84: 25337904430 | S84: 23771082792 | T84: 17467337158 | U84: 8862221411 | V84: 119244291662
D85: Desember'23 | E85: 9.7001827e+10 | F85: 38504922662 | G85: 25118199594 | H85: 24893243278 | I85: 25437623982 | J85: 12553865667 | K85: 2.2350968e+11 | O85: Desember'22 | P85: 72412331182 | Q85: 46579901695 | R85: 29689685890 | S85: 24031748250 | T85: 21154827181 | U85: 13885456566 | V85: 207753950764
D86: Total | E86: 9.7001827e+10 | F86: 74914396129 | G86: 41962326989 | H86: 48549414716 | I86: 122976857347 | J86: 48826346292 | K86: 4.3423117e+11 | O86: Total | P86: 72412331182 | Q86: 134036439371 | R86: 55027590320 | S86: 70211081880 | T86: 38622164339 | U86: 43860240148 | V86: 414169847240
D88: Penjualan Desember 2023 | O88: Penjualan sd November 2022
D89: Periode Penjualan | E89: UIW Riau | F89: Kit SUMUT | G89: KIT SUMSEL | H89: KIT KALIMANTAN | I89: UIW BABEL | J89: UIW NTB | K89: Total | O89: Periode Penjualan | P89: UIW Riau | Q89: Kit SUMUT | R89: KIT SUMSEL | S89: KIT KALIMANTAN | T89: UIW BABEL | U89: UIW NTB | V89: Total
D90: Januari '23 | E90: 74145122129 | F90: 44747349274 | G90: 28619687710 | H90: 22470628547 | I90: 19840362906 | J90: 14992926054 | K90: 204816076620 | L90: 9.4901376e+11 | M90: RKR | O90: Januari '22 | P90: 68528200619 | Q90: 42871764768 | R90: 24358201502 | S90: 22533604085 | T90: 18820274088 | U90: 12757605742 | V90: 189869650804
D91: Februari '23 | E91: 68935631428 | F91: 39507637299 | G91: 25013232578 | H91: 20414604513 | I91: 17564132052 | J91: 11259696134 | K91: 182694934004 | L91: 1453803348051 | M91: MPP | O91: Februari '22 | P91: 61059327266 | Q91: 38104016373 | R91: 18770373220 | S91: 19242775792 | T91: 17153640550 | U91: 10121191664 | V91: 164451324865
D92: Maret '23 | E92: 76454850867 | F92: 45042516811 | G92: 27622695600 | H92: 24141274970 | I92: 19239363590 | J92: 9390183065 | K92: 201890884903 | O92: Maret '22 | P92: 70266475239 | Q92: 42761003381 | R92: 29153870318 | S92: 19942136854 | T92: 18226497272 | U92: 11395935898 | V92: 191745918962
D93: April '23 | E93: 72251572015 | F93: 43776027587 | G93: 27339256358 | H93: 22950798690 | I93: 18691564639 | J93: 12379281138 | K93: 197388500427 | L93: 484601116017 | M93: per 4 bulan | O93: April '22 | P93: 6.388893e+10 | Q93: 38652825585 | R93: 27186242583 | S93: 22441619432 | T93: 18296967181 | U93: 12296912093 | V93: 1.827635e+11
D94: Mei '23 | E94: 77862473528 | F94: 42154138663 | G94: 24954845784 | H94: 23320556234 | I94: 19070036539 | J94: 14750423023 | K94: 202112473771 | O94: Mei '22 | P94: 67813913664 | Q94: 42099644235 | R94: 23592145492 | S94: 23479968600 | T94: 18161087767 | U94: 13059102938 | V94: 188205862696
D95: Juni '23 | E95: 76257054071 | F95: 40247182404 | G95: 26708358628 | H95: 22679870255 | I95: 17200855224 | J95: 11687818582 | K95: 194781139164 | O95: Juni '22 | P95: 63438734426 | Q95: 38571076545 | R95: 26678051308 | S95: 21632744636 | T95: 17768750303 | U95: 12483811580 | V95: 180573168798
D96: Juli'23 | E96: 77865168121 | F96: 38267095100 | G96: 25221528267 | H96: 23318199657 | I96: 19059252389 | J96: 12401205323 | K96: 196132448857 | O96: Juli'22 | P96: 73654139193 | Q96: 42620328062 | R96: 27954075417 | S96: 24097747919 | T96: 17016190153 | U96: 13392430789 | V96: 198734911533
D97: Agustus'23 | E97: 79522703498 | F97: 37384413824 | G97: 24765485827 | H97: 23081422597 | I97: 25882864438 | J97: 11001712931 | K97: 201638603115 | O97: Agustus'22 | P97: 70845340351 | Q97: 43569322773 | R97: 27458595100 | S97: 23263340954 | T97: 17001158609 | U97: 12344740620 | V97: 194482498407
D98: September'23 | E98: 93681571805 | F98: 34557371317 | G98: 19494477851 | H98: 23550057789 | I98: 24150256506 | J98: 10161403671 | K98: 205595138939 | O98: September'22 | P98: 68748451512 | Q98: 40625158120 | R98: 27464457101 | S98: 22408250838 | T98: 18457788028 | U98: 11384146440 | V98: 189088252039
D99: Oktober'23 | E99: 79619577720 | F99: 41371573675 | G99: 17698126534 | H99: 25190028511 | I99: 24690331292 | J99: 12642851241 | K99: 201212488973 | O99: Oktober'22 | P99: 70520721028 | Q99: 43650791805 | R99: 28277753332 | S99: 24246079943 | T99: 17115520353 | U99: 9728415731 | V99: 193539282192
D100: November'23 | E100: 75416203670 | F100: 36409473467 | G100: 16844127395 | H100: 23656171438 | I100: 25250531264 | J100: 13468225713 | K100: 191044732947 | O100: November'22 | P100: 68457246022 | Q100: 43805745871 | R100: 25337904430 | S100: 23771082792 | T100: 17467337158 | U100: 8862221411 | V100: 187701537684
D101: Desember'23 | E101: 9.7001827e+10 | F101: 38504922662 | G101: 25118199594 | H101: 24893243278 | I101: 25437623982 | J101: 12553865667 | K101: 2.2350968e+11 | O101: Desember'22 | P101: 72412331182 | Q101: 46579901695 | R101: 29689685890 | S101: 24031748250 | T101: 21154827181 | U101: 13885456566 | V101: 207753950764
D102: Total | E102: 9.4901376e+11 | F102: 481969702083 | G102: 289400022126 | H102: 279666856479 | I102: 256077174821 | J102: 146689592542 | K102: 2.4028171e+12 | O102: Total | P102: 8.1963381e+11 | Q102: 503911579213 | R102: 315921355693 | S102: 271091100095 | T102: 216640038643 | U102: 141711971472 | V102: 2.2689099e+12
D105: Bulan | E105: Jumlah Hari | O105: Bulan | P105: Jumlah Hari
D106: Januari '23 | E106: 31 | O106: Januari '22 | P106: 31
D107: Februari '23 | E107: 28 | O107: Februari '22 | P107: 28
D108: Maret '23 | E108: 31 | O108: Maret '22 | P108: 31
D109: April '23 | E109: 30 | O109: April '22 | P109: 30
D110: Mei '23 | E110: 31 | O110: Mei '22 | P110: 31
D111: Juni '23 | E111: 30 | O111: Juni '22 | P111: 30
D112: Juli'23 | E112: 31 | O112: Juli'22 | P112: 31
D113: Agustus'23 | E113: 31 | O113: Agustus'22 | P113: 31
D114: September'23 | E114: 30 | O114: September'22 | P114: 30
D115: Oktober'23 | E115: 31 | O115: Oktober'22 | P115: 31
D116: November'23 | E116: 30 | O116: November'22 | P116: 30
...

Sheet Source
A1: Kembali ke Daftar Isi
B3: TINGKAT KEMUNGKINAN | C3: Hampir Pasti Terjadi | D3: 5 | E3: Low to Moderate 7 | F3: Moderate 12 | G3: Moderate to High 17 | H3: High 22 | I3: High 25
C8: Sangat Mungkin Terjadi | D8: 4 | E8: Low 4 | F8: Low to Moderate 9 | G8: Moderate 14 | H8: Moderate to High 19 | I8: High 24
C13: Bisa Terjadi | D13: 3 | E13: Low 3 | F13: Low to Moderate 8 | G13: Moderate 13 | H13: Moderate to High 18 | I13: High 23
C18: Jarang Terjadi | D18: 2 | E18: Low 2 | F18: Low to Moderate 6 | G18: Low to Moderate 11 | H18: Moderate to High 16 | I18: High 21
C23: Sangat Jarang Terjadi | D23: 1 | E23: Low 1 | F23: Low 5 | G23: Low to Moderate 10 | H23: Moderate 15 | I23: High 20
B28: INHEREN | E28: 1 | F28: 2 | G28: 3 | H28: 4 | I28: 5
E29: Sangat Rendah | F29: Rendah | G29: Moderat | H29: Tinggi | I29: Sangat Tinggi
E30: TINGKAT DAMPAK
B33: TINGKAT KEMUNGKINAN | C33: Hampir Pasti Terjadi | D33: 5 | E33: 7 | F33: 12 | G33: 17 | H33: 22 | I33: 25 | L33: WAJIB ISI | M33: Kuantitatif | N33: Transfer/sharing | P33: Low | Q33: Accept/Monitor | V33: SPI
C34: Sangat Mungkin Terjadi | D34: 4 | E34: 4 | F34: 9 | G34: 14 | H34: 19 | I34: 24 | L34: TIDAK WAJIB | M34: Kualitatif | N34: Reduce/mitigate | P34: Low To Moderat | Q34: Reduce/Mitigate | R34: Accept/Monitor | V34: SETPER
C35: Bisa Terjadi | D35: 3 | E35: 3 | F35: 8 | G35: 13 | H35: 18 | I35: 23 | N35: Accept/monitor | P35: Moderate | Q35: Reduce/Mitigate | V35: BID HCGA
C36: Jarang Terjadi | D36: 2 | E36: 2 | F36: 6 | G36: 11 | H36: 16 | I36: 21 | N36: Avoid/hindari | P36: Moderate to High | Q36: Reduce/Mitigate | R36: Accept/Monitor | V36: BID KEU
C37: Sangat Jarang Terjadi | D37: 1 | E37: 1 | F37: 5 | G37: 10 | H37: 15 | I37: 20 | P37: High | Q37: Reduce/Mitigate | R37: Hindari/Avoid | V37: BID REN
B38: RESIDUAL | D38: Q4 | E38: 1 | F38: 2 | G38: 3 | H38: 4 | I38: 5 | V38: BID MANPRO
E39: Sangat Rendah | F39: Rendah | G39: Moderat | H39: Tinggi | I39: Sangat Tinggi | V39: BID OPS
E40: TINGKAT DAMPAK | V40: BID K3L
L41: Low | M41: Low To Moderate | N41: Moderate | O41: Moderate To High | P41: High | V41: BID AGA
L42: Accept/Monitor | M42: Reduce/Mitigate | N42: Reduce/Mitigate | O42: Reduce/Mitigate | P42: Reduce/Mitigate | V42: BID BIS
B43: 1-5 low | M43: Accept/Monitor | O43: Transfer/Sharing | P43: Hindari/Avoid | V43: BID STRADA
B44: 6-11 low to moderate | V44: UB KITRANS
B45: 12-15 moderate | V45: UB BES
B46: 16-19 moderate to high | V46: UB MS
B47: 20-25 high | V47: UB DISYAN
V48: UB INFRA
B49: Skala Risiko | E49: 1 | F49: 4 | G49: 7 | H49: 10 | I49: 13 | J49: 16 | K49: 17 | L49: 18 | M49: 19 | N49: 20 | O49: 21 | P49: 22 | Q49: 23 | R49: 24 | S49: 25
B50: Level Risiko | E50: Low | F50: Low | G50: Low to Moderate | H50: Low to Moderate | I50: Moderate | J50: Moderate to High | K50: Moderate to High | L50: Moderate to High | M50: Moderate to High | N50: High | O50: High | P50: High | Q50: High | R50: High | S50: High
B52: INHEREN
B53: Nomor Risiko | D53: Skala | E53: 1 | F53: 4 | G53: 7 | H53: 10 | I53: 13 | J53: 16 | K53: 17 | L53: 18 | M53: 19 | N53: 20 | O53: 21 | P53: 22 | Q53: 23 | R53: 24 | S53: 25 | V53: Diisi dengan pilihan jenis rencana perlakuan risiko:
C54: 1 | D54: ='[10]Risiko Inheren Kuantitatif'!O9 -> 9 | V54: Peningkatan Kecukupan Desain Control
C55: 2 | D55: ='[10]Risiko Inheren Kuantitatif'!O10 -> 19 | M55: 2. | V55: Peningkatan Efektivitas Pelaksanaan Control
C56: 3 | D56: ='[10]Risiko Inheren Kuantitatif'!O11 -> 11 | J56: 3. | V56: Perbaikan Melalui Breakthrough Project
C57: 4 | D57: ='[10]Risiko Inheren Kuantitatif'!O12 -> 18 | I57: 4. | V57: Lainnya
C58: 5 | D58: ='[10]Risiko Inheren Kualitatif'!O9 -> 1 | E58: 5.
C59: 6 | D59: ='[10]Risiko Inheren Kualitatif'!O10 -> 13 | I59: 6.
C60: 7 | D60: ='[10]Risiko Inheren Kualitatif'!O11 -> 13 | I60: 7.
C61: 8 | D61: ='[10]Risiko Inheren Kualitatif'!O12 -> 14 | V61: Anggaran biaya perlakuan risiko telah dimasukkan dalam salah satu jenis program RKAP, dengan pilihan: - | X61: ANGGARAN | AA61: Kontrol operasi - level entitas/kantor pusat
C62: 9 | D62: ='[10]Risiko Inheren Kualitatif'!O13 -> 1 | E62: 9. | AA62: Kontrol operasi - level operasi
C63: 10 | D63: ='[10]Risiko Inheren Kualitatif'!O14 -> 7 | G63: 10. | V63: Pemasaran dan penjualan | X63: Anggaran Kas Investasi | AA63: Kontrol kepatuhan (compliance) - level entitas/kantor pusat
C64: 11 | D64: ='[10]Risiko Inheren Kuantitatif'!O13 -> 23 | Q64: 11. | V64: Pengadaan | X64: Anggaran Operasi | AA64: Kontrol kepatuhan (compliance) - level operasi
C65: 12 | D65: ='[10]Risiko Inheren Kualitatif'!O15 -> 1 | E65: 12. | V65: Produksi dan Kualitas Produk | AA65: Kontrol pelaporan - level entitas/kantor pusat
C66: 13 | D66: ='[10]Risiko Inheren Kualitatif'!O16 -> 13 | V66: Teknis dan Teknologi | AA66: Kontrol pelaporan - level operasi
C67: 14 | D67: ='[10]Risiko Inheren Kuantitatif'!O14 -> 2 | H67: 10. | V67: Keuangan dan Akuntansi
C68: 15 | D68: ='[10]Risiko Inheren Kuantitatif'!O15 -> 4 | F68: 15. | V68: Sistem dan Organisasi
C69: 16 | D69: ='[10]Risiko Inheren Kuantitatif'!O16 -> 17 | H69: 16. | V69: Pengembangan SDM
C70: 17 | D70: ='[10]Risiko Inheren Kuantitatif'!O17 -> 3 | V70: Penelitian dan Pengembangan
C71: 18 | D71: ='[10]Risiko Inheren Kuantitatif'!O18 -> 4 | V71: Pelestarian Lingkungan
C72: 19 | D72: ='[10]Risiko Inheren Kuantitatif'!O19 -> 7 | V72: Investasi
C73: 20 | D73: ='[10]Risiko Inheren Kuantitatif'!O20 -> 15 | F73: 20. | V73: Lainnya
C74: 21 | D74: ='[10]Risiko Inheren Kuantitatif'!O21 -> 1 | E74: 21.
C75: 22 | D75: ='[10]Risiko Inheren Kualitatif'!O18 -> 25 | S75: 22.
C76: 23 | D76: ='[10]Risiko Inheren Kuantitatif'!O22 -> 1 | E76: 23.
C77: 24 | D77: ='[10]Risiko Inheren Kuantitatif'!O23 -> 1 | E77: 24. | V77: 1. Cukup dan Efektif | X77: 1. Nilai ekonomi dan sosial
C78: 25 | D78: ='[10]Risiko Inheren Kuantitatif'!O24 -> 4 | F78: 25. | V78: 2. Cukup dan Efektif Sebagian | X78: 2. Inovasi bisnis model
C79: 26 | D79: ='[10]Risiko Inheren Kualitatif'!O19 -> 15 | V79: 3. Cukup dan Tidak Efektif | X79: 3. Kepemimpinan teknologi
C80: 27 | D80: ='[10]Risiko Inheren Kuantitatif'!O25 -> 3 | V80: 4. Tidak Cukup dan Efektif Sebagian | X80: 4. Peningkatan investasi
C81: 28 | D81: 21 & 6 | O81: 28. | V81: 5. Tidak Cukup dan Tidak Efektif | X81: 5. Pengembangan talenta
C82: 29 | D82: ='[10]Risiko Inheren Kuantitatif'!O28 -> 12 | X82: 6. Kepatuhan
C83: 30 | D83: ='[10]Risiko Inheren Kualitatif'!O20 -> 13 | I83: 30. | V83: 1. Risiko Fiskal - Dividen
C84: 31 | D84: ='[10]Risiko Inheren Kualitatif'!O21 -> 19 | V84: 2. Risiko Fiskal - PMN
C85: 32 | D85: ='[10]Risiko Inheren Kualitatif'!O22 -> 19 | V85: 3. Risiko Fiskal - Subsidi & Kompensasi
C86: 33 | D86: ='[10]Risiko Inheren Kualitatif'!O23 -> 10 | H86: 33. | V86: 4. Risiko Kebijakan - SDM
C87: 34 | D87: ='[10]Risiko Inheren Kuantitatif'!O29 -> 3 | V87: 5. Risiko Kebijakan - Sektoral
C88: 35 | D88: ='[10]Risiko Inheren Kualitatif'!O24 -> 16 | J88: 35 | V88: 6. Risiko Komposisi - Konsentrasi Portofolio
C89: 36 | D89: ='[10]Risiko Inheren Kuantitatif'!O30 -> 4 | F89: 36. | V89: 7. Risiko Struktur - Struktur Korporasi
C90: 37 | D90: ='[10]Risiko Inheren Kuantitatif'!O31 -> 14 | V90: 8. Risiko Restrukturisasi & Reorganisasi - Penggabungan, Pengambilalihan, Peleburan, Pemisahan, Pembubaran, Likuidasi, Kemitraan, dan Restrukturisasi
C91: 38 | D91: ='[10]Risiko Inheren Kuantitatif'!O32 -> 5 | V91: 9. Risiko Industri Umum - Formulasi Strategis
C92: 39 | D92: ='[10]Risiko Inheren Kuantitatif'!O33 -> 20 | N92: 39. | V92: 10. Risiko Industri Umum - Pasar & Makroekonomi
B93: Kompilasi | E93: =E54&E55&E56&E57&E58&E59&E60&E61&E62&E63&E64&E65&E66&E67&E68&E69&E70&E71&E72&E73&E74&E75&E76&E77&E78&E79&E80&E81&E82&E83&E84&E85&E86&E87&E88&E89&E90&E91&E92 -> 5.9.12.21.23.24. | F93: =F54&F55&F56&F57&F58&F59&F60&F61&F62&F63&F64&F65&F66&F67&F68&F69&F70&F71&F72&F73&F74&F75&F76&F77&F78&F79&F80&F81&F82&F83&F84&F85&F86&F87&F88&F89&F90&F91&F92 -> 15.20.25.36. | G93: =G54&G55&G56&G57&G58&G59&G60&G61&G62&G63&G64&G65&G66&G67&G68&G69&G70&G71&G72&G73&G74&G75&G76&G77&G78&G79&G80&G81&G82&G83&G84&G85&G86&G87&G88&G89&G90&G91&G92 -> 10. | H93: =H54&H55&H56&H57&H58&H59&H60&H61&H62&H63&H64&H65&H66&H67&H68&H69&H70&H71&H72&H73&H74&H75&H76&H77&H78&H79&H80&H81&H82&H83&H84&H85&H86&H87&H88&H89&H90&H91&H92 -> 10.16.33. | I93: =I54&I55&I56&I57&I58&I59&I60&I61&I62&I63&I64&I65&I66&I67&I68&I69&I70&I71&I72&I73&I74&I75&I76&I77&I78&I79&I80&I81&I82&I83&I84&I85&I86&I87&I88&I89&I90&I91&I92 -> 4.6.7.30. | J93: =J54&J55&J56&J57&J58&J59&J60&J61&J62&J63&J64&J65&J66&J67&J68&J69&J70&J71&J72&J73&J74&J75&J76&J77&J78&J79&J80&J81&J82&J83&J84&J85&J86&J87&J88&J89&J90&J91&J92 -> 3.35 | K93: =K54&K55&K56&K57&K58&K59&K60&K61&K62&K63&K64&K65&K66&K67&K68&K69&K70&K71&K72&K73&K74&K75&K76&K77&K78&K79&K80&K81&K82&K83&K84&K85&K86&K87&K88&K89&K90&K91&K92 | L93: =L54&L55&L56&L57&L58&L59&L60&L61&L62&L63&L64&L65&L66&L67&L68&L69&L70&L71&L72&L73&L74&L75&L76&L77&L78&L79&L80&L81&L82&L83&L84&L85&L86&L87&L88&L89&L90&L91&L92 | ... S93: =S54&S55&S56&S57&S58&S59&S60&S61&S62&S63&S64&S65&S66&S67&S68&S69&S70&S71&S72&S73&S74&S75&S76&S77&S78&S79&S80&S81&S82&S83&S84&S85&S86&S87&S88&S89&S90&S91&S92 -> 22. | V93: 11. Risiko Industri Umum - Keuangan
V94: 12. Risiko Industri Umum - Reputasi & Kepatuhan
V95: 13. Risiko Industri Umum - Proyek
B96: RESIDUAL | D96: Q4 | V96: 14. Risiko Industri Umum - Teknologi & Keamanan Siber
B97: Nomor Risiko | D97: Skala | E97: 1 | F97: 4 | G97: 7 | H97: 10 | I97: 13 | J97: 16 | K97: 17 | L97: 18 | M97: 19 | N97: 20 | O97: 21 | P97: 22 | Q97: 23 | R97: 24 | S97: 25 | V97: 15. Risiko Industri Umum - Sosial & Lingkungan
C98: 1 | D98: 1 | E98: 1. | V98: 16. Risiko Industri Umum - Operasional
C99: 2 | D99: 5 | V99: 17. Risiko Industri Perbankan - Kredit
C100: 3 | D100: 5 | V100: 18. Risiko Industri Perbankan - Likuiditas
C101: 4 | D101: 2 | V101: 19. Risiko Industri Asuransi - Investasi
C102: 5 | D102: 1 | E102: 5. | V102: 20. Risiko Industri Asuransi - Aktuarial
C103: 6 | D103: 5 | V103: 21. Risiko lainnya
C104: 7 | D104: 5
C105: 8 | D105: 1 | E105: 8.
C106: 9 | D106: 2
C107: 10 | D107: 1 | E107: 10.
C108: 11 | D108: ='[10]Risiko Inheren Kuantitatif'!O56 -> 0
C109: 12 | D109: 1 | E109: 12.
C110: 13 | D110: 5
C111: 14 | D111: 1 | E111: 14.
C112: 15 | D112: 3
C113: 16 | D113: 9
C114: 17 | D114: 2
C115: 18 | D115: 2
C116: 19 | D116: 1 | E116: 19.
C117: 20 | D117: 8
C118: 21 | D118: 2
C119: 22 | D119: 2
C120: 23 | D120: 1 | E120: 23.
C121: 24 | D121: 1 | E121: 24.
C122: 25 | D122: 4 | F122: 25.
C123: 26 | D123: 2
C124: 27 | D124: 1 | E124: 27.
...

Sheet Taksonomi Risiko PLN
A1: LAMPIRAN I PETUNJUK TEKNIS NOMOR PEMETAAN HIERARKI TAKSONOMI RISIKO PLN
A2: T1 (Terna Risiko) | I2: T2 | Q2: T3 (Kelomook Peristiwa Risiko) | T2: T4 (Sub Kelomook Peristiwa Risiko)
L3: Kateciori Risiko)
A4: 1 | B4: Terna Risiko Portofolio BUMN | I4: 1.1. | L4: Kategori Risiko fiskal | Q4: 1.1 | R4: Peristiwa Risiko terkait dividen | T4: 1.1.1 | U4: Risiko pembayaran dividen | AA4: =CONCATENATE(Q4," ",R4) -> 1.1 Peristiwa Risiko terkait dividen
Q5: 1.1.2 | R5: Peristiwa Risiko terkait Penyertaan Modal Negara (PMN) | T5: 1.1.2.2 | U5: Risiko penerimaan PMN | AA5: =CONCATENATE(Q5," ",R5) -> 1.1.2 Peristiwa Risiko terkait Penyertaan Modal Negara (PMN)
T6: 1.1.2.3 | U6: Risiko penggunaan PMN | AA6: =CONCATENATE(Q6," ",R6)
Q7: 1.1.3 | R7: Peristiwa Risiko terkait subsidi dan kompensasi | T7: 1.1.3.4 | U7: Risiko kompensasi | AA7: =CONCATENATE(Q7," ",R7) -> 1.1.3 Peristiwa Risiko terkait subsidi dan kompensasi
T8: 1.1.3.5 | U8: Risiko subsidi | AA8: =CONCATENATE(Q8," ",R8)
I9: 1.2 | L9: Kategori Risiko kebijakan | Q9: 1.2.4 | R9: Peristiwa Risiko terkait kebijakan Sumber Daya Manusia (SOM) | T9: 1.2.4.6 | U9: Risiko kebijakan SOM | AA9: =CONCATENATE(Q9," ",R9) -> 1.2.4 Peristiwa Risiko terkait kebijakan Sumber Daya Manusia (SOM)
T10: 1.2.4.7 | U10: Risiko penerapan kebijakan pemilihan, pengangkatan dan Direksi dan Dewan Komisaris | AA10: =CONCATENATE(Q10," ",R10)
T11: 1.2.4.8 | U11: Risiko penetapan Key Performance Indicator (KPI) Direksi dan Dewan Komisaris | AA11: =CONCATENATE(Q11," ",R11)
Q12: 1.2.5 | R12: Peristiwa Risiko terkait kebijakan sektoral | T12: 1.2.5.9 | U12: Risiko kebijakan terkait sektor energi | AA12: =CONCATENATE(Q12," ",R12) -> 1.2.5 Peristiwa Risiko terkait kebijakan sektoral
T13: 1.2.5.10 | U13: Risiko kebijakan terkait sektor non energi | AA13: =CONCATENATE(Q13," ",R13)
I14: 1.3 | L14: Kategori Risiko komposisi | Q14: 1.3.6 | R14: Peritiwa Risiko terkait konsentrasi portofolio | T14: 1.3.6.11 | U14: Risiko konsentrasi portfolio aset | AA14: =CONCATENATE(Q14," ",R14) -> 1.3.6 Peritiwa Risiko terkait konsentrasi portofolio
A15: T1 (Terna Risiko) | I15: T2 | Q15: T3 (Kelompok Peristiwa Risiko) | T15: T4 (Sub Kelompok Peristiwa Risiko)
L16: KateQori Risiko) | AA16: =CONCATENATE(Q16," ",R16)
T17: 1.3.6.12 | U17: Risiko konsentrasi portfolio pendapatan | AA17: =CONCATENATE(Q17," ",R17)
T18: 1.3.6.13 | U18: Risiko konsentrasi operasional | AA18: =CONCATENATE(Q18," ",R18)
A19: 2 | B19: Terna Risiko struktur korporasi dan organisasi | I19: 2.4 | L19: Kategori Risiko struktur korporasi | Q19: 2.4.7 | R19: Peristiwa Risiko terkait struktur korporasi | T19: 2.4.7.14 | U19: Risiko kompleksitas struktur perusahaan | AA19: =CONCATENATE(Q19," ",R19) -> 2.4.7 Peristiwa Risiko terkait struktur korporasi
T20: 2.4.7.15 | U20: Risiko penyertaan dan kerja sama | AA20: =CONCATENATE(Q20," ",R20)
I21: 2.5 | L21: Kategori Risiko restrukturisas i dan reorganisasi | Q21: 2.5.8 | R21: Peristiwa Risiko terkait penggabungan, pengambilalihan , peleburan, pemisahan, pembubaran, likuidasi, dan restrukturisasi | T21: 2.5.8.16 | U21: Risiko merg er, akuisisi, kerja sama strategis dan privatisasi | AA21: =CONCATENATE(Q21," ",R21) -> 2.5.8 Peristiwa Risiko terkait penggabungan, pengambilalihan , peleburan, pemisahan, pembubaran, likuidasi, dan restrukturisasi
T22: 2.5.8.17 | U22: Risiko perubahan struktur organisasi | AA22: =CONCATENATE(Q22," ",R22)
A23: 3 | B23: Terna Risiko bisnis BUMN | I23: 3.6 | L23: Kategori Risiko industri umum | Q23: 3.6.9 | R23: Peristiwa Risiko terkait formulasi strategis | T23: 3.6.9.18 | U23: Risiko kinerja Perusahaan | AA23: =CONCATENATE(Q23," ",R23) -> 3.6.9 Peristiwa Risiko terkait formulasi strategis
T24: 3.6.9.19 | U24: Risiko analisa lingkungan bisnis | AA24: =CONCATENATE(Q24," ",R24)
T25: 3.6.9.20 | U25: Risiko perencanaan strategis | AA25: =CONCATENATE(Q25," ",R25)
T26: 3.6.9.21 | U26: Risiko eksekusi strategis | AA26: =CONCATENATE(Q26," ",R26)
Q27: 3.6.10 | R27: Peristiwa Risiko terkait pasar dan makro ekonomi | T27: 3.6.10.22 | U27: Risiko harga komoditas | AA27: =CONCATENATE(Q27," ",R27) -> 3.6.10 Peristiwa Risiko terkait pasar dan makro ekonomi
T28: 3.6.10.23 | U28: Risiko kondisi ekonomi global | AA28: =CONCATENATE(Q28," ",R28)
T29: 3.6.10.24 | U29: Risiko suku bunga | AA29: =CONCATENATE(Q29," ",R29)
T30: 3.6.10.25 | U30: Risiko nilai tukar | AA30: =CONCATENATE(Q30," ",R30)
T31: 3.6.10.26 | U31: Risiko politik & geopolitik | AA31: =CONCATENATE(Q31," ",R31)
A32: T1 (Terna Risiko) | I32: T2 | Q32: T3 (Kelompok Peristiwa Risiko) | T32: T4 (Sub Kelompok Peristiwa Risiko)
L33: Kateaori Risiko) | AA33: =CONCATENATE(Q33," ",R33)
T34: 3.6.10.27 | U34: Risiko perdagangan internasional | AA34: =CONCATENATE(Q34," ",R34)
T35: 3.6.10.28 | U35: Risiko kebijakan moneter & fiskal | AA35: =CONCATENATE(Q35," ",R35)
Q36: 3.6.11 | R36: Peristiwa Risiko terkait keuangan | T36: 3.6.11.29 | U36: Risiko asuransi | AA36: =CONCATENATE(Q36," ",R36) -> 3.6.11 Peristiwa Risiko terkait keuangan
T37: 3.6.11.30 | U37: Risiko pendanaan | AA37: =CONCATENATE(Q37," ",R37)
T38: 3.6.11.31 | U38: Risiko perpajakan | AA38: =CONCATENATE(Q38," ",R38)
T39: 3.6.11.32 | U39: Risiko anggaran & akuntansi | AA39: =CONCATENATE(Q39," ",R39)
T40: 3.6.11.33 | U40: Risiko pengelolaan modal kerja | AA40: =CONCATENATE(Q40," ",R40)
T41: 3.6.11.34 | U41: Risiko arus kas | AA41: =CONCATENATE(Q41," ",R41)
T42: 3.6.11.35 | U42: Risiko piutang | AA42: =CONCATENATE(Q42," ",R42)
T43: 3.6.11.36 | U43: Risiko integritas penyusunan laporan keuangan | AA43: =CONCATENATE(Q43," ",R43)
Q44: 3.6.12 | R44: Peristiwa Risiko terkait hukum, reputasi, dan kepatuhan | T44: 3.6.12.37 | U44: Risikoreputasi | AA44: =CONCATENATE(Q44," ",R44) -> 3.6.12 Peristiwa Risiko terkait hukum, reputasi, dan kepatuhan
T45: 3.6.12.38 | U45: Risiko kepatuhanterhadap peraturan dan kebijakan | AA45: =CONCATENATE(Q45," ",R45)
T46: 3.6.12.39 | U46: Risiko litigasi/hukum | AA46: =CONCATENATE(Q46," ",R46)
T47: 3.6.12.40 | U47: Risiko fraud | AA47: =CONCATENATE(Q47," ",R47)
Q48: 3.6.13 | R48: Peristiwa Risiko terkait proyek | T48: 3.6.13.41 | U48: Risiko perencanaanproyek | AA48: =CONCATENATE(Q48," ",R48) -> 3.6.13 Peristiwa Risiko terkait proyek
T49: 3.6.13.42 | U49: Risiko pemilihan penyedia barang jasa/mitra/ konsorsium | AA49: =CONCATENATE(Q49," ",R49)
T50: 3.6.13.43 | U50: Risiko eksekusi proyek | AA50: =CONCATENATE(Q50," ",R50)
T51: 3.6.13.44 | U51: Risiko penyelesaianproyek | AA51: =CONCATENATE(Q51," ",R51)
A52: T1 (Terna Risiko) | I52: T2 | Q52: T3 (Kelomook Peristiwa Risiko) | T52: T4 (Sub Kelomook Peristiwa Risiko)
L53: Kateaori Risiko) | AA53: =CONCATENATE(Q53," ",R53)
Q54: 3.6.14 | R54: Peristiwa Risiko terkait teknologi informasi dan keamanan siber | T54: 3.6.14.45 | U54: Risiko teknologi informasi | AA54: =CONCATENATE(Q54," ",R54) -> 3.6.14 Peristiwa Risiko terkait teknologi informasi dan keamanan siber
T55: 3.6.14.46 | U55: Risiko keamanan siber | AA55: =CONCATENATE(Q55," ",R55)
Q56: 3.6.15 | R56: Peristiwa Risiko terkait sosial dan lingkungan | T56: 3.6.15.47 | U56: Risiko sosial | AA56: =CONCATENATE(Q56," ",R56) -> 3.6.15 Peristiwa Risiko terkait sosial dan lingkungan
T57: 3.6.15.48 | U57: Risiko lingkungan | AA57: =CONCATENATE(Q57," ",R57)
T58: 3.6.15.49 | U58: Risiko transisi energi | AA58: =CONCATENATE(Q58," ",R58)
Q59: 3.6.16 | R59: Peristiwa Risiko terkait operasional | T59: 3.6.16.50 | U59: Risiko rantai pasok | AA59: =CONCATENATE(Q59," ",R59) -> 3.6.16 Peristiwa Risiko terkait operasional
T60: 3.6.16.51 | U60: Risiko Kesehatan Keselamatan Kerja (K3) | AA60: =CONCATENATE(Q60," ",R60)
T61: 3.6.16.52 | U61: Risiko proses internal | AA61: =CONCATENATE(Q61," ",R61)
T62: 3.6.16.53 | U62: Risiko sistem | AA62: =CONCATENATE(Q62," ",R62)
T63: 3.6.16.54 | U63: Risiko energi primer | AA63: =CONCATENATE(Q63," ",R63)
T64: 3.6.16.55 | U64: Risiko pembangkit | AA64: =CONCATENATE(Q64," ",R64)
T65: 3.6.16.56 | U65: Risiko transmisi | AA65: =CONCATENATE(Q65," ",R65)
T66: 3.6.16.57 | U66: Risiko distribusi | AA66: =CONCATENATE(Q66," ",R66)
T67: 3.6.16.58 | U67: Risiko niaga | AA67: =CONCATENATE(Q67," ",R67)
A68: LAMPIRAN II PETUNJUK TEKNIS NOMOR TAKSONOMI RISIKO PLN TINGKAT 3 (T3)
A69: No | C69: Kelompok Peristiwa Risiko {T3) | O69: Pengertian
A70: 1 | C70: Risiko terkait dividen | O70: Peristiwa Risiko yang disebabkan oleh kegagalan dalam pembayaran dividen kepada Anggaran Pendapatan dan Belanja Negara (APBN)
A71: 2 | C71: Risiko terkait Penyertaan Modal Negara (PMN) | O71: Peristiwa Risiko yang disebabkan oleh proses penerimaan dan penggunaan PMN
A72: 3 | C72: Risiko terkaitsubsidi dan kompensasi | O72: PeristiwaRisiko yang disebabkan oleh kekurangan dan keterlambatanpenerimaan subsidi dan kompensasi
A73: 4 | C73: Risiko terkait kebijakan SOM | O73: Peristiwa Risiko yang disebabkan oleh penerapan kebijakan pemilihan, pengangkatan dan penetapan KPI Direksi dan Dewan Komisaris atau Dewan PengawasBUMN serta kebijakan SOM BUMN
A74: 5 | C74: Risiko terkait kebijakan sektoral | O74: Peristiwa Risiko yang disebabkan oleh ketidakselarasan kebijakan yang dikeluarkan oleh Kementerian Teknis dan lembaga regulator yang dapat mempengaruhi ketidakpastian penerimaanatau operasi BUMN secara material
A75: 6 | C75: Risiko terkait konsentrasi portofolio | O75: Peristiwa Risiko yang ditimbulkan oleh komposisi Portofolio BUMN yang terkonsentrasipada industri tertentu
A76: 7 | C76: Risiko terkait strukturkorporasi | O76: Peristiwa Risiko yang ditimbulkan oleh struktur korporasi BUMN yang kompleks, termasuk penyertaan dan kerja sama operasi dan/atau tidak transparan yang dapat menimbulkan ketidakpastian yang material atas kinerja BUMN dan/atau menimbulkan kewajiban- kewajiban bagi induk BUMN terhadap komitmen yang dilakukan oleh Anak Perusahaan
A77: 8 | C77: Risiko terkait penggabungan, pengambilalihan, peleburan, pemisahan, pembubaran, likuidasi, kemitraan dan restrukturisasi | O77: Peristiwa Risiko yang disebabkan oleh transaksi aksi korporasi atas penggabungan, pengambilalihan, peleburan, pemisahan, pembubaran, likuidasi, kemitraan, dan restrukturisasi yang material yang dapat mempengaruhi posisi strategis BUMN di masa yang akan datang. Peristiwa Risiko ini terkait dengan proses implementasi kegiatan penggabungan,
A78: No | C78: Kelompok Peristiwa Risiko (T3) | O78: Pengertian
O79: pengambilalihan, peleburan, pemisahan, pembubaran, likuidasi, kemitraan,dan restrukturisasi dan selanjutnya dapat diklasifikasikan menjadi Risiko ketidaktercapaian sinergitas yang diharapkan, Risiko struktur perkontrakan yang lemah, Risiko keuangan, Risiko perpajakan, dan Risiko integrasi pasca kegiatan merger dan akuisisi
A80: 9 | C80: Risiko terkait formulasi strategis | O80: Peristiwa Risiko yang disebabkan oleh ketidakpastian kondisi BUMN dalam peta industri dimana BUMN tersebut beroperasi, termasuk ketidaktepatan arahan kebijakan strategis masing-masing BUMN yang dapat memberikan dampak yang material terhadap posisi BUMN dalam industri di mana BUMN tersebutberoperasi
A81: 10 | C81: Risiko terkait pasar dan makro ekonomi | O81: Peristiwa Risiko yang disebabkanoleh pergerakan-pergerakan variabel makro ekonomi global seperti pergerakan tingkat bunga referensi, pergerakan nilai tukar rupiah, dan/atau pergerakan harga-harga komoditas yang tidak dapat dikendalikan oleh BUMN
A82: 11 | C82: Risiko terkait keuangan | O82: Peristiwa Risiko yang disebabkan oleh struktur dan akses pendanaan, terkait perpajakan, anggaran, akuntansi, piutang, pengelolaan modal kerja dan arus kas serta Risiko integritas alas penyusunandan pelaporan keuangan
A83: 12 | C83: Risiko terkail hukum, reputasi dan kepatuhan | O83: Peristiwa Risiko yang disebabkan oleh tindakan dan/atau tuntutan hukum, kecurangandalam konteks korupsi, kolusi dan nepotisme, perburukan reputasi BUMN dan ketidakpatuhanpada peraturan perundang-undangan yang berlaku yang dapat berpengaruh terhadap reputasi dan kinerja BUMN
A84: 13 | C84: Risiko terkait proyek | O84: Peristiwa Risiko yang disebabkanoleh proyek- proyek yang dijalankan oleh BUMN mulai dari perencanaanproyek, pemilihan konsorsium, Risiko kontraktual proyek, Risiko eksekusi proyek dan penyelesaian proyek. Risiko ini terutama berasal dari BUMN yang memiliki sumber pendapatan yang berasal dari kontrak-kontrak jangka panjang, dan atau BUMN yang sedang menjalankan proyek jangka panjang untuk kepentingan ekspansi
A85: 14 | C85: Risiko terkait teknologiinformasidan keamanan siber | O85: Risiko yang disebabkan oleh kegagalan perangkat lunak, perangkat keras, jaringan, atau sistem teknologi informasi lainnya pada BUMN termasuk Risiko yang diakibatkan oleh serangan siber (cybe r attacks), kehilangan data, pelanggaran privasi, manipulasi data berbahaya, dan/atau pengelolaan akses data
A86: No | C86: Kelompok Peri stiwa Risiko (T3) | O86: Pengertian
A87: 15 | C87: Risiko terkait sosial dan lingkungan | O87: Potensi eksposur yang disebabkan oleh peristiwa perubahan iklim fisik, dan/atau Risiko transisi terkait perubahan kebijakan lingkungan, Risiko terkait hubungan yang tidak baik dengan komunitas/masyarakat sekitar dan social engagement
A88: 16 | C88: Risiko terkait operasional | O88: Potensi kerugian yang disebabkan oleh proses internal, kegagalan sistem, kecelakaan dalam kesehatan keselamatan kerja, kesalahan manusia, atau kejadian eksternal (seperti gangguan rantai pasok, logistik, dan lain sebagainya) yang mempengaruhi operasi bisnis sehari-hari
A90: TAKSONOMI RISIKO PLN TINGKAT 4 (T4}
A91: No | C91: Sub Kelompok Peristiwa Risiko (T4) | J91: Pengertian | S91: Contoh Peristiwa Risiko
A92: 1 | C92: Risiko pembayaran dividen | J92: Risiko terkait ketidakmampuan Perusahaan untuk membayarkan dividen yang disebabkan oleh kondisi keuangan yang tidak stabil mengakibatkan kehilangkan potensi investasi bagi pemegang saham | S92: a. Ketidakmampuan Perusahaan untuk membayarkan dividen; b. Penghentian pembayaran dividen kepada pemegang saham; C. {dapat ditambahkan sesuai konteks peristiwa risiko pada satuan keria masinq-masinq)
A93: 2 | C93: Risiko penerimaan PMN | J93: Risiko terkait penurunan alokasi PMN atau risiko penolakan usulan penambahan dana PMN yang disebabkan, diantaranya, kebijakan fiskal yang lebih ketat atau perubahan prioritas investasi Pemerintah | S93: a. Keterlambatan penerimaan PMN b. Tidak disetujuinya usulan PMN C. (dapat ditambahkan sesuai konteks perisliwa risiko pada satuan kerja masing-masing)
A94: 3 | C94: Risiko penggunaan PMN | J94: Risiko terkait inefisiensi pengelolaan dana PMN atau risiko kegagalan implementasi proyek PMN yang disebabkan, diantaranya, kurangnya pengawasan atau kesalahan dalam perencanaan proyek. | S94: a. Kurangnya pengawasan dalam pengambilan keputusan investasi b. Ketidakcocokan alokasi dana dengan prioritas Pemerintah C. (dapat ditambahkan sesuai konteks peristiwa risiko pada satuan keria masing-masinq)
A95: 4 | C95: Risiko kompensasi | J95: Risiko terkait penundaan pembayaran kompensasi atau kemungkinan ketidaksesuaian pembayaran kompensasi yang diterima yang disebabkan, diantaranya, perubahan kebijakan Pemerintah atau perubahan skema subsidi energi | S95: a. Keterlambatan pembayaran kompensasi b. Ketidaktepatan perhitungan nilai kompensasi C. (dapat ditambahkan sesuai konteks peristiwa risiko pada satuan kerja masing-masing)
A96: 5 | C96: Risiko subsidi | J96: Risiko terkait penundaan pembayaran subsidi atau kelidakpastian jumlah pembayaran subsidi yang | S96: a. Penundaan pembayaran subsidi b. Perubahan skema subsidi energi
J97: disebabkan, diantaranya, perubahan prioritas anggaran Pemerintah atau fluktuasi ekonomi | S97: C. (dapat ditambahkan sesuai konteks peristiwa risiko pada satuan kerja masing-masing)
A98: 6 | C98: Risiko kebijakan SDM | J98: Risiko yang timbul dari keputusan, tindakan, atau perubahan dalam kebijakan yang berpengaruh pada aspek sumber daya manusia. | S98: a. Penempatan pegawai tidak sesuai kompetensi b. Suksesi jabatan tidak berkesinambungan C. (dapat ditambahkan sesua i konteks peristiwa risiko pada satuan keria masino-masinq)
A99: 7 | C99: Risiko penerapan kebijakan pemilihan, pengangkatan dan Direksi dan Dewan Komisaris | J99: Risiko terkait dengan performa Direksi dan Dewan Komisaris dalam menjalankan perusahaan sesuai prinsip Good Corporate Governance (GCG) | S99: a. Kegagalan Direksi atau Dewan Komisaris dalam penerapan prinsip GCG b. Kurangnya kriteria seleksi Direksi atau Dewan Komisaris C. (dapat ditambahkan sesuai konteks peristiwa risiko pada satuan kerja masing-masing)
A100: 8 | C100: Risiko penetapan KPI Direksi dan Dewan Komisaris | J100: Risiko yang berkaitan dengan potensi dampak negatif yang dapat terjadi jika KPI yang ditetapkan untuk mengukur kinerja para pejabat eksekutif dan pengawas tidak dirancang atau diterapkan dengan benar. | S100: a. Ketidaksesuaian sasaran KPI Direksi dan Dewan Komisaris dengan Aspirasi Pemegang Saham (APS) atau arahan strategis b. Tidak terintegrasinya KPI Direksi antara Direktorat C. (dapat ditambahkan sesuai konteks peristiwa risiko pada satuan keria masinq-masinq)
A101: 9 | C101: Risiko kebijakan terkait sektor energi | J101: Risiko ketidakstabilan Perusahaan akibat perubahan kebijakan dan regulasi yang mempengaruhi industri sektor energi. | S101: a. Perubahan model bisnis yang merugikanPLN b. Tidak tercapainya target net zero emmision C. (dapat ditambahkan sesuai konteks peristiwa risiko pada satuan keria masino-masinq)
...

Sheet Perhitungan Heatmap
B2: 1-5 low
B3: 6-11 low to moderate
B4: 12-15 moderate
B5: 16-19 moderate to high
B6: 20-25 high
B7: Skala Dampak | D7: 1 | E7: 1 | F7: 1 | G7: 1 | H7: 2 | I7: 2 | J7: 1 | K7: 2 | L7: 2 | M7: 3 | N7: 3 | O7: 2 | P7: 3
B8: Skala Probabilitas | D8: 1 | E8: 2 | F8: 3 | G8: 4 | H8: 1 | I8: 2 | J8: 5 | K8: 3 | L8: 4 | M8: 1 | N8: 2 | O8: 5 | P8: 3
B9: Skala Risiko | D9: 1 | E9: 2 | F9: 3 | G9: 4 | H9: 5 | I9: 6 | J9: 7 | K9: 8 | L9: 9 | M9: 10 | N9: 11 | O9: 12 | P9: 13 | Q9: 14 | R9: 15 | S9: 16 | T9: 17 | U9: 18 | V9: 19 | W9: 20 | X9: 21 | Y9: 22 | Z9: 23 | AA9: 24 | AB9: 25
B10: Level Risiko | D10: Low | E10: Low | F10: Low | G10: Low | H10: Low | I10: Low To Moderate | J10: Low To Moderate | K10: Low To Moderate | L10: Low To Moderate | M10: Low To Moderate | N10: Low To Moderate | O10: Moderate | P10: Moderate | Q10: Moderate | R10: Moderate | S10: Moderate To High | T10: Moderate To High | U10: Moderate To High | V10: Moderate To High | W10: High | X10: High | Y10: High | Z10: High | AA10: High | AB10: High

Sheet Profil Risiko
A1: Kembali ke Daftar Isi
A2: Data Item | B2: No. | C2: Nama BUMN | D2: Kode BUMN | E2: Sasaran BUMN | F2: Sasaran KBUMN | G2: Kategori Risiko BUMN | H2: Kategori Risiko T2 & T3 KBUMN | I2: No. Risiko | J2: Peristiwa Risiko | K2: Deskripsi Peristiwa risiko | L2: No. Penyebab Risiko | M2: Kode Penyebab risiko | N2: Penyebab risiko | O2: Key Risk Indicators | P2: Unit Satuan KRI | Q2: Kategori Threshold KRI | T2: Jenis Existing Control | U2: Existing Control | V2: Penilaian Efektivitas Kontrol | W2: Kategori Dampak | X2: Deskripsi Dampak | Y2: Perkiraan Waktu Terpapar Risiko
Q3: Aman | R3: Hati-Hati | S3: Bahaya
A4: Jenis Data | B4: Number | C4: Dropdown list | D4: Formula | E4: Free Text | F4: Dropdown list | G4: Free Text | H4: Dropdown list | I4: Number | J4: Free Text | K4: Free Text | L4: Alphabet | M4: Formula | N4: Free Text | O4: Free Text/Ratio/Number | P4: Free Text/Ratio/Number | Q4: Free Text/Ratio/Number | R4: Free Text/Ratio/Number | S4: Free Text/Ratio/Number | T4: Dropdown List | U4: Free Text | V4: Dropdown list | W4: Dropdown list | X4: Free Text | Y4: Free Text
A5: Petunjuk | D5: Kolom ini tidak perlu diisi. Akan diisi oleh Kementerian BUMN | E5: Diisi sesuai dengan sasaran BUMN | F5: Diisi dengan pilihan sasaran Kementerian BUMN yang meliputi: 1) Nilai ekonomi dan sosial; 2) Inovasi bisnis model; 3) Kepemimpinan teknologi; 4) Peningkatan investasi; dan 5) Pengembangan talenta. | G5: Diisi dengan Taksonomi Risiko yang berlaku pada masing-masing BUMN | H5: Diisi dengan pilihan kategori risiko Portofolio BUMN Kementerian BUMN berikut: 1. Risiko Fiskal - Dividen 2. Risiko Fiskal - PMN 3. Risiko Fiskal - Subsidi & Kompensasi 4. Risiko Kebijakan - SDM 5. Risiko Kebijakan - Sektoral 6. Risiko Komposisi - Konsentrasi Portofolio 7. Risiko Struktur - Struktur Korporasi 8. Risiko Restrukturisasi & Reorganisasi - Penggabungan, Pengambilalihan, Peleburan, Pemisahan, Pembubaran, Likuidasi, Kemitraan, dan Restrukturisasi 9. Risiko Industri Umum - Formulasi Strategis 10. Risiko Industri Umum - Pasar & Makroekonomi 11. Risiko Industri Umum - Keuangan 12. Risiko Industri Umum - Reputasi & Kepatuhan 13. Risiko Industri Umum - Proyek 14. Risiko Industri Umum - Teknologi & Keamanan Siber 15. Risiko Industri Umum - Sosial & Lingkungan 16. Risiko Industri Umum - Operasional 17. Risiko Industri Perbankan - Kredit 18. Risiko Industri Perbankan - Likuiditas 19. Risiko Industri Asuransi - Investasi 20. Risiko Industri Asuransi - Aktuarial | I5: Diisi dengan nomor urutan risiko | J5: Diisi dengan peristiwa risiko yang relevan. | K5: Penjelasan /narasi atas peristiwa risiko | L5: Diisi dengan nomor urutan penyebab risiko | M5: Kodifikasi untuk penyebab risiko (Setiap penyebab risiko diberikan unique ID, misal PTPI - 1. xxx") | N5: Diisi penyebab risiko secara jelas. BUMN dapat menggali berbagai penyebab risiko. Sebagai contoh dapat melihat dari berbagai segi: people, process, network, maupun system. | O5: Setiap peristiwa risiko harus memiliki minimal satu KRI | P5: Unit satuan KRI bisa berbentuk amount,/percentage/range/kualitatif | Q5: Diisi sesuai dengan batasan yang ditetapkan oleh masing-masing BUMN | T5: Diisi dengan pilihan pada hirarki pertama: - Kontrol operasi - Kontrol kepatuhan (compliance) - Kontrol pelaporan Setelah hirarki pertama dipilih, dilanjutkan dengan pilihan hirarki kedua: - Kontrol pada level entitas/kantor pusat - Kontral pada level operasi | U5: BUMN dapat mengisikan semua existing control yang relevan terhadap suatu risiko. Existing control tersebut dapat berupa kontrol SOP, sistem, kebijakan, dll | V5: Diisi dengan penilaian terhadap efektivitas kontrol saat ini (existing control) dengan pilihan sebagai berikut: 1) Cukup dan Efektif; 2) Cukup dan Efektif Sebagian; 3) Cukup dan Tidak Efektif; 4) Tidak Cukup dan Efektif Sebagian; dan 5) Tidak Cukup dan Tidak Efektif. | W5: Diisi dengan pilihan kategori dampak: - Dampak kuantitatif - Dampak kualitatif | X5: Disi dengan penjelasan/deskripsi atas dampak yang akan diterima apabila risiko terjadi. | Y5: Diisi dengan perkiraan periode waktu BUMN terpapar Risiko, sesuai dengan karakter Risiko tersebut. Perkiraan waktu diidentifikasi melalui proyeksi, data historis, maupun keumuman pada industri BUMN terkait
A6: Notes | E6: Sasaran disusun secara lengkap. Sebagai contoh: "Peningkatan market share segmen corporate dari 20% menjadi 30% pada akhir tahun 2024" | H6: - Risiko pada Industri Umum tidak boleh dipetakan dalam kategori Risiko Industri Perbankan dan Asuransi - Risiko pada Industri perbankan & asuransi dapat dipetakan dalam kategori Risiko Industri Umum | I6: 1. Nomor risiko harus konsisten pada saat pelaporan. 2. Apabila terdapat risiko yang bertambah manak nomornya melanjutkan sesuai dengan urutan terakhir | J6: Risiko harus diidentifikasi dengan tepat, dan memenuhi ketentuan: - Bukan negasi sasaran - Dipetakan dalam fault tree analysis dan yang menjadi risk event yang paling mendekati dengan sumber utama penyebab risiko. | M6: Setiap penyebab kejadian diberikan unique ID | N6: Jika satu Risiko memiliki lebih dari satu penyebab Risiko, maka dituliskan dalam cell di baris berikutnya (tidak digabung menjadi satu cell). | T6: Apabila jenis existing control memiliki lebih dari satu jenis control, maka dituliskan dalam cell di baris berikutnya (tidak digabung menjadi satu cell). | U6: Apabila existing control lebih dari 1, untuk control ke 2 dst agar ditambahkan pada row di bawahnya | W6: 1) Dampak kuantitatif: Risiko yang memiliki dampak finansial terhadap pencapaian target laba BUMN. 2) Dampak kualitatif: Risiko yang tidak memiliki dampak finansial terhadap pencapaian target laba BUMN. | Y6: Periode waktu dapat berupa range bulan (contoh Januari 2023 – Februari 2024)
A7: Start Pengisian | C7: PT Perusahaan Listrik Negara (Persero) | E7: Meningkatkan keandalan suply dan kualitas layanan | F7: 1. Nilai ekonomi dan sosial | G7: Risiko Operasional (Pembangkitan dan Transmisi) | H7: 16. Risiko Industri Umum - Operasional | I7: 1 | J7: Terjadi pemadaman meluas pada sistem Batam Bintan | K7: Terjadinya pemadaman meluas dan atau blackout di sistem kelistrikan batam bintan, yang dapat disebabkan oleh gangguan pembangkit dan transmisi, selain itu juga disebabkan kejadian alam. | L7: a | N7: P1. Gangguan Pembangkit PLTGU Tanjung Uncang | O7: EAF PLTGU TGU #01 (GT) (+) EAF PLTGU TGU #02 (GT) (+) EAF PLTGU TGU #03 (ST) (+) | P7: % | Q7: >94% >94% >94% | R7: <94% <94% <94% | S7: <92% <92% <92% | T7: Kontrol operasi - level operasi | U7: 'Prosedur Pengoperasian dan Pemeliharaan PLTGU | V7: Cukup dan Efektif Sebagian | W7: Dampak Kuantitatif | X7: 1. Target SAIDI SAIFI tidak tercapai | Y7: Jan - Des 2024
L8: b | N8: P2. Gangguan Pembangkit PLTMG Panaran | U8: Instruksi Kerja Pengoperasian Turbin PLTGU | V8: Cukup dan Efektif | X8: 2. Tidak tercapainya keandalan sistem | Y8: Jan - Des 2024
L9: c | N9: P3. Gangguan Gardu Induk | U9: Prosedur Pengoperasian dan Pemeliharaan Chlorination Plant PLTGU | V9: Cukup dan Efektif | X9: 3. Kompensasi TMP | Y9: Jan - Des 2024
L10: d | N10: P4. Sistem Proteksi Gardu Induk tidak efektif | U10: Prosedur Performance Test PLTGU | V10: Cukup dan Efektif | X10: 4. Pendapatan menurun | Y10: Jan - Des 2024
L11: e | N11: P5. Manajemen Pengelolaan Gardu Induk tidak efektif | U11: Prosedur Pengoperasian dan Pemeliharaan WTP PLTGU | V11: Cukup dan Efektif
L12: f | N12: P6. Overload pada Sistem Transmisi Batam | U12: Prosedur Analisa Kerja Dan Laporan Pengusahaan Pembangkit | V12: Cukup dan Efektif
L13: g | N13: P7. Gangguan Sistem Transmisi Batam | O13: EAF PLTMG Panaran #01 EAF PLTMG Panaran #02 EAF PLTMG Panaran #03 | P13: % | Q13: >94% >94% >94% | R13: <94% <94% <94% | S13: <92% <92% <92% | U13: Prosedur Pengoperasian dan Pemeliharaan PLTMG | V13: Cukup dan Efektif
L14: h | N14: P8. Defense Scheme tidak berfungsi efektif dan optimal | U14: Prosedur Pemeliharaan Engine PLTMG, dan Instruksi Kerja Pengoperasian Engine PLTMG | V14: Cukup dan Efektif
L15: i | N15: P9. Kompetensi SDM tidak optimal | U15: Prosedur Performance Test PLTMG Panaran | V15: Cukup dan Efektif
L16: j | N16: P10. Performa pembangkit IPP tidak optimal (Force Outage, kordinasi sistem proteksi pembangkit IPP tidak sesuai) | O16: TROF (-) | P16: Kali/Unit/Tahun | Q16: <0.80 Kali/Unit/Tahun | R16: >0.80 Kali/Unit/Tahun | S16: >1.00 Kali/Unit/Tahun | U16: Prosedur Pemeliharaan Proteksi dan Meter, dan Prosedur Analisa Kinerja Proteksi dan Meter | V16: Cukup dan Efektif
L17: k | N17: P11. Kinerja transmisi dan gardu induk di Pulau Bintan | O17: TROD (-) | P17: Jam/Unit/Tahun | Q17: <0.80 Kali/Unit/Tahun | R17: >0.80 Kali/Unit/Tahun | S17: >1.00 Kali/Unit/Tahun | U17: Prosedur Pengoperasian dan Pemeliharaan PLTMG | V17: Cukup dan Efektif
L18: l | N18: P12. Gangguan pasokan gas (penurunan pressure gas secara signifikan dengan tiba-tiba)
L23: d
L24: e | N24: P5. Overload pada Sistem Transmisi Batam
L25: f | N25: P6. Gangguan Sistem Transmisi Batam | O25: TLOF (-) | P25: Kali/100 kms/Tahun | Q25: <4 Kali/100 kms/Tahun | R25: >4 Kali/100 kms/Tahun | S25: >8 Kali/100 kms/Tahun
O26: TLOD (-) | P26: Jam/100 kms/Tahun | Q26: <2 Jam/100 kms/Tahun | R26: >2 Jam/100 kms/Tahun | S26: >4 Jam/100 kms/Tahun
L27: g | N27: P7. Defense Scheme tidak berfungsi efektif dan optimal
L28: h | N28: P8. Kompetensi SDM tidak optimal
L29: i | N29: P9. Performa pembangkit IPP tidak optimal (Force Outage, kordinasi sistem proteksi pembangkit IPP tidak sesuai)
L30: j | N30: P10. Kinerja transmisi dan gardu induk di Pulau Bintan
L31: k | N31: P11. Gangguan pasokan gas (penurunan pressure gas secara signifikan dengan tiba-tiba)
I32: 2 | J32: Terjadinya Defisit Daya pada Sistem Kelistrikan Batam-Bintan
I33: 3 | J33: Operasional dan jaringan distribusi tidak berfungsi optimal
I35: 4 | J35: Ketersediaan material utama (MTU dan MDU) tidak memenuhi kebutuhan operasional & pemeliharaan transmisi dan distribusi, serta pemasaran

Sheet Rencana Perlakuan Risiko
A1: Kembali ke Daftar Isi
A2: Data Item | B2: No. | C2: BUMN | D2: Kode BUMN | E2: No. Risiko | F2: No. Penyebab Risiko | G2: Penyebab risiko | H2: Opsi Perlakuan Risiko | I2: Jenis Rencana Perlakuan Risiko | J2: Rencana Perlakuan Risiko | K2: Output Perlakuan Risiko | L2: Biaya Perlakuan Risiko (Rp/Mata Uang Lain) | M2: AI | N2: AO | P2: Jenis Program Dalam RKAP | Q2: PIC | R2: Timeline (Bulan)
N3: HAR | O3: ADM | R3: 1 | S3: =R3+1 -> 2 | T3: =S3+1 -> 3 | U3: =T3+1 -> 4 | V3: =U3+1 -> 5 | W3: =V3+1 -> 6 | X3: =W3+1 -> 7 | Y3: =X3+1 -> 8 | Z3: =Y3+1 -> 9 | ... AC3: =AB3+1 -> 12
A4: Jenis Data | B4: Number | C4: Dropdown list | D4: Formula | E4: Number | F4: Alphabet | G4: Formula | H4: Dropdown list | I4: Multiple List | J4: Free Text | K4: Free Text | L4: Nilai full mata uang dalam Rupiah/mata uang fungsional pembukuan | P4: Free Text | Q4: Free Text | R4: Numerik (diisi nilai 1 jika mitgasi dilakukan pada bulan tertentu)
A5: Petunjuk | E5: Kolom ini tidak perlu diisi. Akan diisi oleh Kementerian BUMN | F5: Diisi dengan nomor urutan penyebab risiko | G5: Diisi dengan penyebab risiko yang ada pada tabel profil risiko | H5: Diisi dengan pilihan: - Transfer/sharing - Reduce/mitigate - Accept/monitor - Avoid/hindari | I5: Diisi dengan pilihan jenis rencana perlakuan risiko: - Peningkatan Kecukupan Desain Control - Peningkatan Efektivitas Pelaksanaan Control - Perbaikan Melalui Breakthrough Project - Lainnya | J5: 1. Setiap perlakuan risiko di-break down dalam aktivitas-aktivitas yang lebih detail 2. [rule] Setiap unique ID penyebab risiko memiliki minimal 1 perlakuan risiko | K5: Diisi dengan output atas masing-masing aktivitas rencana perlakuan risiko | L5: Diisi dengan anggaran dalam pelaksanaan perlakuan risiko | P5: Anggaran biaya perlakuan risiko telah dimasukkan dalam salah satu jenis program RKAP, dengan pilihan: - Pemasaran dan penjualan - Pengadaan - Produksi dan Kualitas Produk - Teknis dan Teknologi - Keuangan dan Akuntansi - Sistem dan Organisasi - Pengembangan SDM - Penelitian dan Pengembangan - Pelestarian Lingkungan - Investasi - Lainnya | Q5: Unit penanggung jawab perlakuan risiko setingkat BOD | R5: Terhadap masing-masing perlakuan risiko per penyebab risiko, agar diisi timeline rencana implementasinya. Apabila perlakuan risiko berlangsung sepanjang tahun, maka timeline harus diisi setiap bulan
A6: Notes | G6: Nama penyebab risiko harus sama persis dengan nama penyebab risiko yang ada pada tabel profil risiko | I6: Pilihan dapat lebih dari satu | J6: 1. Setiap penyebab risiko memiliki rencana perlakuan risiko. 2. Rencana perlakuan risiko harus spesifik dan tidak memungkinkan akan sama untuk menyelesaikan setiap penyebab. 3. Apabila satu perlakuan risiko dapat menyelesaikan lebih dari satu penyebab, artinya penyebab-penyebab tersebut belum diidentifikasi secara mendalam untuk mendapatkan akar penyebabnya.
A7: Start Pengisian | C7: PT Perusahaan Listrik Negara (Persero) | D7: =IFERROR(VLOOKUP(C7,Master!$D$2:$E$50,2,0),"") -> PLNA | E7: ='Profil Risiko'!I7 -> 1 | F7: a | G7: ='Profil Risiko'!N7 -> P1. Gangguan Pembangkit PLTGU Tanjung Uncang | H7: Reduce/mitigate | I7: Peningkatan Efektivitas Pelaksanaan Kontrol | J7: 1. Meningkatkan keandalan PLTGU dalam sistem kelistrikan Batam-Bintan : | P7: Lainnya
J8: a. Melanjutkan Pengadaan suku cadang HGPI GT#2 (emergency finding parts) (P1) | K8: Tersedianya material suku cadang dan terlaksananya pemeliharaan PLTGU Tg Uncang tepat waktu | L8: =SUM(M8:O8) -> 56026241000 | M8: 56026241000 | P8: Penelitian dan Pengembangan | Q8: SM UBKITRANS | R8: 1 | S8: 1 | T8: 1 | U8: 1 | V8: 1 | W8: 1 | X8: 1 | Y8: 1 | Z8: 1
J9: b. Melaksanakan Level C Inspection GT#1 PLTGU Tanjung Uncang (P1) | K9: Terlaksananya mayor overhaul 50K STG Tg Uncang | L9: =SUM(M9:O9) -> 11818722000 | M9: 11818722000 | P9: Pengadaan | Q9: SM UBKITRANS | R9: 1 | S9: 1 | T9: 1 | U9: 1 | V9: 1 | W9: 1 | X9: 1 | Y9: 1 | Z9: 1 | AA9: 1 | AB9: 1
J10: c. Melaksanakan Level C Inspection GT#2 PLTGU Tanjung Uncang (P1) | K10: Tersedianya cadangan blower ventilation PLTGU Tg Uncang | L10: =SUM(M10:O10) -> 4412100000 | M10: 4412100000 | P10: Pengadaan | Q10: SM UBKITRANS | R10: 1 | S10: 1 | T10: 1 | U10: 1 | V10: 1 | W10: 1
J11: d. Melaksanakan Major Overhaul 50K STG PLTGU Tanjung Uncang (P1 | K11: Terlaksananya pemeliharaan terencana preventive dan corrective PLTGU Tg Uncang 2024 | L11: 96278092000 | N11: 96278092000 | P11: Pengadaan | Q11: SM UBKITRANS | R11: 1 | S11: 1 | T11: 1 | U11: 1 | V11: 1 | W11: 1 | X11: 1 | Y11: 1 | Z11: 1 | AA11: 1 | AB11: 1 | AC11: 1
F12: ='Profil Risiko'!L8 -> b | G12: ='Profil Risiko'!N8 -> P2. Gangguan Pembangkit PLTMG Panaran | I12: Peningkatan Efektivitas Pelaksanaan Kontrol | J12: 2. Meningkatkan keandalan PLTMG Panaran dalam sistem kelistrikan Batam-Bintan :
J13: Meningkatkan keandalan PLTMG Panaran dalam sistem kelistrikan Batam-Bintan Pemeliharaan 60K Engine#1 dan Engine#3 PLTMG Panaran (P2) | K13: Terlaksanakan pemeliharaan 60 K Engine #1 & #3 PLTMG Panaran | L13: 17069564000 | P13: Pengadaan | Q13: SM UBKITRANS | U13: 1 | V13: 1 | W13: 1 | X13: 1 | Y13: 1 | Z13: 1 | AA13: 1 | AB13: 1 | AC13: 1
J14: Meningkatkan keandalan PLTMG Panaran dalam sistem kelistrikan Batam-Bintan Pemeliharaan 60K Engine#2 PLTMG Panaran | K14: Terlaksanakan pemeliharaan 60 K Engine #2 PLTMG Panaran | L14: 2526494000 | P14: Pengadaan | Q14: SM UBKITRANS | R14: 1 | S14: 1 | T14: 1 | U14: 1
F15: ='Profil Risiko'!L9 -> c | G15: ='Profil Risiko'!N9 -> P3. Gangguan Gardu Induk | I15: Peningkatan Efektivitas Pelaksanaan Kontrol | J15: 3. Meningkatkan keandalan Gardu Induk dalam sistem Batam-Bintan :
J16: a. Melanjutkan Pengadaan & Pemasangan Kubikel 20 kV GI Tersebar 2023 sampai 2025 (P3) | Q16: SM UBKITRANS
J17: b. Melaksanakan Upgrade Kubikel 20 kV GI Baloi Air Insulated ke Fully Insulated (19 Kubikel) (P3) | Q17: SM UBKITRANS
J18: c. Melanjutkan Pengadaan dan Penggantian Peralatan Serandang GI 150 kV rusak tahun 2023 sampai 2025 (P3) | Q18: SM UBKITRANS
J19: d. Melanjutkan Pengadaan KWH Meter (P3) | Q19: SM UBKITRANS
J20: e. Melanjutkan Pembangunan Bay Trafo 3 x 60 MVA Batam Tersebar, Tahap 1 dan Tahap 2 tahun 2023 sampai 2025 (P3) | Q20: VP REN
J21: f. Melanjutkan Pembangunan Bay Trafo 2 GI Panaran, Relokasi Trafo dan MTU Dari GI Sengkuang Ke GI Panaran (P3) | Q21: SM UBKITRANS
J22: g. Melakukan Pengadaan dan Pemasangan Charger dan Baterai 110 VDC GI 2024 (P3) | Q22: SM UBKITRANS
F23: ='Profil Risiko'!L10 -> d | G23: ='Profil Risiko'!N10 -> P4. Sistem Proteksi Gardu Induk tidak efektif | J23: 4. Meningkatkan keandalan Sistem Proteksi Gardu Induk dalam sistem Batam-Bintan :
J24: a. Melanjutkan Pengadaan dan Pemasangan Charger dan Baterai 110 VDC GI 2023 (P4)
J25: b. Melanjutkan Optimalisasi Relai dan Meter 150 kV 2023 (P4)
J26: c. Melanjutkan Optimalisasi Sistem Proteksi 20 kV Gardu Induk (P4)
J27: d. Melanjutkan Optimalisasi Relai Defense Scheme Sistem Batam (P4)
J28: e. Mengganti Relay Proteksi 150 KV dan Meter 20 KV 2024-2025 (P4)
J29: f. Mengganti Relai AVR utk GI Tanpa Operator (Kasam, Sengkuang, Harapan (P4)
J30: g. Melakukan Pengadaan alat uji sekunder 3 phasa (P4)
J31: h. Melakukan Optimalisasi DFR 150 KV Terserbar 2024-2025 (P4)
J32: i. Implementasi Adaptif Defense Scheme 2024-2025 (P4)
J33: j. Melanjutkan Pengembangan Remote Station Gardu Distribusi di lokasi 70 Gardu Distribusi Tersebar (P4)
F34: ='Profil Risiko'!L11 -> e | G34: ='Profil Risiko'!N11 -> P5. Manajemen Pengelolaan Gardu Induk tidak efektif | J34: 5. Meningkatkan efektifitas manajemen Gardu Induk :
J35: a. Melakukan Pengembangan smart monitoring GI, Pengadaan dan Pemasangan CCTV Gardu Induk dan Pembangkit serta update NVR (P5)
F36: ='Profil Risiko'!L12 -> f | G36: ='Profil Risiko'!N12 -> P6. Overload pada Sistem Transmisi Batam | J36: 6. Meningkatkan efektifitas manajemen Gardu Induk :
J37: a. Melanjutkan Pengadaan Transmisi 150 kV GI Batu Besar - GI Nongsa (P6)
J38: b. Melakukan Pembangunan SUTT Tj Uncang - Phi Con Sagulung - Harapan (P6)
J39: c. Melakukan Pembangunan SUTT Nongsa-Nongsa Digital Park (P6)
J40: d. Melakukan Pembangunan Double Phi Connection Batu Besar-Kabil- Tanjung Kasam (P6)
F41: ='Profil Risiko'!L13 -> g | G41: ='Profil Risiko'!N13 -> P7. Gangguan Sistem Transmisi Batam | J41: 7. Memperkuat keandalan Sistem Transmisi Batam :
J42: a. Melanjutkan Reroute/Penguatan Tapak Tower Transmisi Tersebar (Sagulung - Panaran T38 s/d T47) (P7)
J43: b. Melaksanakan pengadaan & penggantian Material Transmisi Utama 150kV Serandang GI 2024 (P7)
J44: 8. Memperkuat efektifitas Manajemen Sistem Operasi Batam-Bintan :
J45: a. Melakukan Integrasi AGC (Automatic Generation Control) Penggantian Remote Station Pembangkit dan Penggantian Fasilitas Operasi Sistem (Redesign BCC) (P7)
J46: b. Melakukan Pengadaan Software untuk Aplikasi Manajemen Energi & Aplikasi Analisa Operasi Sistem Realtime (Digsilent) (P7)
F47: ='Profil Risiko'!L14 -> h | G47: ='Profil Risiko'!N14 -> P8. Defense Scheme tidak berfungsi efektif dan optimal | J47: 9. Evaluasi Difense Scheme
J48: a. Melakukan evaluasi dengan melakukan review dan update Defense Scheme, dan melakukan pengujian atas Defense Scheme beserta peralatan pendukungnya secara berkala (triwulanan/semester) (P8)
F49: ='Profil Risiko'!L15 -> i | G49: ='Profil Risiko'!N15 -> P9. Kompetensi SDM tidak optimal | J49: 10. Meningkatkan kompetensi SDM yang terkait dengan O&M pembangkit, transmisi, GI dan proteksi
J50: a. Memberikan pelatihan dan sertifikasi yang diperlukan kepada SDM yang terkait dengan O&M pembangkit, transmisi, GI dan proteksi (P9)
F51: ='Profil Risiko'!L16 -> j | G51: ='Profil Risiko'!N16 -> P10. Performa pembangkit IPP tidak optimal (Force Outage, kordinasi sistem proteksi pembangkit IPP tidak sesuai) | J51: 11. Komunikasi dan koordinasi rutin dengan IPP
J52: a. Komunikasi dan koordinasi rutin dengan IPP melalui Rapat mingguan terkait kinerja IPP (P10)
J53: b. Koordinasi pelaksanaan pemeliharaan pembangkit dan perbaikan gangguan pembangkit (P10)
J54: c. Evaluasi dan monitoring penyelesaian pekerjaan pemeliharaan dan perbaikan gangguan (P10)
J55: d. Assesment bersama pengujian black start dan uji fungsi relay proteksi (P10)
J56: e. Koordinasi dalam pelaksanaa pengujian rutin island operation dan line charging (P10)
F57: ='Profil Risiko'!L17 -> k | G57: ='Profil Risiko'!N17 -> P11. Kinerja transmisi dan gardu induk di Pulau Bintan | J57: 12. Komunikasi dan koordinasi rutin dengan PLN RKR Tanjungpinang
J58: a. Komunikasi dan koordinasi rutin dengan PLN RKR Tanjungpinang melalui Rapat mingguan terkait transmisi dan gardu induk di Pulau Bintan (P11)
F59: ='Profil Risiko'!L18 -> l | G59: ='Profil Risiko'!N18 -> P12. Gangguan pasokan gas (penurunan pressure gas secara signifikan dengan tiba-tiba) | J59: 13. Koordinasi keandalan pasokan gas dengan pihak sumur, TGI dan PGN
J60: a. Melakukan koordinasi keandalan pasokan gas dengan pihak sumur, TGI dan PGN secara rutin (P12)
J61: 14. Komunikasi dan koordinasi rutin dengan peserta stakeholder gas
J62: a. Mengikuti pertemuan rutin dengan peserta stakeholder gas (SKK Migas, pihak sumur, transporter dan pengguna gas) melalui Coordination Meeting (GCM) Sumatera bagian tengah (Sumbagteng) (PIC: SM UBKITTRAN, VP OPS) (P12)
E63: ='Profil Risiko'!I32 -> 2 | F63: a | G63: P1. Kapasitas Pembangkitan tidak mencukupi pertumbuhan kelistrikan di sistem Batam - Bintan | J63: 1. Menambah kapasitas pembangkitan dalam sistem kelistrikan Batam-Bintan
J64: a. Melanjutkan FS PLTGU 120 MW Dan AMDAL (PIC: VP REN) (Juni 2024 - Des 2024) (P1)
J65: b. Melaksanakan pengadaan EPC PLTGU 120 MW (PIC: VP REN) (Juni 2024 - Jun 2026) (P1)
J66: c. Melakukan pembangunan EPC Pembangkit PLTGU 180 MW & Evakuasi Daya (PIC: VP REN) (Jan 2025 - Des 2027) (P1)
J67: d. Melanjutkan Pembangunan EPC Pembangkit PLTMG Batam 50 MW (P1)
F69: b | G69: P2. Perencanaan kapasitas pembangkitan tidak akurat | J69: 2. Melakukan Perencanaan yang komprehensif
J70: a. Melakukan perencanaan pembangkitan untuk kebutuhan sistem Batam-Bintan dengan melibatkan semua pihak terkait dengan mempertimbangkan growth rate, load factor, dan sebagainya, dengan target reserve margin 30% (P2)
F72: c | G72: P3. Keterlambatan pembangunan pembangkit baru | J72: 3. Melakukan koordinasi rutin terkait progress pembangunan pembangkit
J73: a. Melakukan koordinasi rutin untuk memastikan Pembangkit baru baik milik PLN Batam maupun IPP, realisasi COD sesuai dengan waktu yang ada di kontrak EPC atau PJBTL (P3)
F74: d | G74: P4. Keluarnya pembangkit dari sistem Batam - Bintan tidak sesuai dengan rencana | J74: 4. Memastikan realisasi jadwal pemeliharaan pembangkit PLN Batam sesuai dengan rencana yang sudah disepakati dalam ROT atau ROB
J75: a. Memastikan realisasi jadwal pemeliharaan pembangkit PLN Batam sesuai dengan rencana yang sudah disepakati dalam ROT atau ROB (P4)
F76: e | G76: P5. Terjadi gangguan pembangkit IPP bersamaan dengan periode pemeliharaan pembangkit lainnya. | J76: 5. Komunikasi dan koordinasi rutin dengan IPP
J77: a. Komunikasi dan koordinasi rutin dengan IPP melalui Rapat mingguan terkait kinerja IPP (P5)
F78: f | G78: P6. Perencanaan pengembangan pembangkitan sistem Batam – Bintan tidak sesuai dengan pertumbuhan beban (realisasi pemasaran melebihi kapasitas pembangkitan yang tersedia) | J78: 6. Memastikan penambahan pelanggan baru sesuai dengan ketersediaan cadangan daya Sistem Batam - Bintan
J79: a. Melakukan koordinasi lintas bidang terkait penambahan pelanggan baru yang disesuaikan dengan ketersediaan cadangan daya Sistem Batam - Bintan (P6)
F80: g | G80: P7. Gangguan pasokan gas (penurunan pressure gas secara signifikan dengan tiba-tiba)" | J80: 7. Koordinasi keandalan pasokan gas dengan pihak sumur, TGI dan PGN
J81: a. Melakukan koordinasi keandalan pasokan gas dengan pihak sumur, TGI dan PGN secara rutin (P7)
J82: 8. Komunikasi dan koordinasi rutin dengan peserta stakeholder gas
J83: b. Mengikuti pertemuan rutin dengan peserta stakeholder gas (SKK Migas, pihak sumur, transporter dan pengguna gas) melalui Coordination Meeting (GCM) Sumatera bagian tengah (Sumbagteng) (PIC: SM UBKITTRAN, VP OPS) (P7)
E84: 3 | F84: a | G84: P1. Jaringan Distribusi Jaringan Tegangan Menengah (JTM) tidak berfungsi optimal | J84: Meningkatkan Mutu dan Keandalan (MUDAL) Jaringan Tegangan Menengah (JTM) (P1):
J85: Melakukan program Pecah Beban Feeder BAKAU (P1) SM UBDISYAN
J86: Melakukan program Pecah Beban Feeder VIOLET (P1) SM UBDISYAN
J87: Melakukan program Pecah Beban Feeder ROSELLA (P1) SM UBDISYAN
J88: Melakukan program Pecah Beban Feeder NONG ISA (P1) SM UBDISYAN
J89: Melakukan program Pecah Beban Feeder GARUDA (P1) SM UBDISYAN
J90: Melakukan program Pecah Beban Feeder ELANG (P1) SM UBDISYAN
J91: Melakukan program Pecah Beban Feeder SEDAP MALAM (P1) SM UBDISYAN
J92: Melakukan program Pecah Beban Feeder DAHLIA (P1) SM UBDISYAN
J93: Melakukan program Pecah Beban Feeder KELINCI/ZEBRA (P1) SM UBDISYAN
J94: Melakukan program Pecah Beban Feeder AKASIA (P1) SM UBDISYAN
J95: Melakukan program Pecah Beban Feeder LUMBA-LUMBA (P1) SM UBDISYAN
F97: b | G97: P2. Jaringan Distribusi Jaringan Tegangan Menengah & Tegangan Rendah (JTM & JTR) tidak berfungsi optimal | J97: Meningkatkan Keandalan Jaringan Tegangan Menegah & Tegangan Rendah (JTM & JTR) untuk mengurangi SAIDI (P2, P4, P5, P6, P7):
J98: Melanjutkan Program SAIDI 2023 (P2) SM UBDISYAN
J99: Program SAIDI - Pemasangan Recloser 2024-2025 (P2) SM UBDISYAN
J100: Program SAIDI - Upgrade Kubikel LBS menjadi CB di GT Existing (Keypoint) 2024-2025 (P2) SM UBDISYAN
J101: Program SAIDI - Upgrade Kubikel GH (Pemasangan Kubikel Coupler) 2024-2025 (P2) SM UBDISYAN
J102: Program SAIDI - Pemasangan GD Kios untuk GD Portal 2024-2025 (P2) SM UBDISYAN
J104: Meningkatkan Keandalan Jaringan Tegangan Menengah & Tegangan Rendah (JTM & JTR) untuk mengurangi SAIFI (P2, P4, P5, P6, P7):
...

Sheet Risiko Inheren Kuantitatif
A1: Kembali ke Daftar Isi
A2: Data Item | B2: No. | C2: BUMN | D2: Kode BUMN | E2: No. Risiko | F2: Peristiwa risiko | G2: Risiko Inheren
G3: Asumsi Perhitungan Dampak | H3: Nilai Dampak | I3: Skala Dampak | K3: Nilai Probabilitas | L3: Skala Probabilitas | N3: Eksposur Risiko | O3: Skala Risiko | Q3: Level Risiko
I4: BUMN | J4: KBUMN | L4: BUMN | M4: KBUMN | O4: BUMN | P4: KBUMN | Q4: BUMN | R4: KBUMN
A5: Jenis Data | B5: Formula | C5: Formula | D5: Formula | E5: Formula | F5: Formula | G5: Free Text | H5: Nilai full mata uang dalam Rupiah/mata uang fungsional pembukuan | I5: Dropdown list | J5: Formula | K5: % | L5: Dropdown list | M5: Dropdown list | N5: Nilai dalam mata uang rupiah Rupiah/USD | O5: Skala 1-25 | P5: Skala 1-25 | Q5: Free Text | R5: Formula
A6: Petunjuk | D6: Kolom ini tidak perlu diisi. Akan diisi oleh Kementerian BUMN | E6: Diisi dengan nomor urutan risiko | F6: Diisi dengan peristiwa risiko yang ada pada tabel profil risiko | G6: Diisi penjelasan atas asumsi/pendekatan yang dipakai untuk menghitung nilai dampak. | H6: Nilai dampak dalam Rupiah/mata uang fungsional pembukuan | I6: Diisi dengan penilaian dampak Risiko Inheren dengan skala 1 s.d. 5 | J6: Dikosongkan. Akan diisi oleh Kementerian BUMN | K6: Diisi dengan nilai probabilitas atas suatu Risiko dalam persentase | L6: Diisi dengan penilaian probabilitas Risiko Inheren dengan skala 1 s.d. 5 | M6: Dikosongkan. Akan diisi oleh Kementerian BUMN | N6: Nilai dampak x nilai probabilitas. | O6: Diisi dengan skala Risiko BUMN yang merupakan koordinat Risiko sebagaimana acuan heatmap Kementerian BUMN pada Diagram 3 Peta Risiko (Heatmap) | P6: Dikosongkan. Akan diisi oleh Kementerian BUMN | Q6: Diisi dengan pewarnaan risiko masing-masing BUMN yang terdiri dari: - Sangat Tinggi - Tinggi - Menengah - Rendah - Sangat Rendah | R6: Dikosongkan. Akan diisi oleh Kementerian BUMN
A7: Notes | F7: Nama peristiwa risiko harus sama persis dengan nama peristiwa risiko yang ada pada tabel profil risiko | H7: - Bagi unit kerja profit generator, dihitung sebesar potensi penurunan laba yang hilang jika Risiko terjadi (dapat menggunakan pendekatan gross profit, revenue dikalikan profit margin, EBITDA, atau net income). - Bagi unit kerja non-profit generator, dihitung sebesar potensi penambahan biaya yang muncul yang belum dianggarkan jika Risiko tersebut terjadi. | I7: Kriteria Skala Dampak Kuantitatif menggunakan acuan Tabel Kriteria Dampak Kuantitatif pada sheet Kriteria Dampak & Probabilitas. | L7: Kriteria Skala Probabilitas menggunakan acuan Tabel Kriteria Probabilitas pada sheet Kriteria Dampak & Probabilitas. | N7: Hasil perkalian akan menghasilkan nilai rupiah/mata uang fungsional pembukuan | Q7: Masing-masing BUMN mendefinisikan level risiko sesuai dengan penetapan masing-masing | R7: Level risiko KBUMN terdiri dari: - Low - Low to Moderate - Moderate - Moderate to High - High
A8: Start Pengisian | C8: PT Perusahaan Listrik Negara (Persero) | D8: =IFERROR(VLOOKUP(C8,Master!$D$2:$E$50,2,0),"") -> PLNA | E8: ='Profil Risiko'!I7 -> 1 | F8: =IFERROR(VLOOKUP($E8,'Profil Risiko'!$I:$J,2,0),"") -> Terjadi pemadaman meluas pada sistem Batam Bintan | G8: Bila terjadi pemadaman meluas maka berpotensi kehilangan pendapatan sebesar 12,20 | H8: 12.2 | I8: 5 | K8: 0.2 | L8: 3 | N8: =$H8*$K8 -> 2.44 | O8: 23 | P8: =IFERROR(VLOOKUP($J8&$M8,Master!$V$2:$W$26,2,0),"No Data") -> No Data | Q8: =VLOOKUP(O8,E$14:F$38,2,FALSE) -> High | R8: =IFERROR(VLOOKUP($J8&$M8,Master!$W$2:$Y$26,3,0),"No Data") -> No Data
D10: =IFERROR(VLOOKUP(C10,Master!$D$2:$E$50,2,0),"") | F10: =IFERROR(VLOOKUP($E10,'Profil Risiko'!$I:$J,2,0),"") | N10: =$H10*$K10 -> 0 | P10: =IFERROR(VLOOKUP($J10&$M10,Master!$V$2:$W$26,2,0),"No Data") -> No Data | R10: =IFERROR(VLOOKUP($J10&$M10,Master!$W$2:$Y$26,3,0),"No Data") -> No Data
E14: 1 | F14: Low
E15: 2 | F15: Low
E16: 3 | F16: Low
E17: 4 | F17: Low
E18: 5 | F18: Low
E19: 6 | F19: Low to Moderate
E20: 7 | F20: Low to Moderate
E21: 8 | F21: Low to Moderate
E22: 9 | F22: Low to Moderate
E23: 10 | F23: Low to Moderate
E24: 11 | F24: Low to Moderate
E25: 12 | F25: Moderate
... E38: 25 | F38: High

Sheet Risiko Inheren Kualitatif
A1: Kembali ke Daftar Isi
A2: Data Item | B2: No. | C2: BUMN | D2: Kode BUMN | E2: No. Risiko | F2: Peristiwa risiko | G2: Risiko Inheren
G3: Penjelasan Dampak Kualitatif | H3: Nilai Dampak | I3: Skala Dampak | K3: Nilai Probabilitas | L3: Skala Probabilitas | N3: Nilai Eksposur Risiko | O3: Skala Risiko | Q3: Level Nilai Risiko
I4: BUMN | J4: KBUMN | L4: BUMN | M4: KBUMN | O4: BUMN | P4: KBUMN | Q4: BUMN | R4: KBUMN
A5: Jenis Data | B5: Formula | C5: Formula | D5: Formula | E5: Formula | F5: Formula | G5: Free Text | H5: Nilai full mata uang dalam Rupiah/mata uang fungsional pembukuan | I5: Dropdown list | J5: Formula | K5: % | L5: Dropdown list | M5: Formula | N5: Number | O5: Skala 1-25 | P5: Skala 1-25 | Q5: Free Text | R5: Formula
A6: Petunjuk | D6: Kolom ini tidak perlu diisi. Akan diisi oleh Kementerian BUMN | E6: Diisi dengan nomor urutan risiko | F6: Diisi dengan peristiwa risiko yang ada pada tabel profil risiko | G6: Diisi penjelasan atas dampak kualitatif yang akan terjadi. | H6: Dapat dikosongkan | I6: Diisi dengan penilaian dampak Risiko Inheren dengan skala 1 s.d. 5 | J6: Dikosongkan. Akan diisi oleh Kementerian BUMN | K6: Diisi dengan nilai probabilitas atas suatu Risiko dalam persentase | L6: Diisi dengan penilaian probabilitas Risiko Inheren dengan skala 1 s.d. 5 | M6: Dikosongkan. Akan diisi oleh Kementerian BUMN | N6: Diisi dengan hasil perhitungan: skala Dampak x 1% Batasan Risiko yang ditetapkan dalam strategi Risiko x nilai Probabilitas (%). | O6: Diisi dengan skala Risiko BUMN yang merupakan koordinat Risiko sebagaimana acuan heatmap Kementerian BUMN pada Diagram 3 Peta Risiko (Heatmap) | P6: Dikosongkan. Akan diisi oleh Kementerian BUMN | Q6: Diisi dengan leveling dan pewarnaan risiko masing-masing BUMN. | R6: Dikosongkan. Akan diisi oleh Kementerian BUMN
A7: Notes | F7: Nama peristiwa risiko harus sama persis dengan nama peristiwa risiko yang ada pada tabel profil risiko | I7: Kriteria Skala Dampak Kualitatif menggunakan acuan Tabel Kriteria Dampak Kualitatif pada sheet Kriteria Dampak & Probabilitas. Apabila acuan kriteria dampak tidak tersedia pada tabel di atas, BUMN dapat menggunakan acuan tabel kriteria dampak kualitatif lainnya sesuai dengan pedoman masing-masing dan menyampaikannya dalam buku RKAP. | L7: Kriteria Skala Probabilitas menggunakan acuan Tabel Kriteria Probabilitas pada sheet Kriteria Dampak & Probabilitas. | O7: Masing-masing BUMN mendefinisikan skala 1-25 sesuai dengan penetapan masing-masing | Q7: Masing-masing BUMN mendefinisikan level risiko sesuai dengan penetapan masing-masing | R7: Level risiko KBUMN terdiri dari: - Low - Low to Moderate - Moderate - Moderate to High - High
A8: Start Pengisian | C8: PT Perusahaan Listrik Negara (Persero) | D8: =IFERROR(VLOOKUP(C8,Master!$D$2:$E$50,2,0),"") -> PLNA | E8: 1 | F8: =IFERROR(VLOOKUP($E8,'Profil Risiko'!$I:$J,2,0),"") -> Terjadi pemadaman meluas pada sistem Batam Bintan | G8: Bila terjadi pemadaman meluas maka berpotensi kehilangan pendapatan sebesar 12,20 Sorotan stakeholder dan media yang memperburuk citra perusahaan dan kinerja operasional tidak mencapai target | H8: 12.2 | I8: 5 | K8: 0.2 | L8: 1 | N8: =1%*'Metrik Strategi Risiko'!$E$7*$I8*$K8 -> 0.0036 | O8: 20 | P8: =IFERROR(VLOOKUP($J8&$M8,Master!$V$2:$W$26,2,0),"No Data") -> No Data | Q8: High | R8: =IFERROR(VLOOKUP($J8&$M8,Master!$W$2:$Y$26,3,0),"No Data") -> No Data
D15: =IFERROR(VLOOKUP(C15,Master!$D$2:$E$50,2,0),"") | F15: =IFERROR(VLOOKUP($E15,'Profil Risiko'!$I:$J,2,0),"") | I15: 3 | N15: =1%*'Metrik Strategi Risiko'!$E$7*$I15*$K15 -> 0 | P15: =IFERROR(VLOOKUP($J15&$M15,Master!$V$2:$W$26,2,0),"No Data") -> No Data | R15: =IFERROR(VLOOKUP($J15&$M15,Master!$W$2:$Y$26,3,0),"No Data") -> No Data

Sheet Risiko Residual Kuantitatif
A1: Kembali ke Daftar Isi
A2: Data Item | B2: No. | C2: BUMN | D2: Kode BUMN | E2: No. Risiko | F2: Peristiwa risiko | G2: Target Risiko Residual
G3: Nilai Dampak | K3: Skala Dampak | S3: Nilai Probabilitas | W3: Skala Probabilitas | AE3: Eksposur Risiko | AI3: Skala Risiko | AQ3: Level Risiko
K4: BUMN | O4: KBUMN | W4: BUMN | AA4: KBUMN | AI4: BUMN | AM4: KBUMN | AQ4: BUMN | AU4: KBUMN
G5: Q1 | H5: Q2 | I5: Q3 | J5: Q4 | K5: Q1 | L5: Q2 | M5: Q3 | N5: Q4 | O5: Q1 | P5: Q2 | Q5: Q3 | R5: Q4 | S5: Q1 | T5: Q2 | U5: Q3 | V5: Q4 | W5: Q1 | X5: Q2 | Y5: Q3 | Z5: Q4 | AA5: Q1 | AB5: Q2 | AC5: Q3 | AD5: Q4 | AE5: Q1 | AF5: Q2 | AG5: Q3 | AH5: Q4 | AI5: Q1 | AJ5: Q2 | AK5: Q3 | AL5: Q4 | AM5: Q1 | AN5: Q2 | AO5: Q3 | AP5: Q4 | AQ5: Q1 | AR5: Q2 | AS5: Q3 | AT5: Q4 | AU5: Q1 | AV5: Q2 | AW5: Q3 | AX5: Q4
A6: Jenis Data | B6: Number | C6: Dropdown list | D6: Formula | E6: Number | F6: Formula | G6: Nilai full mata uang dalam Rupiah/mata uang fungsional pembukuan | K6: Dropdown list | O6: Formula | S6: % | W6: Dropdown list | AA6: Formula | AE6: Nilai full mata uang dalam Rupiah/mata uang fungsional pembukuan | AI6: Skala 1-25 | AM6: Skala 1-25 | AQ6: Free Text | AU6: Formula
A7: Petunjuk | D7: Kolom ini tidak perlu diisi. Akan diisi oleh Kementerian BUMN | E7: Diisi dengan nomor urutan risiko | F7: Diisi dengan peristiwa risiko yang ada pada tabel profil risiko | G7: Diisi dengan target perkiraan nilai dampak yang akan diterima per masing-masing triwulan dalam Rupiah atau mata uang fungsional pembukuan. | K7: Diisi dengan target skala dampak setiap triwulan | O7: Dikosongkan. Akan diisi oleh Kementerian BUMN | S7: Diisi dengan target probabilitas setiap triwulan | W7: Diisi dengan target skala probabilitas setiap triwulan | AA7: Dikosongkan. Akan diisi oleh Kementerian BUMN | AE7: Formula nilai dampak x nilai probabilitas | AI7: Diisi dengan skala Risiko BUMN yang merupakan koordinat Risiko sebagaimana acuan heatmap Kementerian BUMN pada Diagram 3 Peta Risiko (Heatmap) | AM7: Dikosongkan. Akan diisi oleh Kementerian BUMN | AQ7: Masing-masing BUMN mendefinisikan level risiko sesuai dengan skala masing-masing | AU7: Dikosongkan. Akan diisi oleh Kementerian BUMN
A8: Notes | F8: Nama peristiwa risiko harus sama persis dengan nama peristiwa risiko yang ada pada tabel profil risiko
A9: Start Pengisian | C9: PT Perusahaan Listrik Negara (Persero) | D9: =IFERROR(VLOOKUP(C9,Master!$D$2:$E$50,2,0),"") -> PLNA | E9: ='Profil Risiko'!I7 -> 1 | F9: =IFERROR(VLOOKUP($E9,'Profil Risiko'!$I:$J,2,0),"") -> Terjadi pemadaman meluas pada sistem Batam Bintan | G9: =12.2-(0%*12.2) -> 12.2 | H9: =12.2-(35%*12.2) -> 7.93 | I9: =12.2-(40%*12.2) -> 7.32 | J9: =12.2-(40%*12.2) -> 7.32 | K9: 5 | L9: 4 | M9: 4 | N9: 4 | S9: 0.1 | T9: 0.1 | U9: 0.05 | V9: 0.05 | W9: 2 | X9: 2 | Y9: 1 | Z9: 1 | AE9: =$G9*$S9 -> 1.22 | AF9: =$H9*$T9 -> 0.793 | AG9: =$I9*$U9 -> 0.366 | AH9: =$J9*$V9 -> 0.366 | AI9: 21 | AJ9: 16 | AK9: 15 | AL9: 15 | AM9: =IFERROR(VLOOKUP($O9&$AA9,Master!$V$2:$W$26,2,0),"No Data") -> No Data | AN9: =IFERROR(VLOOKUP($P9&$AB9,Master!$V$2:$W$26,2,0),"No Data") -> No Data | AO9: =IFERROR(VLOOKUP($Q9&$AC9,Master!$V$2:$W$26,2,0),"No Data") -> No Data | AP9: =IFERROR(VLOOKUP($R9&$AD9,Master!$V$2:$W$26,2,0),"No Data") -> No Data | AQ9: High | AR9: Moderat to High | AS9: Moderat | AT9: Moderat | AU9: =IFERROR(VLOOKUP($O9&$AA9,Master!$W$2:$Y$26,3,0),"No Data") -> No Data | AV9: =IFERROR(VLOOKUP($P9&$AB9,Master!$W$2:$Y$26,3,0),"No Data") -> No Data | AW9: =IFERROR(VLOOKUP($Q9&$AC9,Master!$W$2:$Y$26,3,0),"No Data") -> No Data | AX9: =IFERROR(VLOOKUP($R9&$AD9,Master!$W$2:$Y$26,3,0),"No Data") -> No Data
F10: =IFERROR(VLOOKUP($E10,'Profil Risiko'!$I:$J,2,0),"")
D14: =IFERROR(VLOOKUP(C14,Master!$D$2:$E$50,2,0),"") | F14: =IFERROR(VLOOKUP($E14,'Profil Risiko'!$I:$J,2,0),"") | AE14: =$G14*$S14 -> 0 | AF14: =$H14*$T14 -> 0 | AG14: =$I14*$U14 -> 0 | AH14: =$J14*$V14 -> 0 | AM14: =IFERROR(VLOOKUP($O14&$AA14,Master!$V$2:$W$26,2,0),"No Data") -> No Data | AN14: =IFERROR(VLOOKUP($P14&$AB14,Master!$V$2:$W$26,2,0),"No Data") -> No Data | AO14: =IFERROR(VLOOKUP($Q14&$AC14,Master!$V$2:$W$26,2,0),"No Data") -> No Data | AP14: =IFERROR(VLOOKUP($R14&$AD14,Master!$V$2:$W$26,2,0),"No Data") -> No Data | AU14: =IFERROR(VLOOKUP($O14&$AA14,Master!$W$2:$Y$26,3,0),"No Data") -> No Data | AV14: =IFERROR(VLOOKUP($P14&$AB14,Master!$W$2:$Y$26,3,0),"No Data") -> No Data | AW14: =IFERROR(VLOOKUP($Q14&$AC14,Master!$W$2:$Y$26,3,0),"No Data") -> No Data | AX14: =IFERROR(VLOOKUP($R14&$AD14,Master!$W$2:$Y$26,3,0),"No Data") -> No Data

Sheet Risiko Residual Kualitatif
A1: Kembali ke Daftar Isi
A2: Data Item | B2: No. | C2: BUMN | D2: Kode BUMN | E2: No. Risiko | F2: Peristiwa risiko | G2: Target Risiko Residual
G3: Nilai Dampak | K3: Skala Dampak | S3: Nilai Probabilitas | W3: Skala Probabilitas | AE3: Eksposur Risiko | AI3: Skala Risiko | AQ3: Level Risiko
K4: BUMN | O4: KBUMN | W4: BUMN | AA4: KBUMN | AI4: BUMN | AM4: KBUMN | AQ4: BUMN | AU4: KBUMN
G5: Q1 | H5: Q2 | I5: Q3 | J5: Q4 | K5: Q1 | L5: Q2 | M5: Q3 | N5: Q4 | O5: Q1 | P5: Q2 | Q5: Q3 | R5: Q4 | S5: Q1 | T5: Q2 | U5: Q3 | V5: Q4 | W5: Q1 | X5: Q2 | Y5: Q3 | Z5: Q4 | AA5: Q1 | AB5: Q2 | AC5: Q3 | AD5: Q4 | AE5: Q1 | AF5: Q2 | AG5: Q3 | AH5: Q4 | AI5: Q1 | AJ5: Q2 | AK5: Q3 | AL5: Q4 | AM5: Q1 | AN5: Q2 | AO5: Q3 | AP5: Q4 | AQ5: Q1 | AR5: Q2 | AS5: Q3 | AT5: Q4 | AU5: Q1 | AV5: Q2 | AW5: Q3 | AX5: Q4
A6: Jenis Data | B6: Number | C6: Dropdown list | D6: Formula | E6: Number | F6: Formula | G6: Nilai full mata uang dalam Rupiah/mata uang fungsional pembukuan | K6: Dropdown list | O6: Formula | S6: % | W6: Dropdown list | AA6: Formula | AE6: Number | AI6: Skala 1-25 | AM6: Skala 1-25 | AQ6: Free Text | AU6: Formula
A7: Petunjuk | D7: Kolom ini tidak perlu diisi. Akan diisi oleh Kementerian BUMN | E7: Diisi dengan nomor urutan risiko | F7: Diisi dengan peristiwa risiko yang ada pada tabel profil risiko | G7: Dapat dikosongkan | K7: Diisi dengan target skala dampak setiap triwulan | O7: Dikosongkan. Akan diisi oleh Kementerian BUMN | S7: Diisi dengan target probabilitas setiap triwulan | W7: Diisi dengan target skala probabilitas setiap triwulan | AA7: Dikosongkan. Akan diisi oleh Kementerian BUMN | AE7: Diisi dengan hasil perhitungan: skala Dampak x 1% Batasan Risiko yang ditetapkan dalam strategi Risiko x nilai Probabilitas (%). | AI7: Diisi dengan skala Risiko BUMN yang merupakan koordinat Risiko sebagaimana acuan heatmap Kementerian BUMN pada Diagram 3 Peta Risiko (Heatmap) | AM7: Dikosongkan. Akan diisi oleh Kementerian BUMN | AQ7: Masing-masing BUMN mendefinisikan level risiko sesuai dengan skala masing-masing | AU7: Dikosongkan. Akan diisi oleh Kementerian BUMN
A8: Notes | F8: Nama peristiwa risiko harus sama persis dengan nama peristiwa risiko yang ada pada tabel profil risiko
A9: Start Pengisian | D9: =IFERROR(VLOOKUP(C9,Master!$D$2:$E$50,2,0),"") | F9: =IFERROR(VLOOKUP($E9,'Profil Risiko'!$I:$J,2,0),"") | K9: 5 | L9: 5 | M9: 4 | N9: 4 | S9: 0.2 | T9: 0.15 | U9: 0.1 | V9: 0.05 | W9: 1 | X9: 1 | Y9: 1 | Z9: 1 | AE9: =1%*'Metrik Strategi Risiko'!$E$7*$K9*$S9 -> 0.0036 | AF9: =1%*'Metrik Strategi Risiko'!$E$7*$L9*$T9 -> 0.0027 | AG9: =1%*'Metrik Strategi Risiko'!$E$7*$M9*$U9 -> 0.00144 | AH9: =1%*'Metrik Strategi Risiko'!$E$7*$N9*$V9 -> 0.00072 | AI9: {=INDEX($AI$24:$AM$28,W9,K9)} -> 0 | AJ9: {=INDEX($AI$24:$AM$28,X9,L9)} -> 0 | AK9: {=INDEX($AI$24:$AM$28,Y9,M9)} -> 0 | AL9: {=INDEX($AI$24:$AM$28,Z9,N9)} -> 0 | AM9: =IFERROR(VLOOKUP($O9&$AA9,Master!$V$2:$W$26,2,0),"No Data") -> No Data | AN9: =IFERROR(VLOOKUP($P9&$AB9,Master!$V$2:$W$26,2,0),"No Data") -> No Data | AO9: =IFERROR(VLOOKUP($Q9&$AC9,Master!$V$2:$W$26,2,0),"No Data") -> No Data | AP9: =IFERROR(VLOOKUP($R9&$AD9,Master!$V$2:$W$26,2,0),"No Data") -> No Data | AQ9: High | AR9: High | AS9: High | AT9: High | AU9: =IFERROR(VLOOKUP($O9&$AA9,Master!$W$2:$Y$26,3,0),"No Data") -> No Data | AV9: =IFERROR(VLOOKUP($P9&$AB9,Master!$W$2:$Y$26,3,0),"No Data") -> No Data | AW9: =IFERROR(VLOOKUP($Q9&$AC9,Master!$W$2:$Y$26,3,0),"No Data") -> No Data | AX9: =IFERROR(VLOOKUP($R9&$AD9,Master!$W$2:$Y$26,3,0),"No Data") -> No Data
D12: =IFERROR(VLOOKUP(C12,Master!$D$2:$E$50,2,0),"") | F12: =IFERROR(VLOOKUP($E12,'Profil Risiko'!$I:$J,2,0),"") | AE12: =1%*'Metrik Strategi Risiko'!$E$7*$K12*$S12 -> 0 | AF12: =1%*'Metrik Strategi Risiko'!$E$7*$L12*$T12 -> 0 | AG12: =1%*'Metrik Strategi Risiko'!$E$7*$M12*$U12 -> 0 | AH12: =1%*'Metrik Strategi Risiko'!$E$7*$N12*$V12 -> 0 | AM12: =IFERROR(VLOOKUP($O12&$AA12,Master!$V$2:$W$26,2,0),"No Data") -> No Data | AN12: =IFERROR(VLOOKUP($P12&$AB12,Master!$V$2:$W$26,2,0),"No Data") -> No Data | AO12: =IFERROR(VLOOKUP($Q12&$AC12,Master!$V$2:$W$26,2,0),"No Data") -> No Data | AP12: =IFERROR(VLOOKUP($R12&$AD12,Master!$V$2:$W$26,2,0),"No Data") -> No Data | AU12: =IFERROR(VLOOKUP($O12&$AA12,Master!$W$2:$Y$26,3,0),"No Data") -> No Data | AV12: =IFERROR(VLOOKUP($P12&$AB12,Master!$W$2:$Y$26,3,0),"No Data") -> No Data | AW12: =IFERROR(VLOOKUP($Q12&$AC12,Master!$W$2:$Y$26,3,0),"No Data") -> No Data | AX12: =IFERROR(VLOOKUP($R12&$AD12,Master!$W$2:$Y$26,3,0),"No Data") -> No Data

Sheet Heatmap
A1: Kembali ke Daftar Isi
AE2: 1 | AF2: =AE2+1 -> 2 | AG2: =AF2+1 -> 3 | AH2: =AG2+1 -> 4 | AI2: =AH2+1 -> 5 | AJ2: =AI2+1 -> 6 | AK2: =AJ2+1 -> 7 | AL2: =AK2+1 -> 8 | AM2: =AL2+1 -> 9 | ... AR2: =AQ2+1 -> 14
B3: TINGKAT KEMUNGKINAN | C3: Hampir Pasti Terjadi | D3: 5 | E3: Low to Moderate 7 | J3: Moderate 12 | O3: Moderate to High 17 | T3: High 22 | Y3: High 25 | AE3: No. | AF3: Risk Event | AG3: Inherent Risk | AM3: Residual Risk
AG4: BUMN | AJ4: KBUMN | AM4: BUMN | AP4: KBUMN
AG5: Impact | AH5: Likelihood | AI5: Level | AJ5: Impact | AK5: Likelihood | AL5: Level | AM5: Impact | AN5: Likelihood | AO5: Level | AP5: Impact | AQ5: Likelihood | AR5: Level
AE6: 1
AE7: =AE6+1 -> 2
C8: Sangat Mungkin Terjadi | D8: 4 | E8: Low 4 | J8: Low to Moderate 9 | O8: Moderate 14 | T8: Moderate to High 19 | Y8: High 24 | AE8: =AE7+1 -> 3
AE9: =AE8+1 -> 4
AE10: =AE9+1 -> 5
C13: Bisa Terjadi | D13: 3 | E13: Low 3 | J13: Low to Moderate 8 | O13: Moderate 13 | T13: Moderate to High 18 | Y13: High 23
C18: Jarang Terjadi | D18: 2 | E18: Low 2 | J18: Low to Moderate 6 | O18: Low to Moderate 11 | T18: Moderate to High 16 | Y18: High 21
C23: Sangat Jarang Terjadi | D23: 1 | E23: Low 1 | J23: Low 5 | O23: Low to Moderate 10 | T23: Moderate 15 | Y23: High 20
E28: 1 | J28: 2 | O28: 3 | T28: 4 | Y28: 5
E29: Sangat Rendah | J29: Rendah | O29: Moderat | T29: Tinggi | Y29: Sangat Tinggi
E30: TINGKAT DAMPAK

Sheet LAP REAL III.A
A1: Kembali ke Daftar Isi
A2: Kembali Bab III
A3: Lampiran III.A. Format Tabel Realisasi Risiko Residual Triwulanan dan Tahunan
A4: Data Item | B4: Realisasi Residual Risk | AE4: Efektifitas Perlakuan Risiko
B5: Asumsi Perhitungan Dampak | C5: Nilai Dampak | G5: Skala Dampak | K5: Nilai Probabilitas | O5: Skala Probabilitas | S5: Nilai Eksposur Risiko | W5: Skala Nilai Risiko | AA5: Level Risiko
G6: BUMN | O6: BUMN | W6: BUMN | AA6: BUMN
C7: Q1 | D7: Q2 | E7: Q3 | F7: Q4 | G7: Q1 | H7: Q2 | I7: Q3 | J7: Q4 | K7: Q1 | L7: Q2 | M7: Q3 | N7: Q4 | O7: Q1 | P7: Q2 | Q7: Q3 | R7: Q4 | S7: Q1 | T7: Q2 | U7: Q3 | V7: Q4 | W7: Q1 | X7: Q2 | Y7: Q3 | Z7: Q4 | AA7: Q1 | AB7: Q2 | AC7: Q3 | AD7: Q4
A8: Jenis Data | B8: Free Text | C8: Nilai mata uang dalam Rupiah/USD | G8: Dropdown list | K8: % | O8: Dropdown list | S8: Nilai dalam mata uang rupiah Rupiah/USD | W8: Skala 1-25 | AA8: Free Text | AE8: Dropdown list
A9: Petunjuk | B9: BUMN agar menambahkan juga penjelasan atas asumsi/pendekatan yang dipakai untuk menghitung nilai dampak. | C9: Agar diisikan dengan realisasi perkiraan nilai dampak yang akan diterima per masing-masing quarter dalam 1 tahun, baik dalam Rupiah atau currency lainnya. Apabila nilai dampak bersifat kualitatif, maka kolom ini dapat diisikan dengan "0" | G9: Masing-masing BUMN mendefinisikan skala 1-5 sesuai dengan skala masing-masing | K9: Agar BUMN mengisikan nilai probabilitas atas suatu risiko tersebut. Adapun, nilai probabilitas tersebut bisa bersifat nilai tengah dari suatu range | O9: Masing-masing BUMN mendefinisikan skala 1-5 sesuai dengan skala masing-masing | S9: Formula nilai dampak x nilai probabilitas | W9: Diisi dengan skala nilai Risiko BUMN yang merupakan koordinat Risiko sebagaimana acuan heatmap Kementerian BUMN pada Diagram III.C Peta Risiko (Heatmap) | AA9: Diisi dengan pewarnaan risiko sesuai Diagram III.C Peta Risiko (Heatmap) berdasarkan Skala Nilai Risiko BUMN | AE9: Efektivitas perlakuan risiko merupakan kombinasi dari ketepatan waktu & kemampuan dalam menurunkan nilai eksposur risiko
A10: Notes | G10: Atas dampak yang bersifat kualitatif, agar dapat dilakuan average | AE10: Apabila Realisasi Skala Nilai Risiko BUMN <= Skala Nilai Risiko BUMN pada Nilai Target Residual Risk, maka Perlakuan Risiko bersifat Efektif. Apabila Realisasi Skala Nilai Risiko BUMN > Skala Nilai Risiko BUMN pada Nilai Target Residual Risk, maka Perlakuan Risiko bersifat Tidak Efektif
A11: Start pengisian | G11: 3 | H11: 4 | I11: 2 | J11: 5 | O11: 5 | P11: 1 | Q11: 2 | R11: 5 | S11: =$C11*$K11 -> 0 | T11: =$D11*$L11 -> 0 | U11: =$E11*$M11 -> 0 | V11: =$F11*$N11 -> 0 | W11: =INDEX(Source!$E$33:$I$37,MATCH(O11,Source!$D$33:$D$37,0),MATCH(G11,Source!$E$38:$I$38,0)) -> 17 | X11: =INDEX(Source!$E$33:$I$37,MATCH(P11,Source!$D$33:$D$37,0),MATCH(H11,Source!$E$38:$I$38,0)) -> 15 | Y11: =INDEX(Source!$E$33:$I$37,MATCH(Q11,Source!$D$33:$D$37,0),MATCH(I11,Source!$E$38:$I$38,0)) -> 6 | Z11: =INDEX(Source!$E$33:$I$37,MATCH(R11,Source!$D$33:$D$37,0),MATCH(J11,Source!$E$38:$I$38,0)) -> 25 | AA11: =LOOKUP(MATCH(W11,'Perhitungan Heatmap'!$D$9:$AB$9),'Perhitungan Heatmap'!$D$9:$AB$9,'Perhitungan Heatmap'!$D$10:$AB$10) -> Moderate To High | AB11: =LOOKUP(MATCH(X11,'Perhitungan Heatmap'!$D$9:$AB$9),'Perhitungan Heatmap'!$D$9:$AB$9,'Perhitungan Heatmap'!$D$10:$AB$10) -> Moderate | AC11: =LOOKUP(MATCH(Y11,'Perhitungan Heatmap'!$D$9:$AB$9),'Perhitungan Heatmap'!$D$9:$AB$9,'Perhitungan Heatmap'!$D$10:$AB$10) -> Low To Moderate | AD11: =LOOKUP(MATCH(Z11,'Perhitungan Heatmap'!$D$9:$AB$9),'Perhitungan Heatmap'!$D$9:$AB$9,'Perhitungan Heatmap'!$D$10:$AB$10) -> High
A12: 1 | B12: =IFERROR(INDEX(SUMMARY!$AC$10:$AC$22,MATCH('LAP REAL III.A'!A12,SUMMARY!$L$10:$L$22,0)),"") -> Dari nilai tukar rupiah terhadap kurs untuk pembayaran biaya operasional dan beban bunga perusahaan | S12: =$C12*$K12 -> 0 | T12: =$D12*$L12 -> 0 | U12: =$E12*$M12 -> 0 | V12: =$F12*$N12 -> 0 | W12: =INDEX(Source!$E$33:$I$37,MATCH(O12,Source!$D$33:$D$37,0),MATCH(G12,Source!$E$38:$I$38,0)) -> #N/A | X12: =INDEX(Source!$E$33:$I$37,MATCH(P12,Source!$D$33:$D$37,0),MATCH(H12,Source!$E$38:$I$38,0)) -> #N/A | Y12: =INDEX(Source!$E$33:$I$37,MATCH(Q12,Source!$D$33:$D$37,0),MATCH(I12,Source!$E$38:$I$38,0)) -> #N/A | Z12: =INDEX(Source!$E$33:$I$37,MATCH(R12,Source!$D$33:$D$37,0),MATCH(J12,Source!$E$38:$I$38,0)) -> #N/A | AA12: =LOOKUP(MATCH(W12,'Perhitungan Heatmap'!$D$9:$AB$9),'Perhitungan Heatmap'!$D$9:$AB$9,'Perhitungan Heatmap'!$D$10:$AB$10) -> #N/A | AB12: =LOOKUP(MATCH(X12,'Perhitungan Heatmap'!$D$9:$AB$9),'Perhitungan Heatmap'!$D$9:$AB$9,'Perhitungan Heatmap'!$D$10:$AB$10) -> #N/A | AC12: =LOOKUP(MATCH(Y12,'Perhitungan Heatmap'!$D$9:$AB$9),'Perhitungan Heatmap'!$D$9:$AB$9,'Perhitungan Heatmap'!$D$10:$AB$10) -> #N/A | AD12: =LOOKUP(MATCH(Z12,'Perhitungan Heatmap'!$D$9:$AB$9),'Perhitungan Heatmap'!$D$9:$AB$9,'Perhitungan Heatmap'!$D$10:$AB$10) -> #N/A
S13: =$C13*$K13 -> 0 | T13: =$D13*$L13 -> 0 | U13: =$E13*$M13 -> 0 | V13: =$F13*$N13 -> 0 | W13: =INDEX(Source!$E$33:$I$37,MATCH(O13,Source!$D$33:$D$37,0),MATCH(G13,Source!$E$38:$I$38,0)) -> #N/A | X13: =INDEX(Source!$E$33:$I$37,MATCH(P13,Source!$D$33:$D$37,0),MATCH(H13,Source!$E$38:$I$38,0)) -> #N/A | Y13: =INDEX(Source!$E$33:$I$37,MATCH(Q13,Source!$D$33:$D$37,0),MATCH(I13,Source!$E$38:$I$38,0)) -> #N/A | Z13: =INDEX(Source!$E$33:$I$37,MATCH(R13,Source!$D$33:$D$37,0),MATCH(J13,Source!$E$38:$I$38,0)) -> #N/A | AA13: =LOOKUP(MATCH(W13,'Perhitungan Heatmap'!$D$9:$AB$9),'Perhitungan Heatmap'!$D$9:$AB$9,'Perhitungan Heatmap'!$D$10:$AB$10) -> #N/A | AB13: =LOOKUP(MATCH(X13,'Perhitungan Heatmap'!$D$9:$AB$9),'Perhitungan Heatmap'!$D$9:$AB$9,'Perhitungan Heatmap'!$D$10:$AB$10) -> #N/A | AC13: =LOOKUP(MATCH(Y13,'Perhitungan Heatmap'!$D$9:$AB$9),'Perhitungan Heatmap'!$D$9:$AB$9,'Perhitungan Heatmap'!$D$10:$AB$10) -> #N/A | AD13: =LOOKUP(MATCH(Z13,'Perhitungan Heatmap'!$D$9:$AB$9),'Perhitungan Heatmap'!$D$9:$AB$9,'Perhitungan Heatmap'!$D$10:$AB$10) -> #N/A
S14: =$C14*$K14 -> 0 | T14: =$D14*$L14 -> 0 | U14: =$E14*$M14 -> 0 | V14: =$F14*$N14 -> 0 | W14: =INDEX(Source!$E$33:$I$37,MATCH(O14,Source!$D$33:$D$37,0),MATCH(G14,Source!$E$38:$I$38,0)) -> #N/A | X14: =INDEX(Source!$E$33:$I$37,MATCH(P14,Source!$D$33:$D$37,0),MATCH(H14,Source!$E$38:$I$38,0)) -> #N/A | Y14: =INDEX(Source!$E$33:$I$37,MATCH(Q14,Source!$D$33:$D$37,0),MATCH(I14,Source!$E$38:$I$38,0)) -> #N/A | Z14: =INDEX(Source!$E$33:$I$37,MATCH(R14,Source!$D$33:$D$37,0),MATCH(J14,Source!$E$38:$I$38,0)) -> #N/A | AA14: =LOOKUP(MATCH(W14,'Perhitungan Heatmap'!$D$9:$AB$9),'Perhitungan Heatmap'!$D$9:$AB$9,'Perhitungan Heatmap'!$D$10:$AB$10) -> #N/A | AB14: =LOOKUP(MATCH(X14,'Perhitungan Heatmap'!$D$9:$AB$9),'Perhitungan Heatmap'!$D$9:$AB$9,'Perhitungan Heatmap'!$D$10:$AB$10) -> #N/A | AC14: =LOOKUP(MATCH(Y14,'Perhitungan Heatmap'!$D$9:$AB$9),'Perhitungan Heatmap'!$D$9:$AB$9,'Perhitungan Heatmap'!$D$10:$AB$10) -> #N/A | AD14: =LOOKUP(MATCH(Z14,'Perhitungan Heatmap'!$D$9:$AB$9),'Perhitungan Heatmap'!$D$9:$AB$9,'Perhitungan Heatmap'!$D$10:$AB$10) -> #N/A
S15: =$C15*$K15 -> 0 | T15: =$D15*$L15 -> 0 | U15: =$E15*$M15 -> 0 | V15: =$F15*$N15 -> 0 | W15: =INDEX(Source!$E$33:$I$37,MATCH(O15,Source!$D$33:$D$37,0),MATCH(G15,Source!$E$38:$I$38,0)) -> #N/A | X15: =INDEX(Source!$E$33:$I$37,MATCH(P15,Source!$D$33:$D$37,0),MATCH(H15,Source!$E$38:$I$38,0)) -> #N/A | Y15: =INDEX(Source!$E$33:$I$37,MATCH(Q15,Source!$D$33:$D$37,0),MATCH(I15,Source!$E$38:$I$38,0)) -> #N/A | Z15: =INDEX(Source!$E$33:$I$37,MATCH(R15,Source!$D$33:$D$37,0),MATCH(J15,Source!$E$38:$I$38,0)) -> #N/A | AA15: =LOOKUP(MATCH(W15,'Perhitungan Heatmap'!$D$9:$AB$9),'Perhitungan Heatmap'!$D$9:$AB$9,'Perhitungan Heatmap'!$D$10:$AB$10) -> #N/A | AB15: =LOOKUP(MATCH(X15,'Perhitungan Heatmap'!$D$9:$AB$9),'Perhitungan Heatmap'!$D$9:$AB$9,'Perhitungan Heatmap'!$D$10:$AB$10) -> #N/A | AC15: =LOOKUP(MATCH(Y15,'Perhitungan Heatmap'!$D$9:$AB$9),'Perhitungan Heatmap'!$D$9:$AB$9,'Perhitungan Heatmap'!$D$10:$AB$10) -> #N/A | AD15: =LOOKUP(MATCH(Z15,'Perhitungan Heatmap'!$D$9:$AB$9),'Perhitungan Heatmap'!$D$9:$AB$9,'Perhitungan Heatmap'!$D$10:$AB$10) -> #N/A
S16: =$C16*$K16 -> 0 | T16: =$D16*$L16 -> 0 | U16: =$E16*$M16 -> 0 | V16: =$F16*$N16 -> 0 | W16: =INDEX(Source!$E$33:$I$37,MATCH(O16,Source!$D$33:$D$37,0),MATCH(G16,Source!$E$38:$I$38,0)) -> #N/A | X16: =INDEX(Source!$E$33:$I$37,MATCH(P16,Source!$D$33:$D$37,0),MATCH(H16,Source!$E$38:$I$38,0)) -> #N/A | Y16: =INDEX(Source!$E$33:$I$37,MATCH(Q16,Source!$D$33:$D$37,0),MATCH(I16,Source!$E$38:$I$38,0)) -> #N/A | Z16: =INDEX(Source!$E$33:$I$37,MATCH(R16,Source!$D$33:$D$37,0),MATCH(J16,Source!$E$38:$I$38,0)) -> #N/A | AA16: =LOOKUP(MATCH(W16,'Perhitungan Heatmap'!$D$9:$AB$9),'Perhitungan Heatmap'!$D$9:$AB$9,'Perhitungan Heatmap'!$D$10:$AB$10) -> #N/A | AB16: =LOOKUP(MATCH(X16,'Perhitungan Heatmap'!$D$9:$AB$9),'Perhitungan Heatmap'!$D$9:$AB$9,'Perhitungan Heatmap'!$D$10:$AB$10) -> #N/A | AC16: =LOOKUP(MATCH(Y16,'Perhitungan Heatmap'!$D$9:$AB$9),'Perhitungan Heatmap'!$D$9:$AB$9,'Perhitungan Heatmap'!$D$10:$AB$10) -> #N/A | AD16: =LOOKUP(MATCH(Z16,'Perhitungan Heatmap'!$D$9:$AB$9),'Perhitungan Heatmap'!$D$9:$AB$9,'Perhitungan Heatmap'!$D$10:$AB$10) -> #N/A
A17: Start pengisian | S17: =$C17*$K17 -> 0 | T17: =$D17*$L17 -> 0 | U17: =$E17*$M17 -> 0 | V17: =$F17*$N17 -> 0 | W17: =INDEX(Source!$E$33:$I$37,MATCH(O17,Source!$D$33:$D$37,0),MATCH(G17,Source!$E$38:$I$38,0)) -> #N/A | X17: =INDEX(Source!$E$33:$I$37,MATCH(P17,Source!$D$33:$D$37,0),MATCH(H17,Source!$E$38:$I$38,0)) -> #N/A | Y17: =INDEX(Source!$E$33:$I$37,MATCH(Q17,Source!$D$33:$D$37,0),MATCH(I17,Source!$E$38:$I$38,0)) -> #N/A | Z17: =INDEX(Source!$E$33:$I$37,MATCH(R17,Source!$D$33:$D$37,0),MATCH(J17,Source!$E$38:$I$38,0)) -> #N/A | AA17: =LOOKUP(MATCH(W17,'Perhitungan Heatmap'!$D$9:$AB$9),'Perhitungan Heatmap'!$D$9:$AB$9,'Perhitungan Heatmap'!$D$10:$AB$10) -> #N/A | AB17: =LOOKUP(MATCH(X17,'Perhitungan Heatmap'!$D$9:$AB$9),'Perhitungan Heatmap'!$D$9:$AB$9,'Perhitungan Heatmap'!$D$10:$AB$10) -> #N/A | AC17: =LOOKUP(MATCH(Y17,'Perhitungan Heatmap'!$D$9:$AB$9),'Perhitungan Heatmap'!$D$9:$AB$9,'Perhitungan Heatmap'!$D$10:$AB$10) -> #N/A | AD17: =LOOKUP(MATCH(Z17,'Perhitungan Heatmap'!$D$9:$AB$9),'Perhitungan Heatmap'!$D$9:$AB$9,'Perhitungan Heatmap'!$D$10:$AB$10) -> #N/A

Sheet LAP REAL III.B
A1: Kembali ke Daftar Isi
A2: Kembali Bab III
A3: Lampiran III.B. Format Tabel Realisasi Pelaksanaan Perlakuan Risiko dan Biaya
A4: Data Item | B4: Realisasi Rencana Perlakuan Risiko | C4: Realisasi Output atas masing-masing Breakdown Perlakuan Risiko | D4: Realisasi Biaya Perlakuan Risiko (Rp/USD) | E4: Persentase Serapan Biaya | F4: Realisasi PIC | G4: Realisasi Timeline | S4: Key Risk Indicators | T4: Realisasi Threshold KRI | V4: Status Rencana Perlakuan Risiko | W4: Penjelasan Status Rencana Perlakuan | X4: Progress Pelaksanaan Rencana Perlakuan
G6: 1 | H6: =G6+1 -> 2 | I6: =H6+1 -> 3 | J6: =I6+1 -> 4 | K6: =J6+1 -> 5 | L6: =K6+1 -> 6 | M6: =L6+1 -> 7 | N6: =M6+1 -> 8 | O6: =N6+1 -> 9 | ... R6: =Q6+1 -> 12 | T6: Threshold | U6: Skor | X6: Q1 | Y6: Q2 | Z6: Q3 | AA6: Q4
A7: Jenis Data | B7: Free Text | C7: Free Text | D7: Nilai mata uang dalam Rupiah/USD | E7: Formula | F7: Free Text | G7: Numerik (diisi nilai 1 jika mitigasi dilakukan pada bulan tertentu) | S7: Formula | T7: Dropdown List | U7: Free Text/Ratio/Number | V7: Dropdown List | W7: Free Text | X7: Formula
A8: Petunjuk | B8: BUMN agar mengisikan realisasi rencana perlakuan risiko yang telah dijalankan | C8: BUMN agar mengisikan realisasi output atas masing-masing rencana perlakuan risiko yang relevan | D8: Terhadap masing-masing perlakuan risiko agar diisikan juga atas realisasi biaya perlakuan risikonya. Harap diberikan keterangan satuan mata uang yang digunakan | E8: Diisi dengan rumus Realisasi Biaya Perlakuan Risiko dibagi Rencana Biaya Perlakuan Risiko | F8: Unit penanggung jawab perlakuan risiko setingkat BOD | G8: Terhadap masing-masing perlakuan risiko per penyebab risiko, BUMN agar mengisikan timeline realisasi implementasinya. Apabila perlakuan risiko berlangsung sepanjang tahun, maka timeline harus diisi setiap bulan | S8: Sebagaimana sebuah risiko memiliki suatu indikator, maka BUMN diharapkan untuk mengisikan indikator yang relevan | T8: Realisasi threshold KRI merupakan realisasi atas KRI yang mengacu kepada kategori threshold KRI | V8: Agar setiap rencana perlakuan risiko diberikan status terhadap implementasinya, yaitu: - Discontinue: Apabila rencana perlakuan risiko tidak dapat diimplementasikan/tidak dapat memitigasi penyebab risiko yang ada/hanya berlaku pada periode tertentu - Revisi: Apabila rencana perlakuan risiko digantikan dengan rencana perlakuan risiko yang lainnya - Continue: Apabila rencana perlakuan risiko masih bersifat on the track/on progress | W8: Apabila rencana perlakuan risiko bersifat discontinue atau revisi, harap diberikan penjelasannya | X8: Terhadap masing-masing perlakuan risiko yang sudah direncanakan, BUMN agar mengisikan progress pelaksanaan rencana perlakuan.
A9: Notes | S9: Setiap top risk item dapat memiliki lebih dari satu KRI
A10: Start pengisian

Sheet RAS

Sheet Kriteria Dampak & Prob.
A1: Kembali ke Daftar Isi
A2: KRITERIA DAMPAK DAN PROBABILITAS
A4: A. | B4: Kriteria Dampak Kuantitatif | F4: Risk Limit | G4: 0.61 | H4: Triliyun | J4: =G4*1000 -> 610 | K4: Milyar
B5: Skala | C5: Kriteria Dampak | D5: Range Dampak Finansial | E5: Deskripsi Dampak
B6: 1 | C6: Sangat Rendah | D6: X ≤ 20% dari Batasan Risiko | E6: Dampak sangat rendah yang dapat mengakibatkan kerusakan/ kerugian/ penurunan kurang dari 20% dari nilai Batasan Risiko
F7: 0 | G7: 0.2 | H7: =G7*$G$4 -> 0.122 | J7: =H7*1000 -> 122
B8: 2 | C8: Rendah | D8: 20% < X ≤ 40% dari Batasan Risiko | E8: Dampak rendah yang dapat mengakibatkan kerusakan/kerugian/penurunan 20% < X ≤ 40% dari nilai Batasan Risiko
F9: =H7 -> 0.122 | G9: 0.4 | H9: =G9*$G$4 -> 0.244 | J9: =H9*1000 -> 244
B10: 3 | C10: Moderat | D10: 40% < X ≤ 60% dari Batasan Risiko | E10: Dampak kritis yang dapat mengakibatkan kerusakan/kerugian/penurunan 40% < X ≤ 60% dari nilai Batasan Risiko
F11: =H9 -> 0.244 | G11: 0.6 | H11: =G11*$G$4 -> 0.366 | J11: =H11*1000 -> 366
B12: 4 | C12: Tinggi | D12: 60% < X ≤ 80% dari Batasan Risiko | E12: Dampak disruptif yang dapat mengakibatkan kerusakan/ kerugian/ penurunan 40% < X ≤ 60% dari nilai Batasan Risiko
F13: =H11 -> 0.366 | G13: 0.8 | H13: =G13*$G$4 -> 0.488 | J13: =H13*1000 -> 488
B14: 5 | C14: Sangat Tinggi | D14: X > 80% dari Batasan Risiko | E14: Dampak katastrofe yang dapat mengakibatkan kerusakan/ kerugian/ penurunan > 80% dari nilai Batasan Risiko
F15: =H13 -> 0.488 | G15: 1 | H15: =G15*$G$4 -> 0.61 | J15: =H15*1000 -> 610
B16: Keterangan:
B17: Nilai Batasan Risiko merupakan nilai Risk Limit di level enterprise sebagaimana yang telah ditetapkan dalam Strategi Risiko BUMN.
A20: B. | B20: Kriteria Dampak Kualitatif
B21: Risiko Kualitatif | C21: Skala
C22: 1 | D22: 2 | E22: 3 | F22: 4 | G22: 5
C23: Sangat Rendah | D23: Rendah | E23: Moderat | F23: Tinggi | G23: Sangat Tinggi
B24: Risiko Strategis
B25: Dampak keterlambatan pencapaian program strategis | C25: Minimal 1 parameter target strategis yang harus selesai pada tahun ini tertunda kurang dari 1 bulan | D25: Minimal 1 parameter tujuan strategis yang harus selesai pada tahun ini tertunda antara 2 - 3 bulan | E25: Minimal 1 parameter tujuan strategis yang harus selesai pada tahun ini tertunda antara 3 - 6 bulan | F25: Minimal 1 parameter tujuan strategis yang harus selesai pada tahun ini tertunda antara 6 - 9 bulan | G25: Minimal 1 parameter tujuan strategis yang harus selesai pada tahun ini tertunda lebih dari 9 bulan
B26: Risiko Hukum
B27: Pelanggaran hukum | C27: Tidak ada somasi/ tuntutan hukum | D27: Perusahaan mendapat somasi. | E27: Perusahaan mendapat tuntutan hukum. | F27: Perusahaan diputuskan kalah di pengadilan tingkat pertama. | G27: Perusahaan diputuskan kalah di pengadilan tingkat selanjutnya.
B28: Risiko Kepatuhan
B29: Pelanggaran ketentuan kepatuhan | C29: Teguran informal / verbal. | D29: Diminta bertemu dengan pihak Regulator (misalkan OJK, Bank Indonesia, IDX, Kementerian terkait, Dirjen Pajak, dan lain-lain) | E29: Peringatan tertulis / formal, terkena denda. | F29: Regulator memberlaku-kan pembatasan dan / atau pembekuan terhadap aktivitas operasional / produk / jasa tertentu. | G29: Regulator memberlaku-kan sanksi signifikan (misalkan delisting saham, tidak diperkenan-kan mengikuti kliring, menarik produk yang beredar, dan lain-lain)
B30: Risiko Reputasi
B31: Keluhan pelanggan / nasabah / pembeli / supplier | C31: Keluhan yang terisolasi dan dapat ditangani dalam 1 hari kerja | D31: Keluhan yang terisolasi dan dapat diselesaikan dalam 3 hari kerja | E31: Keluhan yang menyebar ke skala sektoral dan / atau diajukan secara kolektif yang dapat diselesaikan dalam waktu 7 hari kerja dan masih berada dalam kewenangan Pimpinan Cabang / Wilayah | F31: Keluhan yang menyebar ke skala nasional dan / atau diajukan secara kolektif yang dapat diselesaikan dalam waktu 10 hari kerja dan / atau memerlukan penanganan kewenangan Kantor Pusat | G31: Keluhan yang menyebar ke skala nasional / internasional dan / atau diajukan secara kolektif yang diselesaikan melebihi 10 hari kerja dan / atau memerlukan penanganan kewenangan Kantor Pusat
B32: Pemberitaan negatif di media | C32: Publikasi negatif yg terisolasi di wilayah sektoral melalui media konvensional (misalkan Radio lokal, TV lokal, Surat Kabar daerah) | D32: Publikasi negatif yang lintas sektoral / wilayah / provinsi namun masih tersebar media konvensional. | E32: Publikasi negatif skala nasional yang tersebar di media konvensional | F32: Publikasi negatif mencapai skala nasional yang tersebar di sosial media dan / atau memerlukan penanganan kewenangan Kantor Pusat | G32: Publikasi negatif mencapai skala internasional yang tersebar di sosial media dan / atau memerlukan penanganan kewenangan Kantor Pusat
B33: Kehilangan daya saing | C33: Penurunan pangsa pasar sampai dengan 5% | D33: Penurunan pangsa pasar antara 5% sampai dengan 10% | E33: Penurunan pangsa pasar antara 10% sampai dengan 15% | F33: Penurunan pangsa pasar antara 15% sampai dengan 20% | G33: Penurunan pangsa pasar lebih dari 20%
B34: Risiko Sumber Daya Manusia
B35: Keluhan karyawan | C35: Terdapat keluhan karyawan yang disalurkan sampai tingkat SP Unit namun dapat diisolir dan diselesaikan oleh Pemimpin Unit | D35: Terdapat keluhan karyawan yang perlu diselesaikan oleh Penyelia Pemimpin Unit | E35: Terdapat keluhan yang disalurkan mencapai tingkat sektoral / wilayah / provinsi. | F35: Unjuk rasa karyawan yang mengganggu aktivitas perusahaan dan / atau disertai terjadinya cedera serius / cacat permanen | G35: Demonstrasi terkoordinasi, terjadinya kematian karyawan saat kerja
B36: Turn over karyawan bertalenta | C36: Turn over pegawai bertalenta kurang dari 1% setahun | D36: Turn over pegawai bertalenta dari 1% sampai dengan 5% setahun | E36: Turn over pegawai bertalenta antara 5% sampai dengan 10% setahun | F36: Turn over pegawai bertalenta antara 10% sampai dengan 15% setahun | G36: Turn over pegawai bertalenta >15% setahun
B37: (regretted turnover)
B38: Risiko Sistem Infrastruktur Teknologi dan Keamanan Siber
B39: Gangguan aplikasi infrastruktur pendukung | C39: Aplikasi & Infrastruktur pendukung yang kurang penting tidak berfungsi selama 1 hari | D39: Aplikasi dan Infrastruktur pendukung yang kurang penting tidak berfungsi selama lebih dari 1 hari s/d 3 hari | E39: Infrastruktur vital yang penting tidak berfungsi selama < 1 jam (misalkan Listrik, air, jaringan komunikasi & online system) | F39: Infrastruktur vital yang penting tidak berfungsi selama 2 s/d 6 jam (misalkan Listrik, air, jaringan komunikasi & online system) | G39: Infrastruktur vital yang penting tidak berfungsi selama lebih dari 6 jam (misalkan Listrik, air, jaringan komunikasi & online system)
B40: Serangan siber | C40: Jumlah rata-rata serangan siber per minggu di bawah 50 kali | D40: Jumlah rata-rata serangan siber per minggu 50-99 kali | E40: Jumlah rata-rata serangan siber per minggu 100-199 kali | F40: Jumlah rata-rata serangan siber per minggu 200-500 kali | G40: Jumlah rata-rata serangan siber per minggu lebih dari 500 kali
B41: Hasil penilaian platform security | C41: X > 90% | D41: 90% ≥ X > 80% | E41: 80 % ≥ X > 70% | F41: 70% ≥ X > 60% | G41: X ≤ 60%
B42: Risiko Operasional
